Workbook

Sheet Instructions
A2: How to use this template builder | G2: Instructions (clickon each step to find the tab to fill in)
B3: Tab group | C3: Included tabs to be filled out | G3: 1. Identify the location you are targeting for the templates and enter details in the Country_description tab
A4: Tabs groups to fill out | B4: Building_loads | C4: Building features, Schedules, Building loads, etc. | G4: 2. Identify different internal gains packages and create regonizable names.
B5: HVAC | C5: Heating, Cooling, Ventilation, DHW | G5: 3. Identify types of HVAC systems you want in the templates and fill out corresponding values.
B6: Construction | C6: Roof, Walls, Windows, etc. | G6: 4. Identify types of ventilation systems you want in the templates
B7: Building retrofits | C7: Retrofit package design | G7: 5. Identify types of DHW systems you want in the templates and fill out corresponding values.
G8: 6. Create HVAC and DHW packages from your constructions
G9: 7. Generate constructions based on the provided material lists for different building components
G10: 8. Add together constructions to create a full envelope assembly, and assign a name to each assembly
A11: Guidance/Calculation tabs (no action needed) | B11: Materials_choices | G11: 9. (OPTIONAL) Assign retrofit packages to each "template" for different internal components
B12: Drop_downs
B13: Units
B14: Material_assembly_generator
B15: Schedule_choices | G15: General guidance
B16: Constructions_assmebly | G16: Follow the instructions in the green highlighted text in each tab
B17: HVAC_options | G17: Legend
H18: Fill out this tab
H19: Support tab
A20: Ready to upload to website? | B20: Save this excel and send to MIT team for next steps | H20: Fill in
H21: Drop down options

Sheet Country_description
A1: Fill out here general information about the building stock for the location you are working on
A2: Parameter | B2: Value | C2: Guidance
A3: Location_type | B3: City | C3: Enter the type of location you are considering for this template assignment | O3: description for Seoul, Korea
A4: Location_name | B4: Seoul | C4: Share the name of the region in English | O4: Overview Seoul, the capital of the Republic of Korea, is one of the most densely developed cities in the country and contains a large and highly heterogeneous building stock composed of both residential and non-residential buildings. The current building stock has been shaped by rapid urbanization, large-scale housing supply programs, and repeated cycles of redevelopment and reconstruction. Pronounced differences exist between central and peripheral districts, as well as between low-rise residential neighborhoods and large apartment complexes, resulting in substantial variation in building age, construction type, and energy use characteristics. Average Costs Building asset values in Seoul are among the highest in South Korea and vary significantly by location and building use. Residential buildings—particularly apartment complexes—exhibit high unit prices, while non-residential buildings such as office, commercial, and hospitality facilities show wide variation in construction costs and asset values depending on size, function, and location. Overall, Seoul’s building stock is characterized by high development density and relatively high operating cost burdens due to land scarcity and intensive urban use. Construction Types (in order of commonality) Residential Buildings • Multi-family Housing (Apartments) Apartments are the dominant residential building type in Seoul. These buildings are typically mid- to high-rise reinforced concrete structures, often exceeding five stories, and were largely constructed during major housing supply waves beginning in the 1990s. • Single-Family Homes Despite the prominence of apartment living, single-family homes account for a very large share of the total building count in Seoul. These buildings are typically low-rise and consist of a mix of masonry and reinforced concrete structures. Many are relatively old and exhibit low energy performance. • Low-rise Multi-family Housing (Row houses and small apartment buildings) These buildings are generally two to five stories tall and are widely distributed throughout residential districts. While individually small, they constitute a significant portion of Seoul’s residential building stock. Non-residential Buildings (Based on the 19-category building classification framework provided in the project dataset) • Neighborhood Living Facilities (Type 1 and 2) These are the most widely distributed non-residential buildings in Seoul by count. Typically low- to mid-rise reinforced concrete structures, they are commonly mixed with residential uses and form the backbone of everyday urban activity. • Office Buildings Office buildings are concentrated in central business districts and sub-centers and are generally mid- to high-rise reinforced concrete or composite structures. Cooling and ventilation loads dominate their energy use. • Educational Facilities Schools and research buildings are typically large-scale, long-life structures with relatively stable occupancy patterns. • Medical Facilities Hospitals and related facilities are characterized by continuous operation and high dependence on mechanical systems. • Retail, Accommodation, and Cultural/Assembly Facilities These buildings support commercial, tourism, and cultural activities and tend to exhibit high energy use intensities and strong temporal variability in occupancy and loads. Construction History Across both residential and non-residential sectors, reinforced concrete construction overwhelmingly dominates Seoul’s building stock. This reflects historical priorities related to fire safety, durability, and the need for high-density development. Buildings constructed prior to the 1980s generally lack meaningful thermal insulation, and many single-family homes and low-rise neighborhood facilities from this period exhibit particularly poor envelope performance. Beginning in the early 2000s, the introduction and subsequent strengthening of the Building Energy Conservation Design Standards led to the systematic application of minimum thermal and system efficiency requirements across residential, office, educational, retail, and other non-residential buildings. As a result, year of construction has become a key proxy for energy performance within Seoul’s building stock. Average Age and Renovation Cycles The average age of buildings in Seoul is approximately 30 years, with a high proportion of aging structures in both residential and non-residential categories. Residential buildings typically undergo interior renovations and system upgrades every 15–30 years, while non-residential buildings experience more frequent partial renovations driven by tenant turnover, functional changes, and regulatory requirements. Major structural changes are often implemented through redevelopment or reconstruction rather than incremental retrofits. Heating and HVAC Equipment Residential • Natural Gas Boilers: The most common heating system • District Heating: Predominantly used in large apartment complexes • Electric or Oil-based Systems: Limited to specific cases, often in older single-family homes Non-residential • Central boilers and chillers: Common in office, medical, and educational buildings • Packaged and split HVAC systems: Widely used in neighborhood living facilities and small commercial buildings • VAV / CAV systems: Typical in large office and public buildings Compared to residential buildings, non-residential buildings in Seoul exhibit significantly higher cooling, ventilation, and electricity-driven loads. Energy Cost Environment Seoul operates under the national electricity and gas pricing structure of South Korea. Historically, natural gas prices have remained relatively low and stable, making gas-based heating systems economically attractive across both residential and non-residential buildings. This has led to a strong lock-in of gas and district heating systems within the existing building stock. More recently, rising electricity prices and energy transition policies have increased interest in electrified systems such as heat pumps. However, widespread adoption in existing buildings remains constrained by economic, technical, and structural barriers.
A5: Location_primary_language | B5: Korean | C5: Share the primary language spoken in this location in English
A6: Location_description | B6: Overview 서울특별시는 대한민국에서 가장 고밀도로 개발된 도시로, 주거·비주거 건물이 혼재된 대규모 건물 스톡을 보유하고 있다. 건물들은 급격한 도시 확장과 재개발·재건축 과정을 거치며 형성되었고, 건설 시기와 용도에 따른 이질성이 매우 큰 것이 특징이다. 도심부와 외곽 지역, 그리고 저층 주거 밀집지와 대규모 아파트 단지 간에는 건축 연식, 구조 형식, 에너지 사용 특성에서 뚜렷한 차이가 존재한다. Average Costs 서울의 건물 자산 가치는 대한민국 내에서 가장 높은 수준을 보이며, 입지와 용도에 따라 큰 편차를 가진다. 주거용 건물은 특히 아파트 단지를 중심으로 높은 단가가 형성되어 있으며, 비주거 건물 또한 업무시설, 판매시설, 숙박시설 등 용도에 따라 연면적당 건설비와 자산 가치가 크게 달라진다. 고밀 개발과 토지 희소성으로 인해, 서울의 건물 스톡은 전반적으로 높은 집약도와 높은 운영비 부담 구조를 가진다. Construction Types (in order of commonality) Residential Buildings • 공동주택 (아파트) 서울에서 가장 대표적인 주거 유형으로, 주로 5층 이상 중·고층 철근콘크리트 구조이다. 대규모 단지 형태로 조성되었으며, 1990년대 이후 집중적으로 공급되었다. • 단독주택 서울 주거 건물 중 절대적인 동(棟) 수 비중이 매우 높은 유형으로, 주로 저층이며 조적조 또는 철근콘크리트 구조가 혼재한다. 연식이 길고 에너지 성능이 낮은 건물이 다수를 차지한다. • 다가구·다세대주택 2 ~ 5층 규모의 저층 공동주택으로, 주거지역 전반에 널리 분포한다. 아파트에 비해 개별 건물 규모는 작으나, 도시 주거 스톡에서 중요한 비중을 차지한다. Non-residential Buildings (빌딩분류타입 엑셀의 19개 비주거 유형 체계를 전제로 함) • 근린생활시설 (제1·2종) 서울 전역에 가장 광범위하게 분포한 비주거 유형으로, 저층 또는 중층 철근콘크리트 구조가 일반적이다. 주거와 혼합된 형태로 존재하며 건물 수 기준 비중이 매우 높다. • 업무시설 도심 및 부도심을 중심으로 분포하며, 중·고층 철근콘크리트 또는 철골 구조가 일반적이다. 냉방 및 환기 부하가 지배적인 건물군이다. • 교육시설 학교 및 연구시설로 구성되며, 비교적 대규모 부지와 장수명 구조를 가진다. • 의료시설 병원 및 관련 시설로 구성되며, 연중 상시 운영과 높은 설비 의존도를 특징으로 한다. • 판매시설·숙박시설·문화·집회시설 상업 및 관광 기능을 담당하며, 이용 패턴의 변동성이 크고 에너지 사용 밀도가 높은 경향을 보인다. Construction History 서울의 건물은 주거·비주거를 막론하고 철근콘크리트 구조가 지배적이다. 이는 화재 안전, 내구성, 고밀 개발 요구에 따른 결과이다. 1980년대 이전에 건설된 건물은 단열 기준이 거의 적용되지 않았으며, 단독주택과 저층 근린생활시설을 중심으로 외피 성능이 매우 취약하다. 2000년대 이후 「건축물의 에너지절약설계기준」의 도입과 개정을 통해, 주거뿐 아니라 업무시설, 교육시설, 판매시설 등 비주거 건물에도 외피 및 설비 성능 기준이 단계적으로 적용되었다. 이로 인해 건축 연식은 서울 건물 스톡에서 에너지 성능을 설명하는 핵심 변수로 작용한다. Average Age and Renovation Cycles 서울의 건물 평균 연식은 약 30년 내외로, 주거용과 비주거용 모두 노후 건물 비율이 높다. 주거 건물은 15 ~ 30년 주기로 내부 리모델링 및 설비 교체가 이루어지며, 비주거 건물은 임차인 교체 및 용도 변경에 따라 부분적인 개보수가 반복적으로 수행된다. 대규모 구조 변경은 재건축·재개발 사업을 통해 이루어지는 경우가 많다. Heating and HVAC Equipment Residential • 도시가스 보일러: 가장 보편적인 난방 방식 • 지역난방: 대규모 아파트 단지 중심 • 전기·기름 보일러: 일부 노후 단독주택 및 특수 사례 Non-residential • 중앙식 보일러 및 냉동기 시스템: 업무·의료·교육시설 • 개별 냉난방 및 패키지 공조기: 근린생활시설, 소규모 업무시설 • VAV / CAV 시스템: 대형 업무 및 공공건물 비주거 건물은 주거 건물에 비해 냉방, 환기, 전력 부하의 비중이 높다. Energy Cost Environment 서울은 대한민국의 전력·가스 요금 체계를 그대로 적용받으며, 장기간 도시가스 기반 난방이 경제적으로 유리한 환경을 유지해 왔다. 이로 인해 주거·비주거 모두에서 가스 기반 난방 시스템이 널리 보급되었다. 최근에는 전기요금 변동성과 에너지 전환 정책의 영향으로 전기 기반 설비의 도입 가능성이 확대되고 있으나, 기존 건물 스톡에서는 여전히 가스 및 지역난방 의존도가 높다. | C6: Share a detailed description of the historical context of the building stock. This should include details around construction history, energy price environments, policies, etc. An Example is shared here for Massachusetts
A7: Location_description_translated | B7: As noted next to it | C7: Translated version of the description into primary language
A8: Existing_GIS_data_link | C8: OPTIONAL: Location of GIS data for 3d building footprints
A9: Bibliography | C9: OPTIONAL: List of sources used as reference for all the information in this excel

Sheet Mapping>>

Sheet component_options
A1: Region | B1: Typology | C1: Age_bracket | D1: AtticVentilation | F1: RoofInsulation | G1: AtticFloorInsulation | H1: BasementCeilingInsulation | I1: BasementWallsInsulation | J1: BasementFloorInsulation | K1: Weatherization | L1: Wall | M1: Windows | N1: Heating | O1: Cooling | P1: Distribution | Q1: DHW | R1: Equipment | S1: Lighting | T1: Thermostat
A2: MA | B2: SFH | C2: pre_1975 | D2: UnventilatedAttic | F2: UninsulatedRoof | G2: UninsulatedFloor | H2: UninsulatedCeiling | I2: UninsulatedWalls | J2: UninsulatedGroundSlab | K2: LeakyEnvelope | L2: UninsulatedWalls | M2: SinglePane | N2: ElectricResistance | O2: ACWindow | P2: Steam | Q2: ElectricResistanceDHW | R2: LowEfficiencyEquipment | S2: NoLED | T2: NoControls
B3: MFH | C3: btw_1975_2003 | D3: VentilatedAttic | F3: LimitedInsulationRoof | G3: LimitedInsulationFloor | H3: InsulatedCeiling | I3: InsulatedWalls | J3: InsulatedGroundSlab | K3: SomewhatLeakyEnvelope | L3: SomeInsulationWalls | M3: SinglePaneStormWindows | N3: OilHeating | O3: ACCentral | P3: HotWaterUninsulated | Q3: NaturalGasDHW | R3: HighEfficiencyEquipment | S3: LED | T3: Controls
C4: post_2003 | F4: HighlyInsulatedRoof | G4: HighlyInsulatedFloor | K4: TightEnvelope | L4: SIP | M4: DoublePaneLowE | N4: NaturalGasHeating | O4: WindowASHP | P4: AirDuctsUninsulated | Q4: NaturalGasHeatingDHWCombo
L5: FullInsulationWallsCavity | M5: TriplePaneLowE | N5: NaturalGasCondensingHeating | O5: ASHPCooling | P5: AirDuctsConditionedUninsulated | Q5: HPWH
L6: FullInsulationWallsCavityExterior | N6: ASHPHeating | O6: GSHPCooling | P6: HotWaterInsulated
N7: GSHPHeating | P7: AirDuctsInsulated

Sheet mapping
A1: Components | B1: Region | C1: Typology | D1: Age_bracket | E1: AtticVentilation | F1: RoofInsulation | G1: AtticFloorInsulation | H1: BasementCeilingInsulation | I1: BasementWallsInsulation | J1: BasementFloorInsulation | K1: Weatherization | L1: Wall | M1: Windows | N1: Heating | O1: Cooling | P1: Distribution | Q1: DHW | R1: Equipment | S1: Thermostat | T1: Lighting
A2: Space_use_assembly
A3: Occupancy | B3: Y | C3: Y
A4: Lighting | B4: Y | C4: Y | T4: Y
A5: Power | B5: Y | C5: Y | R5: Y
A6: Thermostat | B6: Y | S6: Y
A7: Water_flow | B7: Y | C7: Y
A8: Systems_assembly | B8: Y | C8: Y | N8: Y | O8: Y | P8: Y | Q8: Y
A9: Conditioning_constructor | B9: Y | N9: Y | O9: Y | P9: Y
A10: Heating | B10: Y | N10: Y | P10: Y
A11: Cooling | B11: Y | O11: Y | P11: Y
A12: Ventilation_constructor | B12: Y | C12: Y | K12: Y
A13: DHW_constructor | B13: Y | C13: Y | Q13: Y
A14: Envelope_assembly
A15: Construction_assembly
A16: FlatRoof | B16: Y | C16: Y | D16: Y | F16: Y
A17: AtticRoof | B17: Y | C17: Y | D17: Y | F17: Y
A18: AtticFloor | B18: Y | C18: Y | G18: Y
A19: Facade | B19: Y | C19: Y | D19: Y | L19: Y
A20: Partition | B20: Y | C20: Y
A21: GroundWall | B21: Y | C21: Y | I21: Y
A22: GroundSlab | B22: Y | C22: Y | J22: Y
A23: BasementCeiling | B23: Y | C23: Y | H23: Y
A24: FloorCeiling | B24: Y | C24: Y
A25: Window | B25: Y | C25: Y | M25: Y
A26: Infiltration | B26: Y | C26: Y | K26: Y
A27: AtticInfiltration | B27: Y | C27: Y | E27: Y | K27: Y
A28: ExternalFloor | B28: Y | C28: Y

Sheet generated_mapping
A1: This is the autogenerated set of labels for each of the tags. Please use these as your chosen labels when going through and assigning names and values
A2: Space_use_assembly | B2: Occupancy | C2: Lighting | D2: Power | E2: Setpoints | F2: Water_flow | G2: Systems_assembly | H2: Conditioning_constructor | I2: Heating | J2: Cooling | K2: Ventilation_constructor | L2: DHW_constructor | M2: Envelope_assembly | N2: Construction_components | O2: Roof | P2: Walls | Q2: Partition | R2: GroundWalls | S2: Slab | T2: Window | U2: Infiltration
A3: MA_SFH_Low_efficiency_equipment_NoControls_NoLED | B3: MA_SFH | C3: MA_SFH_NoLED | D3: MA_SFH_Low_efficiency_equipment | E3: MA_NoControls | F3: MA_SFH | G3: MA_SFH_Electric_resistance_AC_window_Steam_Electric_resistance_DHW | H3: MA_Electric_resistance_AC_window_Steam | I3: Electric_resistance_Steam | J3: AC_window_Steam | K3: MA_SFH | L3: MA_Electric_resistance_DHW | M3: MA_SFH_pre_1975_Occupied_uninsulated_Leaky_envelope_Uninsulated_walls_Single_pane | N3: MA_SFH_pre_1975_Occupied_uninsulated | O3: MA_SFH_Occupied_uninsulated | P3: MA_pre_1975_Uninsulated_walls | Q3: MA_pre_1975 | R3: MA_pre_1975 | S3: MA_pre_1975 | T3: MA_Single_pane | U3: MA_Leaky_envelope
A4: MA_SFH_Low_efficiency_equipment_NoControls_LED | B4: MA_MFH | C4: MA_SFH_LED | D4: MA_SFH_EnergyStar_equipment | E4: MA_Controls | F4: MA_MFH | G4: MA_SFH_Electric_resistance_AC_window_Steam_NG_DHW | H4: MA_Electric_resistance_AC_window_Hot_water_uninsulated | I4: Electric_resistance_Hot_water_uninsulated | J4: AC_window_Hot_water_uninsulated | K4: MA_MFH | L4: MA_NG_DHW | M4: MA_SFH_pre_1975_Occupied_uninsulated_Leaky_envelope_Uninsulated_walls_Single_pane_storm_windows | N4: MA_SFH_pre_1975_Unoccupied_uninsulated_floor | O4: MA_SFH_Unoccupied_uninsulated_floor | P4: MA_pre_1975_Some_wall_insulation | Q4: MA_btw_1975_2003 | R4: MA_btw_1975_2003 | S4: MA_btw_1975_2003 | T4: MA_Single_pane_storm_windows | U4: MA_Somewhat_leaky_envelope
A5: MA_SFH_Low_efficiency_equipment_Controls_NoLED | C5: MA_MFH_NoLED | D5: MA_MFH_Low_efficiency_equipment | G5: MA_SFH_Electric_resistance_AC_window_Steam_Heating_DHW_combo_NG | H5: MA_Electric_resistance_AC_window_Air_ducts_uninsulated | I5: Electric_resistance_Air_ducts_uninsulated | J5: AC_window_Air_ducts_uninsulated | L5: MA_Heating_DHW_combo_NG | M5: MA_SFH_pre_1975_Occupied_uninsulated_Leaky_envelope_Uninsulated_walls_Double_pane_lowE | N5: MA_SFH_pre_1975_Unoccupied_insulated_floor | O5: MA_SFH_Unoccupied_insulated_floor | P5: MA_pre_1975_SIP | Q5: MA_post_2003 | R5: MA_post_2003 | S5: MA_post_2003 | T5: MA_Double_pane_lowE | U5: MA_Tight_envelope_HRV
A6: MA_SFH_Low_efficiency_equipment_Controls_LED | C6: MA_MFH_LED | D6: MA_MFH_EnergyStar_equipment | G6: MA_SFH_Electric_resistance_AC_window_Steam_HPWH | H6: MA_Electric_resistance_AC_window_Air_ducts_conditioned_uninsulated | I6: Electric_resistance_Air_ducts_conditioned_uninsulated | J6: AC_window_Air_ducts_conditioned_uninsulated | L6: MA_HPWH | M6: MA_SFH_pre_1975_Occupied_uninsulated_Leaky_envelope_Uninsulated_walls_Triple_pane_lowE | N6: MA_SFH_pre_1975_Limited_insulation_roof | O6: MA_SFH_Limited_insulation_roof | P6: MA_pre_1975_Full_insulated_wall_cavity | T6: MA_Triple_pane_lowE
A7: MA_SFH_EnergyStar_equipment_NoControls_NoLED | G7: MA_SFH_Electric_resistance_AC_window_Hot_water_uninsulated_Electric_resistance_DHW | H7: MA_Electric_resistance_AC_window_Hot_water_insulated | I7: Electric_resistance_Hot_water_insulated | J7: AC_window_Hot_water_insulated | M7: MA_SFH_pre_1975_Occupied_uninsulated_Leaky_envelope_Some_wall_insulation_Single_pane | N7: MA_SFH_pre_1975_Insulation_roof | O7: MA_SFH_Insulation_roof | P7: MA_pre_1975_Full_insulated_wall_cavity_exterior
A8: MA_SFH_EnergyStar_equipment_NoControls_LED | G8: MA_SFH_Electric_resistance_AC_window_Hot_water_uninsulated_NG_DHW | H8: MA_Electric_resistance_AC_window_Air_ducts_insulated | I8: Electric_resistance_Air_ducts_insulated | J8: AC_window_Air_ducts_insulated | M8: MA_SFH_pre_1975_Occupied_uninsulated_Leaky_envelope_Some_wall_insulation_Single_pane_storm_windows | N8: MA_SFH_pre_1975_Occupied_insulated | O8: MA_SFH_Occupied_insulated | P8: MA_btw_1975_2003_Uninsulated_walls
A9: MA_SFH_EnergyStar_equipment_Controls_NoLED | G9: MA_SFH_Electric_resistance_AC_window_Hot_water_uninsulated_Heating_DHW_combo_NG | H9: MA_Electric_resistance_Central_AC_Steam | I9: Oil_heating_Steam | J9: Central_AC_Steam | M9: MA_SFH_pre_1975_Occupied_uninsulated_Leaky_envelope_Some_wall_insulation_Double_pane_lowE | N9: MA_SFH_pre_1975_Unoccupied_high_insulated_floor | O9: MA_SFH_Unoccupied_high_insulated_floor | P9: MA_btw_1975_2003_Some_wall_insulation
A10: MA_SFH_EnergyStar_equipment_Controls_LED | G10: MA_SFH_Electric_resistance_AC_window_Hot_water_uninsulated_HPWH | H10: MA_Electric_resistance_Central_AC_Hot_water_uninsulated | I10: Oil_heating_Hot_water_uninsulated | J10: Central_AC_Hot_water_uninsulated | M10: MA_SFH_pre_1975_Occupied_uninsulated_Leaky_envelope_Some_wall_insulation_Triple_pane_lowE | N10: MA_SFH_btw_1975_2003_Occupied_uninsulated | O10: MA_MFH_Occupied_uninsulated | P10: MA_btw_1975_2003_SIP
A11: MA_MFH_Low_efficiency_equipment_NoControls_NoLED | G11: MA_SFH_Electric_resistance_AC_window_Air_ducts_uninsulated_Electric_resistance_DHW | H11: MA_Electric_resistance_Central_AC_Air_ducts_uninsulated | I11: Oil_heating_Air_ducts_uninsulated | J11: Central_AC_Air_ducts_uninsulated | M11: MA_SFH_pre_1975_Occupied_uninsulated_Leaky_envelope_SIP_Single_pane | N11: MA_SFH_btw_1975_2003_Unoccupied_uninsulated_floor | O11: MA_MFH_Unoccupied_uninsulated_floor | P11: MA_btw_1975_2003_Full_insulated_wall_cavity
A12: MA_MFH_Low_efficiency_equipment_NoControls_LED | G12: MA_SFH_Electric_resistance_AC_window_Air_ducts_uninsulated_NG_DHW | H12: MA_Electric_resistance_Central_AC_Air_ducts_conditioned_uninsulated | I12: Oil_heating_Air_ducts_conditioned_uninsulated | J12: Central_AC_Air_ducts_conditioned_uninsulated | M12: MA_SFH_pre_1975_Occupied_uninsulated_Leaky_envelope_SIP_Single_pane_storm_windows | N12: MA_SFH_btw_1975_2003_Unoccupied_insulated_floor | O12: MA_MFH_Unoccupied_insulated_floor | P12: MA_btw_1975_2003_Full_insulated_wall_cavity_exterior
A13: MA_MFH_Low_efficiency_equipment_Controls_NoLED | G13: MA_SFH_Electric_resistance_AC_window_Air_ducts_uninsulated_Heating_DHW_combo_NG | H13: MA_Electric_resistance_Central_AC_Hot_water_insulated | I13: Oil_heating_Hot_water_insulated | J13: Central_AC_Hot_water_insulated | M13: MA_SFH_pre_1975_Occupied_uninsulated_Leaky_envelope_SIP_Double_pane_lowE | N13: MA_SFH_btw_1975_2003_Limited_insulation_roof | O13: MA_MFH_Limited_insulation_roof | P13: MA_post_2003_Uninsulated_walls
A14: MA_MFH_Low_efficiency_equipment_Controls_LED | G14: MA_SFH_Electric_resistance_AC_window_Air_ducts_uninsulated_HPWH | H14: MA_Electric_resistance_Central_AC_Air_ducts_insulated | I14: Oil_heating_Air_ducts_insulated | J14: Central_AC_Air_ducts_insulated | M14: MA_SFH_pre_1975_Occupied_uninsulated_Leaky_envelope_SIP_Triple_pane_lowE | N14: MA_SFH_btw_1975_2003_Insulation_roof | O14: MA_MFH_Insulation_roof | P14: MA_post_2003_Some_wall_insulation
A15: MA_MFH_EnergyStar_equipment_NoControls_NoLED | G15: MA_SFH_Electric_resistance_AC_window_Air_ducts_conditioned_uninsulated_Electric_resistance_DHW | H15: MA_Electric_resistance_Natural_ventilation_Steam | I15: NG_heating_Steam | J15: Natural_ventilation_Steam | M15: MA_SFH_pre_1975_Occupied_uninsulated_Leaky_envelope_Full_insulated_wall_cavity_Single_pane | N15: MA_SFH_btw_1975_2003_Occupied_insulated | O15: MA_MFH_Occupied_insulated | P15: MA_post_2003_SIP
A16: MA_MFH_EnergyStar_equipment_NoControls_LED | G16: MA_SFH_Electric_resistance_AC_window_Air_ducts_conditioned_uninsulated_NG_DHW | H16: MA_Electric_resistance_Natural_ventilation_Hot_water_uninsulated | I16: NG_heating_Hot_water_uninsulated | J16: Natural_ventilation_Hot_water_uninsulated | M16: MA_SFH_pre_1975_Occupied_uninsulated_Leaky_envelope_Full_insulated_wall_cavity_Single_pane_storm_windows | N16: MA_SFH_btw_1975_2003_Unoccupied_high_insulated_floor | O16: MA_MFH_Unoccupied_high_insulated_floor | P16: MA_post_2003_Full_insulated_wall_cavity
A17: MA_MFH_EnergyStar_equipment_Controls_NoLED | G17: MA_SFH_Electric_resistance_AC_window_Air_ducts_conditioned_uninsulated_Heating_DHW_combo_NG | H17: MA_Electric_resistance_Natural_ventilation_Air_ducts_uninsulated | I17: NG_heating_Air_ducts_uninsulated | J17: Natural_ventilation_Air_ducts_uninsulated | M17: MA_SFH_pre_1975_Occupied_uninsulated_Leaky_envelope_Full_insulated_wall_cavity_Double_pane_lowE | N17: MA_SFH_post_2003_Occupied_uninsulated | P17: MA_post_2003_Full_insulated_wall_cavity_exterior
A18: MA_MFH_EnergyStar_equipment_Controls_LED | G18: MA_SFH_Electric_resistance_AC_window_Air_ducts_conditioned_uninsulated_HPWH | H18: MA_Electric_resistance_Natural_ventilation_Air_ducts_conditioned_uninsulated | I18: NG_heating_Air_ducts_conditioned_uninsulated | J18: Natural_ventilation_Air_ducts_conditioned_uninsulated | M18: MA_SFH_pre_1975_Occupied_uninsulated_Leaky_envelope_Full_insulated_wall_cavity_Triple_pane_lowE | N18: MA_SFH_post_2003_Unoccupied_uninsulated_floor
G19: MA_SFH_Electric_resistance_AC_window_Hot_water_insulated_Electric_resistance_DHW | H19: MA_Electric_resistance_Natural_ventilation_Hot_water_insulated | I19: NG_heating_Hot_water_insulated | J19: Natural_ventilation_Hot_water_insulated | M19: MA_SFH_pre_1975_Occupied_uninsulated_Leaky_envelope_Full_insulated_wall_cavity_exterior_Single_pane | N19: MA_SFH_post_2003_Unoccupied_insulated_floor
G20: MA_SFH_Electric_resistance_AC_window_Hot_water_insulated_NG_DHW | H20: MA_Electric_resistance_Natural_ventilation_Air_ducts_insulated | I20: NG_heating_Air_ducts_insulated | J20: Natural_ventilation_Air_ducts_insulated | M20: MA_SFH_pre_1975_Occupied_uninsulated_Leaky_envelope_Full_insulated_wall_cavity_exterior_Single_pane_storm_windows | N20: MA_SFH_post_2003_Limited_insulation_roof
G21: MA_SFH_Electric_resistance_AC_window_Hot_water_insulated_Heating_DHW_combo_NG | H21: MA_Electric_resistance_Window_ASHP_Steam | I21: NG_condensing_heating_Steam | J21: Window_ASHP_Steam | M21: MA_SFH_pre_1975_Occupied_uninsulated_Leaky_envelope_Full_insulated_wall_cavity_exterior_Double_pane_lowE | N21: MA_SFH_post_2003_Insulation_roof
G22: MA_SFH_Electric_resistance_AC_window_Hot_water_insulated_HPWH | H22: MA_Electric_resistance_Window_ASHP_Hot_water_uninsulated | I22: NG_condensing_heating_Hot_water_uninsulated | J22: Window_ASHP_Hot_water_uninsulated | M22: MA_SFH_pre_1975_Occupied_uninsulated_Leaky_envelope_Full_insulated_wall_cavity_exterior_Triple_pane_lowE | N22: MA_SFH_post_2003_Occupied_insulated
G23: MA_SFH_Electric_resistance_AC_window_Air_ducts_insulated_Electric_resistance_DHW | H23: MA_Electric_resistance_Window_ASHP_Air_ducts_uninsulated | I23: NG_condensing_heating_Air_ducts_uninsulated | J23: Window_ASHP_Air_ducts_uninsulated | M23: MA_SFH_pre_1975_Occupied_uninsulated_Somewhat_leaky_envelope_Uninsulated_walls_Single_pane | N23: MA_SFH_post_2003_Unoccupied_high_insulated_floor
G24: MA_SFH_Electric_resistance_AC_window_Air_ducts_insulated_NG_DHW | H24: MA_Electric_resistance_Window_ASHP_Air_ducts_conditioned_uninsulated | I24: NG_condensing_heating_Air_ducts_conditioned_uninsulated | J24: Window_ASHP_Air_ducts_conditioned_uninsulated | M24: MA_SFH_pre_1975_Occupied_uninsulated_Somewhat_leaky_envelope_Uninsulated_walls_Single_pane_storm_windows | N24: MA_MFH_pre_1975_Occupied_uninsulated
G25: MA_SFH_Electric_resistance_AC_window_Air_ducts_insulated_Heating_DHW_combo_NG | H25: MA_Electric_resistance_Window_ASHP_Hot_water_insulated | I25: NG_condensing_heating_Hot_water_insulated | J25: Window_ASHP_Hot_water_insulated | M25: MA_SFH_pre_1975_Occupied_uninsulated_Somewhat_leaky_envelope_Uninsulated_walls_Double_pane_lowE | N25: MA_MFH_pre_1975_Unoccupied_uninsulated_floor
G26: MA_SFH_Electric_resistance_AC_window_Air_ducts_insulated_HPWH | H26: MA_Electric_resistance_Window_ASHP_Air_ducts_insulated | I26: NG_condensing_heating_Air_ducts_insulated | J26: Window_ASHP_Air_ducts_insulated | M26: MA_SFH_pre_1975_Occupied_uninsulated_Somewhat_leaky_envelope_Uninsulated_walls_Triple_pane_lowE | N26: MA_MFH_pre_1975_Unoccupied_insulated_floor
G27: MA_SFH_Electric_resistance_Central_AC_Steam_Electric_resistance_DHW | H27: MA_Electric_resistance_ASHP_Steam | I27: ASHP_Steam | J27: ASHP_Steam | M27: MA_SFH_pre_1975_Occupied_uninsulated_Somewhat_leaky_envelope_Some_wall_insulation_Single_pane | N27: MA_MFH_pre_1975_Limited_insulation_roof
G28: MA_SFH_Electric_resistance_Central_AC_Steam_NG_DHW | H28: MA_Electric_resistance_ASHP_Hot_water_uninsulated | I28: ASHP_Hot_water_uninsulated | J28: ASHP_Hot_water_uninsulated | M28: MA_SFH_pre_1975_Occupied_uninsulated_Somewhat_leaky_envelope_Some_wall_insulation_Single_pane_storm_windows | N28: MA_MFH_pre_1975_Insulation_roof
G29: MA_SFH_Electric_resistance_Central_AC_Steam_Heating_DHW_combo_NG | H29: MA_Electric_resistance_ASHP_Air_ducts_uninsulated | I29: ASHP_Air_ducts_uninsulated | J29: ASHP_Air_ducts_uninsulated | M29: MA_SFH_pre_1975_Occupied_uninsulated_Somewhat_leaky_envelope_Some_wall_insulation_Double_pane_lowE | N29: MA_MFH_pre_1975_Occupied_insulated
G30: MA_SFH_Electric_resistance_Central_AC_Steam_HPWH | H30: MA_Electric_resistance_ASHP_Air_ducts_conditioned_uninsulated | I30: ASHP_Air_ducts_conditioned_uninsulated | J30: ASHP_Air_ducts_conditioned_uninsulated | M30: MA_SFH_pre_1975_Occupied_uninsulated_Somewhat_leaky_envelope_Some_wall_insulation_Triple_pane_lowE | N30: MA_MFH_pre_1975_Unoccupied_high_insulated_floor
... G38: MA_SFH_Electric_resistance_Central_AC_Air_ducts_uninsulated_HPWH | H38: MA_Electric_resistance_GSHP_Air_ducts_insulated | I38: GSHP_Air_ducts_insulated | J38: GSHP_Air_ducts_insulated | M38: MA_SFH_pre_1975_Occupied_uninsulated_Somewhat_leaky_envelope_Full_insulated_wall_cavity_Triple_pane_lowE | N38: MA_MFH_post_2003_Occupied_uninsulated
G39: MA_SFH_Electric_resistance_Central_AC_Air_ducts_conditioned_uninsulated_Electric_resistance_DHW | H39: MA_Oil_heating_AC_window_Steam | M39: MA_SFH_pre_1975_Occupied_uninsulated_Somewhat_leaky_envelope_Full_insulated_wall_cavity_exterior_Single_pane | N39: MA_MFH_post_2003_Unoccupied_uninsulated_floor
G40: MA_SFH_Electric_resistance_Central_AC_Air_ducts_conditioned_uninsulated_NG_DHW | H40: MA_Oil_heating_AC_window_Hot_water_uninsulated | M40: MA_SFH_pre_1975_Occupied_uninsulated_Somewhat_leaky_envelope_Full_insulated_wall_cavity_exterior_Single_pane_storm_windows | N40: MA_MFH_post_2003_Unoccupied_insulated_floor
G41: MA_SFH_Electric_resistance_Central_AC_Air_ducts_conditioned_uninsulated_Heating_DHW_combo_NG | H41: MA_Oil_heating_AC_window_Air_ducts_uninsulated | M41: MA_SFH_pre_1975_Occupied_uninsulated_Somewhat_leaky_envelope_Full_insulated_wall_cavity_exterior_Double_pane_lowE | N41: MA_MFH_post_2003_Limited_insulation_roof
G42: MA_SFH_Electric_resistance_Central_AC_Air_ducts_conditioned_uninsulated_HPWH | H42: MA_Oil_heating_AC_window_Air_ducts_conditioned_uninsulated | M42: MA_SFH_pre_1975_Occupied_uninsulated_Somewhat_leaky_envelope_Full_insulated_wall_cavity_exterior_Triple_pane_lowE | N42: MA_MFH_post_2003_Insulation_roof
G43: MA_SFH_Electric_resistance_Central_AC_Hot_water_insulated_Electric_resistance_DHW | H43: MA_Oil_heating_AC_window_Hot_water_insulated | M43: MA_SFH_pre_1975_Occupied_uninsulated_Tight_envelope_HRV_Uninsulated_walls_Single_pane | N43: MA_MFH_post_2003_Occupied_insulated
G44: MA_SFH_Electric_resistance_Central_AC_Hot_water_insulated_NG_DHW | H44: MA_Oil_heating_AC_window_Air_ducts_insulated | M44: MA_SFH_pre_1975_Occupied_uninsulated_Tight_envelope_HRV_Uninsulated_walls_Single_pane_storm_windows | N44: MA_MFH_post_2003_Unoccupied_high_insulated_floor
G45: MA_SFH_Electric_resistance_Central_AC_Hot_water_insulated_Heating_DHW_combo_NG | H45: MA_Oil_heating_Central_AC_Steam | M45: MA_SFH_pre_1975_Occupied_uninsulated_Tight_envelope_HRV_Uninsulated_walls_Double_pane_lowE
G46: MA_SFH_Electric_resistance_Central_AC_Hot_water_insulated_HPWH | H46: MA_Oil_heating_Central_AC_Hot_water_uninsulated | M46: MA_SFH_pre_1975_Occupied_uninsulated_Tight_envelope_HRV_Uninsulated_walls_Triple_pane_lowE
G47: MA_SFH_Electric_resistance_Central_AC_Air_ducts_insulated_Electric_resistance_DHW | H47: MA_Oil_heating_Central_AC_Air_ducts_uninsulated | M47: MA_SFH_pre_1975_Occupied_uninsulated_Tight_envelope_HRV_Some_wall_insulation_Single_pane
G48: MA_SFH_Electric_resistance_Central_AC_Air_ducts_insulated_NG_DHW | H48: MA_Oil_heating_Central_AC_Air_ducts_conditioned_uninsulated | M48: MA_SFH_pre_1975_Occupied_uninsulated_Tight_envelope_HRV_Some_wall_insulation_Single_pane_storm_windows
G49: MA_SFH_Electric_resistance_Central_AC_Air_ducts_insulated_Heating_DHW_combo_NG | H49: MA_Oil_heating_Central_AC_Hot_water_insulated | M49: MA_SFH_pre_1975_Occupied_uninsulated_Tight_envelope_HRV_Some_wall_insulation_Double_pane_lowE
G50: MA_SFH_Electric_resistance_Central_AC_Air_ducts_insulated_HPWH | H50: MA_Oil_heating_Central_AC_Air_ducts_insulated | M50: MA_SFH_pre_1975_Occupied_uninsulated_Tight_envelope_HRV_Some_wall_insulation_Triple_pane_lowE
G51: MA_SFH_Electric_resistance_Natural_ventilation_Steam_Electric_resistance_DHW | H51: MA_Oil_heating_Natural_ventilation_Steam | M51: MA_SFH_pre_1975_Occupied_uninsulated_Tight_envelope_HRV_SIP_Single_pane
G52: MA_SFH_Electric_resistance_Natural_ventilation_Steam_NG_DHW | H52: MA_Oil_heating_Natural_ventilation_Hot_water_uninsulated | M52: MA_SFH_pre_1975_Occupied_uninsulated_Tight_envelope_HRV_SIP_Single_pane_storm_windows
G53: MA_SFH_Electric_resistance_Natural_ventilation_Steam_Heating_DHW_combo_NG | H53: MA_Oil_heating_Natural_ventilation_Air_ducts_uninsulated | M53: MA_SFH_pre_1975_Occupied_uninsulated_Tight_envelope_HRV_SIP_Double_pane_lowE
G54: MA_SFH_Electric_resistance_Natural_ventilation_Steam_HPWH | H54: MA_Oil_heating_Natural_ventilation_Air_ducts_conditioned_uninsulated | M54: MA_SFH_pre_1975_Occupied_uninsulated_Tight_envelope_HRV_SIP_Triple_pane_lowE
G55: MA_SFH_Electric_resistance_Natural_ventilation_Hot_water_uninsulated_Electric_resistance_DHW | H55: MA_Oil_heating_Natural_ventilation_Hot_water_insulated | M55: MA_SFH_pre_1975_Occupied_uninsulated_Tight_envelope_HRV_Full_insulated_wall_cavity_Single_pane
G56: MA_SFH_Electric_resistance_Natural_ventilation_Hot_water_uninsulated_NG_DHW | H56: MA_Oil_heating_Natural_ventilation_Air_ducts_insulated | M56: MA_SFH_pre_1975_Occupied_uninsulated_Tight_envelope_HRV_Full_insulated_wall_cavity_Single_pane_storm_windows
... G218: MA_SFH_Oil_heating_Natural_ventilation_Air_ducts_insulated_HPWH | H218: MA_GSHP_GSHP_Air_ducts_insulated | M218: MA_SFH_pre_1975_Limited_insulation_roof_Somewhat_leaky_envelope_Full_insulated_wall_cavity_Triple_pane_lowE
G219: MA_SFH_Oil_heating_Window_ASHP_Steam_Electric_resistance_DHW | M219: MA_SFH_pre_1975_Limited_insulation_roof_Somewhat_leaky_envelope_Full_insulated_wall_cavity_exterior_Single_pane
G220: MA_SFH_Oil_heating_Window_ASHP_Steam_NG_DHW | M220: MA_SFH_pre_1975_Limited_insulation_roof_Somewhat_leaky_envelope_Full_insulated_wall_cavity_exterior_Single_pane_storm_windows
G221: MA_SFH_Oil_heating_Window_ASHP_Steam_Heating_DHW_combo_NG | M221: MA_SFH_pre_1975_Limited_insulation_roof_Somewhat_leaky_envelope_Full_insulated_wall_cavity_exterior_Double_pane_lowE
G222: MA_SFH_Oil_heating_Window_ASHP_Steam_HPWH | M222: MA_SFH_pre_1975_Limited_insulation_roof_Somewhat_leaky_envelope_Full_insulated_wall_cavity_exterior_Triple_pane_lowE
G223: MA_SFH_Oil_heating_Window_ASHP_Hot_water_uninsulated_Electric_resistance_DHW | M223: MA_SFH_pre_1975_Limited_insulation_roof_Tight_envelope_HRV_Uninsulated_walls_Single_pane
G224: MA_SFH_Oil_heating_Window_ASHP_Hot_water_uninsulated_NG_DHW | M224: MA_SFH_pre_1975_Limited_insulation_roof_Tight_envelope_HRV_Uninsulated_walls_Single_pane_storm_windows
G225: MA_SFH_Oil_heating_Window_ASHP_Hot_water_uninsulated_Heating_DHW_combo_NG | M225: MA_SFH_pre_1975_Limited_insulation_roof_Tight_envelope_HRV_Uninsulated_walls_Double_pane_lowE
G226: MA_SFH_Oil_heating_Window_ASHP_Hot_water_uninsulated_HPWH | M226: MA_SFH_pre_1975_Limited_insulation_roof_Tight_envelope_HRV_Uninsulated_walls_Triple_pane_lowE
G227: MA_SFH_Oil_heating_Window_ASHP_Air_ducts_uninsulated_Electric_resistance_DHW | M227: MA_SFH_pre_1975_Limited_insulation_roof_Tight_envelope_HRV_Some_wall_insulation_Single_pane
G228: MA_SFH_Oil_heating_Window_ASHP_Air_ducts_uninsulated_NG_DHW | M228: MA_SFH_pre_1975_Limited_insulation_roof_Tight_envelope_HRV_Some_wall_insulation_Single_pane_storm_windows
G229: MA_SFH_Oil_heating_Window_ASHP_Air_ducts_uninsulated_Heating_DHW_combo_NG | M229: MA_SFH_pre_1975_Limited_insulation_roof_Tight_envelope_HRV_Some_wall_insulation_Double_pane_lowE
G230: MA_SFH_Oil_heating_Window_ASHP_Air_ducts_uninsulated_HPWH | M230: MA_SFH_pre_1975_Limited_insulation_roof_Tight_envelope_HRV_Some_wall_insulation_Triple_pane_lowE
... G1730: MA_MFH_GSHP_GSHP_Air_ducts_insulated_HPWH | M1730: MA_MFH_btw_1975_2003_Occupied_uninsulated_Tight_envelope_HRV_Some_wall_insulation_Triple_pane_lowE
M1731: MA_MFH_btw_1975_2003_Occupied_uninsulated_Tight_envelope_HRV_SIP_Single_pane
M1732: MA_MFH_btw_1975_2003_Occupied_uninsulated_Tight_envelope_HRV_SIP_Single_pane_storm_windows
M1733: MA_MFH_btw_1975_2003_Occupied_uninsulated_Tight_envelope_HRV_SIP_Double_pane_lowE
M1734: MA_MFH_btw_1975_2003_Occupied_uninsulated_Tight_envelope_HRV_SIP_Triple_pane_lowE
M1735: MA_MFH_btw_1975_2003_Occupied_uninsulated_Tight_envelope_HRV_Full_insulated_wall_cavity_Single_pane
M1736: MA_MFH_btw_1975_2003_Occupied_uninsulated_Tight_envelope_HRV_Full_insulated_wall_cavity_Single_pane_storm_windows
M1737: MA_MFH_btw_1975_2003_Occupied_uninsulated_Tight_envelope_HRV_Full_insulated_wall_cavity_Double_pane_lowE
M1738: MA_MFH_btw_1975_2003_Occupied_uninsulated_Tight_envelope_HRV_Full_insulated_wall_cavity_Triple_pane_lowE
M1739: MA_MFH_btw_1975_2003_Occupied_uninsulated_Tight_envelope_HRV_Full_insulated_wall_cavity_exterior_Single_pane
M1740: MA_MFH_btw_1975_2003_Occupied_uninsulated_Tight_envelope_HRV_Full_insulated_wall_cavity_exterior_Single_pane_storm_windows
M1741: MA_MFH_btw_1975_2003_Occupied_uninsulated_Tight_envelope_HRV_Full_insulated_wall_cavity_exterior_Double_pane_lowE
M1742: MA_MFH_btw_1975_2003_Occupied_uninsulated_Tight_envelope_HRV_Full_insulated_wall_cavity_exterior_Triple_pane_lowE
... M2522: MA_MFH_post_2003_Unoccupied_high_insulated_floor_Tight_envelope_HRV_Full_insulated_wall_cavity_exterior_Triple_pane_lowE

Sheet Internal_gains
A1: Choose the metric you want to define from the dropdown | B1: Does not need to be filled in, will automatically populate | C1: Fill in the value for the chosen metric | D1: Does not need to be filled in, will automatically populate | E1: Name your variable. This should be something to recognize for the template assignment
A2: Variable | B2: Description | C2: Value | D2: Unit | E2: Variable_naming
A3: Occupant_density | B3: {=_xludf.XLOOKUP(A3,Units!$A$2:$A$100,Units!$C$2:$C$100,"")} -> #NAME? | D3: {=_xludf.XLOOKUP(A3,Units!$A$2:$A$100,Units!$B$2:$B$100,"")} -> #NAME? | E3: Occupancy_1
A4: Occupant_density | B4: {=_xludf.XLOOKUP(A4,Units!$A$2:$A$100,Units!$C$2:$C$100,"")} -> #NAME? | D4: {=_xludf.XLOOKUP(A4,Units!$A$2:$A$100,Units!$B$2:$B$100,"")} -> #NAME? | E4: Occupancy_2
A5: Power_density | B5: {=_xludf.XLOOKUP(A5,Units!$A$2:$A$100,Units!$C$2:$C$100,"")} -> #NAME? | D5: {=_xludf.XLOOKUP(A5,Units!$A$2:$A$100,Units!$B$2:$B$100,"")} -> #NAME? | E5: Power_1 | F5: Add another unit kWh per year/m2
A6: Power_density | B6: {=_xludf.XLOOKUP(A6,Units!$A$2:$A$100,Units!$C$2:$C$100,"")} -> #NAME? | D6: {=_xludf.XLOOKUP(A6,Units!$A$2:$A$100,Units!$B$2:$B$100,"")} -> #NAME? | E6: Power_2
A7: Lighting_density | B7: {=_xludf.XLOOKUP(A7,Units!$A$2:$A$100,Units!$C$2:$C$100,"")} -> #NAME? | D7: {=_xludf.XLOOKUP(A7,Units!$A$2:$A$100,Units!$B$2:$B$100,"")} -> #NAME? | E7: Lighting_1
A8: Lighting_density | B8: {=_xludf.XLOOKUP(A8,Units!$A$2:$A$100,Units!$C$2:$C$100,"")} -> #NAME? | D8: {=_xludf.XLOOKUP(A8,Units!$A$2:$A$100,Units!$B$2:$B$100,"")} -> #NAME? | E8: Lighting_2
A9: Occupant_density | B9: {=_xludf.XLOOKUP(A9,Units!$A$2:$A$100,Units!$C$2:$C$100,"")} -> #NAME? | D9: {=_xludf.XLOOKUP(A9,Units!$A$2:$A$100,Units!$B$2:$B$100,"")} -> #NAME?
A10: Schedules | B10: {=_xludf.XLOOKUP(A10,Units!$A$2:$A$100,Units!$C$2:$C$100,"")} -> #NAME? | D10: {=_xludf.XLOOKUP(A10,Units!$A$2:$A$100,Units!$B$2:$B$100,"")} -> #NAME?
A11: Schedules | B11: {=IF(_xludf.XLOOKUP(A11,Units!$A$2:$A$100,Units!$C$2:$C$100,"")=0,"",_xludf.XLOOKUP(A11,Units!$A$2:$A$100,Units!$C$2:$C$100,""))} -> #NAME? | D11: {=IF(_xludf.XLOOKUP(A11,Units!$A$2:$A$100,Units!$B$2:$B$100,"")=0,"",_xludf.XLOOKUP(A11,Units!$A$2:$A$100,Units!$B$2:$B$100,""))} -> #NAME?
A12: Lighting_density | B12: {=IF(_xludf.XLOOKUP(A12,Units!$A$2:$A$100,Units!$C$2:$C$100,"")=0,"",_xludf.XLOOKUP(A12,Units!$A$2:$A$100,Units!$C$2:$C$100,""))} -> #NAME? | C12: 5.6 | D12: {=IF(_xludf.XLOOKUP(A12,Units!$A$2:$A$100,Units!$B$2:$B$100,"")=0,"",_xludf.XLOOKUP(A12,Units!$A$2:$A$100,Units!$B$2:$B$100,""))} -> #NAME?
B13: {=IF(_xludf.XLOOKUP(A13,Units!$A$2:$A$100,Units!$C$2:$C$100,"")=0,"",_xludf.XLOOKUP(A13,Units!$A$2:$A$100,Units!$C$2:$C$100,""))} -> #NAME? | D13: {=IF(_xludf.XLOOKUP(A13,Units!$A$2:$A$100,Units!$B$2:$B$100,"")=0,"",_xludf.XLOOKUP(A13,Units!$A$2:$A$100,Units!$B$2:$B$100,""))} -> #NAME?
B14: {=IF(_xludf.XLOOKUP(A14,Units!$A$2:$A$100,Units!$C$2:$C$100,"")=0,"",_xludf.XLOOKUP(A14,Units!$A$2:$A$100,Units!$C$2:$C$100,""))} -> #NAME? | D14: {=IF(_xludf.XLOOKUP(A14,Units!$A$2:$A$100,Units!$B$2:$B$100,"")=0,"",_xludf.XLOOKUP(A14,Units!$A$2:$A$100,Units!$B$2:$B$100,""))} -> #NAME?
B15: {=IF(_xludf.XLOOKUP(A15,Units!$A$2:$A$100,Units!$C$2:$C$100,"")=0,"",_xludf.XLOOKUP(A15,Units!$A$2:$A$100,Units!$C$2:$C$100,""))} -> #NAME? | D15: {=IF(_xludf.XLOOKUP(A15,Units!$A$2:$A$100,Units!$B$2:$B$100,"")=0,"",_xludf.XLOOKUP(A15,Units!$A$2:$A$100,Units!$B$2:$B$100,""))} -> #NAME?
B16: {=IF(_xludf.XLOOKUP(A16,Units!$A$2:$A$100,Units!$C$2:$C$100,"")=0,"",_xludf.XLOOKUP(A16,Units!$A$2:$A$100,Units!$C$2:$C$100,""))} -> #NAME? | D16: {=IF(_xludf.XLOOKUP(A16,Units!$A$2:$A$100,Units!$B$2:$B$100,"")=0,"",_xludf.XLOOKUP(A16,Units!$A$2:$A$100,Units!$B$2:$B$100,""))} -> #NAME?
B17: {=IF(_xludf.XLOOKUP(A17,Units!$A$2:$A$100,Units!$C$2:$C$100,"")=0,"",_xludf.XLOOKUP(A17,Units!$A$2:$A$100,Units!$C$2:$C$100,""))} -> #NAME? | D17: {=IF(_xludf.XLOOKUP(A17,Units!$A$2:$A$100,Units!$B$2:$B$100,"")=0,"",_xludf.XLOOKUP(A17,Units!$A$2:$A$100,Units!$B$2:$B$100,""))} -> #NAME?
B18: {=IF(_xludf.XLOOKUP(A18,Units!$A$2:$A$100,Units!$C$2:$C$100,"")=0,"",_xludf.XLOOKUP(A18,Units!$A$2:$A$100,Units!$C$2:$C$100,""))} -> #NAME? | D18: {=IF(_xludf.XLOOKUP(A18,Units!$A$2:$A$100,Units!$B$2:$B$100,"")=0,"",_xludf.XLOOKUP(A18,Units!$A$2:$A$100,Units!$B$2:$B$100,""))} -> #NAME?
B19: {=IF(_xludf.XLOOKUP(A19,Units!$A$2:$A$100,Units!$C$2:$C$100,"")=0,"",_xludf.XLOOKUP(A19,Units!$A$2:$A$100,Units!$C$2:$C$100,""))} -> #NAME? | D19: {=IF(_xludf.XLOOKUP(A19,Units!$A$2:$A$100,Units!$B$2:$B$100,"")=0,"",_xludf.XLOOKUP(A19,Units!$A$2:$A$100,Units!$B$2:$B$100,""))} -> #NAME?
B20: {=IF(_xludf.XLOOKUP(A20,Units!$A$2:$A$100,Units!$C$2:$C$100,"")=0,"",_xludf.XLOOKUP(A20,Units!$A$2:$A$100,Units!$C$2:$C$100,""))} -> #NAME? | D20: {=IF(_xludf.XLOOKUP(A20,Units!$A$2:$A$100,Units!$B$2:$B$100,"")=0,"",_xludf.XLOOKUP(A20,Units!$A$2:$A$100,Units!$B$2:$B$100,""))} -> #NAME?
B21: {=IF(_xludf.XLOOKUP(A21,Units!$A$2:$A$100,Units!$C$2:$C$100,"")=0,"",_xludf.XLOOKUP(A21,Units!$A$2:$A$100,Units!$C$2:$C$100,""))} -> #NAME? | D21: {=IF(_xludf.XLOOKUP(A21,Units!$A$2:$A$100,Units!$B$2:$B$100,"")=0,"",_xludf.XLOOKUP(A21,Units!$A$2:$A$100,Units!$B$2:$B$100,""))} -> #NAME?
B22: {=IF(_xludf.XLOOKUP(A22,Units!$A$2:$A$100,Units!$C$2:$C$100,"")=0,"",_xludf.XLOOKUP(A22,Units!$A$2:$A$100,Units!$C$2:$C$100,""))} -> #NAME? | D22: {=IF(_xludf.XLOOKUP(A22,Units!$A$2:$A$100,Units!$B$2:$B$100,"")=0,"",_xludf.XLOOKUP(A22,Units!$A$2:$A$100,Units!$B$2:$B$100,""))} -> #NAME?
B23: {=IF(_xludf.XLOOKUP(A23,Units!$A$2:$A$100,Units!$C$2:$C$100,"")=0,"",_xludf.XLOOKUP(A23,Units!$A$2:$A$100,Units!$C$2:$C$100,""))} -> #NAME? | D23: {=IF(_xludf.XLOOKUP(A23,Units!$A$2:$A$100,Units!$B$2:$B$100,"")=0,"",_xludf.XLOOKUP(A23,Units!$A$2:$A$100,Units!$B$2:$B$100,""))} -> #NAME?
B24: {=IF(_xludf.XLOOKUP(A24,Units!$A$2:$A$100,Units!$C$2:$C$100,"")=0,"",_xludf.XLOOKUP(A24,Units!$A$2:$A$100,Units!$C$2:$C$100,""))} -> #NAME? | D24: {=IF(_xludf.XLOOKUP(A24,Units!$A$2:$A$100,Units!$B$2:$B$100,"")=0,"",_xludf.XLOOKUP(A24,Units!$A$2:$A$100,Units!$B$2:$B$100,""))} -> #NAME?
... B139: {=IF(_xludf.XLOOKUP(A139,Units!$A$2:$A$100,Units!$C$2:$C$100,"")=0,"",_xludf.XLOOKUP(A139,Units!$A$2:$A$100,Units!$C$2:$C$100,""))} -> #NAME? | D139: {=IF(_xludf.XLOOKUP(A139,Units!$A$2:$A$100,Units!$B$2:$B$100,"")=0,"",_xludf.XLOOKUP(A139,Units!$A$2:$A$100,Units!$B$2:$B$100,""))} -> #NAME?

Sheet Building_loads>>>>

Sheet Occupancy
A1: Name your variable. This should be something to recognize for the template assignment | B1: Fill in this column with the occupant density per variable/type of building you choose. | E1: The occupancy schedule can be either self-designed in the three schedule tabs, or you can pick from the set of provided options
A2: Name | B2: Occupant_density | C2: MetabolicRate | D2: Occupant_units | E2: Occupant_schedule | F2: Source
A3: KR_res_sf | B3: 0.03 | C3: 1.2 | D3: person/m2 | E3: Residential_Occupancy_Year | F3: 건축물 에너지효율등급 인증제도 운영규정 [별표2] 주거 및 주거용 이외 건축물 용도프로필 / Operating Regulations for the Building Energy Rating System [Appendix 2]: Use Profiles for Residential and Non-Residential Buildings
A4: KR_res_mf_low | B4: 0.03 | C4: 1.2 | D4: person/m2 | E4: Residential_Occupancy_Year | F4: 건축물 에너지효율등급 인증제도 운영규정 [별표2] 주거 및 주거용 이외 건축물 용도프로필 / Operating Regulations for the Building Energy Rating System [Appendix 2]: Use Profiles for Residential and Non-Residential Buildings
A5: KR_res_mf_high | B5: 0.03 | C5: 1.2 | D5: person/m2 | E5: Residential_Occupancy_Year | F5: 건축물 에너지효율등급 인증제도 운영규정 [별표2] 주거 및 주거용 이외 건축물 용도프로필 / Operating Regulations for the Building Energy Rating System [Appendix 2]: Use Profiles for Residential and Non-Residential Buildings
A6: KR_office_small | B6: 0.039 | C6: 1.2 | D6: person/m2 | E6: Office_Occupancy_Year | F6: 건축물 에너지효율등급 인증제도 운영규정 [별표2] 주거 및 주거용 이외 건축물 용도프로필 / Operating Regulations for the Building Energy Rating System [Appendix 2]: Use Profiles for Residential and Non-Residential Buildings
A7: KR_office_medium | B7: 0.039 | C7: 1.2 | D7: person/m2 | E7: Office_Occupancy_Year | F7: 건축물 에너지효율등급 인증제도 운영규정 [별표2] 주거 및 주거용 이외 건축물 용도프로필 / Operating Regulations for the Building Energy Rating System [Appendix 2]: Use Profiles for Residential and Non-Residential Buildings
A8: KR_office_large | B8: 0.039 | C8: 1.2 | D8: person/m2 | E8: Office_Occupancy_Year | F8: 건축물 에너지효율등급 인증제도 운영규정 [별표2] 주거 및 주거용 이외 건축물 용도프로필 / Operating Regulations for the Building Energy Rating System [Appendix 2]: Use Profiles for Residential and Non-Residential Buildings
A9: KR_retail_small | B9: 0.07 | C9: 1.2 | D9: person/m2 | E9: Retail_Occupancy_Year | F9: 건축물 에너지효율등급 인증제도 운영규정 [별표2] 주거 및 주거용 이외 건축물 용도프로필 / Operating Regulations for the Building Energy Rating System [Appendix 2]: Use Profiles for Residential and Non-Residential Buildings
A10: KR_retail_medium | B10: 0.07 | C10: 1.2 | D10: person/m2 | E10: Retail_Occupancy_Year | F10: 건축물 에너지효율등급 인증제도 운영규정 [별표2] 주거 및 주거용 이외 건축물 용도프로필 / Operating Regulations for the Building Energy Rating System [Appendix 2]: Use Profiles for Residential and Non-Residential Buildings
A11: KR_retail_large | B11: 0.07 | C11: 1.2 | D11: person/m2 | E11: Retail_Occupancy_Year | F11: 건축물 에너지효율등급 인증제도 운영규정 [별표2] 주거 및 주거용 이외 건축물 용도프로필 / Operating Regulations for the Building Energy Rating System [Appendix 2]: Use Profiles for Residential and Non-Residential Buildings
A12: KR_school | B12: 0.305 | C12: 1.2 | D12: person/m2 | E12: School_Occupancy_Year | F12: 건축물 에너지효율등급 인증제도 운영규정 [별표2] 주거 및 주거용 이외 건축물 용도프로필 / Operating Regulations for the Building Energy Rating System [Appendix 2]: Use Profiles for Residential and Non-Residential Buildings
A13: KR_hospital | B13: 0.045 | C13: 1.2 | D13: person/m2 | E13: Hospital_Occupancy_Year | F13: 건축물 에너지효율등급 인증제도 운영규정 [별표2] 주거 및 주거용 이외 건축물 용도프로필 / Operating Regulations for the Building Energy Rating System [Appendix 2]: Use Profiles for Residential and Non-Residential Buildings
A14: KR_welfare | B14: 0.045 | C14: 1.2 | D14: person/m2 | E14: Hospital_Occupancy_Year | F14: 건축물 에너지효율등급 인증제도 운영규정 [별표2] 주거 및 주거용 이외 건축물 용도프로필 / Operating Regulations for the Building Energy Rating System [Appendix 2]: Use Profiles for Residential and Non-Residential Buildings
... A21: KR_etc | B21: 0 | C21: 1.2 | D21: person/m2 | E21: Industrial_Occupancy_Year | F21: 건축물 에너지효율등급 인증제도 운영규정 [별표2] 주거 및 주거용 이외 건축물 용도프로필 / Operating Regulations for the Building Energy Rating System [Appendix 2]: Use Profiles for Residential and Non-Residential Buildings

Sheet Lighting
A1: Name your variable. This should be something to recognize for the template assignment | B1: Fill in this column with the lighting density per variable/type of building you choose. | E1: The lighting schedule can be either self-designed in the three schedule tabs, or you can pick from the set of provided options
A2: Name | B2: Lighting_power_density | C2: DimmingType | D2: Lighting_schedule | E2: Lighting_power_density_unit | F2: Source
A3: KR_res_sf_LowEff | B3: 4.57 | C3: Off | D3: Residential_Lighting_Year | E3: W/m2 | F3: 2020년 에너지총조사_공개용 마이크로데이터/ 2020 Energy Consumption Survey: Public-Use Microdata
A4: KR_res_sf_Standard | B4: 3.39 | C4: Off | D4: Residential_Lighting_Year | E4: W/m2 | F4: 2020년 에너지총조사_공개용 마이크로데이터/ 2020 Energy Consumption Survey: Public-Use Microdata
A5: KR_res_sf_HighEff | B5: 1.52 | C5: Off | D5: Residential_Lighting_Year | E5: W/m2 | F5: 2020년 에너지총조사_공개용 마이크로데이터/ 2020 Energy Consumption Survey: Public-Use Microdata
A6: KR_res_mf_Low_LowEff | B6: 4.38 | C6: Off | D6: Residential_Lighting_Year | E6: W/m2 | F6: 2020년 에너지총조사_공개용 마이크로데이터/ 2020 Energy Consumption Survey: Public-Use Microdata
A7: KR_res_mf_Low_Standard | B7: 3.31 | C7: Off | D7: Residential_Lighting_Year | E7: W/m2 | F7: 2020년 에너지총조사_공개용 마이크로데이터/ 2020 Energy Consumption Survey: Public-Use Microdata
A8: KR_res_mf_Low_HighEff | B8: 2 | C8: Off | D8: Residential_Lighting_Year | E8: W/m2 | F8: 2020년 에너지총조사_공개용 마이크로데이터/ 2020 Energy Consumption Survey: Public-Use Microdata
A9: KR_res_mf_High_LowEff | B9: 4.63 | C9: Off | D9: Residential_Lighting_Year | E9: W/m2 | F9: 2020년 에너지총조사_공개용 마이크로데이터/ 2020 Energy Consumption Survey: Public-Use Microdata
A10: KR_res_mf_High_Standard | B10: 3.34 | C10: Off | D10: Residential_Lighting_Year | E10: W/m2 | F10: 2020년 에너지총조사_공개용 마이크로데이터/ 2020 Energy Consumption Survey: Public-Use Microdata
A11: KR_res_mf_High_HighEff | B11: 1.97 | C11: Off | D11: Residential_Lighting_Year | E11: W/m2 | F11: 2020년 에너지총조사_공개용 마이크로데이터/ 2020 Energy Consumption Survey: Public-Use Microdata
A12: KR_office_small_LowEff | B12: 6.69 | C12: Off | D12: Office_Lighting_Year | E12: W/m2 | F12: 2020년 에너지총조사_공개용 마이크로데이터/ 2020 Energy Consumption Survey: Public-Use Microdata
A13: KR_office_small_Standard | B13: 4.75 | C13: Off | D13: Office_Lighting_Year | E13: W/m2 | F13: 2020년 에너지총조사_공개용 마이크로데이터/ 2020 Energy Consumption Survey: Public-Use Microdata
A14: KR_office_small_HighEff | B14: 3.23 | C14: Off | D14: Office_Lighting_Year | E14: W/m2 | F14: 2020년 에너지총조사_공개용 마이크로데이터/ 2020 Energy Consumption Survey: Public-Use Microdata
... A59: KR_etc_HighEff | B59: 3.23 | C59: Off | D59: Industrial_Lighting_Year | E59: W/m2 | F59: 2020년 에너지총조사_공개용 마이크로데이터/ 2020 Energy Consumption Survey: Public-Use Microdata

Sheet Power
A1: Name your variable. This should be something to recognize for the template assignment | B1: Fill in this column with the equipment power density per variable/type of building you choose. | D1: The equipment schedule can be either self-designed in the three schedule tabs, or you can pick from the set of provided options
A2: Name | B2: Equipment_power_density | C2: Equipment_power_density_unit | D2: Equipment_schedule | E2: Sources
A3: KR_res_sf | B3: 2.17 | C3: W/m2 | D3: Residential_Equipment_Year | E3: 건축물 에너지효율등급 인증제도 운영규정 [별표2] 주거 및 주거용 이외 건축물 용도프로필 / Operating Regulations for the Building Energy Rating System [Appendix 2]: Use Profiles for Residential and Non-Residential Buildings
A4: KR_res_mf_low | B4: 2.17 | C4: W/m2 | D4: Residential_Equipment_Year | E4: 건축물 에너지효율등급 인증제도 운영규정 [별표2] 주거 및 주거용 이외 건축물 용도프로필 / Operating Regulations for the Building Energy Rating System [Appendix 2]: Use Profiles for Residential and Non-Residential Buildings
A5: KR_res_mf_high | B5: 2.17 | C5: W/m2 | D5: Residential_Equipment_Year | E5: 건축물 에너지효율등급 인증제도 운영규정 [별표2] 주거 및 주거용 이외 건축물 용도프로필 / Operating Regulations for the Building Energy Rating System [Appendix 2]: Use Profiles for Residential and Non-Residential Buildings
A6: KR_office_small | B6: 7.64 | C6: W/m2 | D6: Office_Equipment_Year | E6: 건축물 에너지효율등급 인증제도 운영규정 [별표2] 주거 및 주거용 이외 건축물 용도프로필 / Operating Regulations for the Building Energy Rating System [Appendix 2]: Use Profiles for Residential and Non-Residential Buildings
A7: KR_office_medium | B7: 7.64 | C7: W/m2 | D7: Office_Equipment_Year | E7: 건축물 에너지효율등급 인증제도 운영규정 [별표2] 주거 및 주거용 이외 건축물 용도프로필 / Operating Regulations for the Building Energy Rating System [Appendix 2]: Use Profiles for Residential and Non-Residential Buildings
A8: KR_office_large | B8: 7.64 | C8: W/m2 | D8: Office_Equipment_Year | E8: 건축물 에너지효율등급 인증제도 운영규정 [별표2] 주거 및 주거용 이외 건축물 용도프로필 / Operating Regulations for the Building Energy Rating System [Appendix 2]: Use Profiles for Residential and Non-Residential Buildings
A9: KR_retail_small | B9: 2.7 | C9: W/m2 | D9: Retail_Equipment_Year | E9: Ashrae Standard 90.1
A10: KR_retail_medium | B10: 2.7 | C10: W/m2 | D10: Retail_Equipment_Year | E10: Ashrae Standard 90.1
A11: KR_retail_large | B11: 2.7 | C11: W/m2 | D11: Retail_Equipment_Year | E11: Ashrae Standard 90.1
A12: KR_school | B12: 2.77 | C12: W/m2 | D12: School_Equipment_Year | E12: 건축물 에너지효율등급 인증제도 운영규정 [별표2] 주거 및 주거용 이외 건축물 용도프로필 / Operating Regulations for the Building Energy Rating System [Appendix 2]: Use Profiles for Residential and Non-Residential Buildings
A13: KR_hospital | B13: 10.8 | C13: W/m2 | D13: Hospital_Equipment_Year | E13: Ashrae Standard 90.1
A14: KR_welfare | B14: 10.8 | C14: W/m2 | D14: Hospital_Equipment_Year | E14: Ashrae Standard 90.1
... A21: KR_etc | B21: 0 | C21: W/m2 | D21: Industrial_Equipment_Year | E21: 건축물 에너지효율등급 인증제도 운영규정 [별표2] 주거 및 주거용 이외 건축물 용도프로필 / Operating Regulations for the Building Energy Rating System [Appendix 2]: Use Profiles for Residential and Non-Residential Buildings

Sheet Generated_schedule
A1: Schedule+type

Sheet Schedule_viewer
A1: View sample schedules here and alter them | B1: Schedule

Sheet HVAC
A1: Choose the metric you want to define from the dropdown | B1: Does not need to be filled in, will automatically populate | C1: Fill in the value for the chosen metric | D1: Does not need to be filled in, will automatically populate | E1: Name your variable. This should be something to recognize for the template assignment
A2: Variable | B2: Description | C2: Value | D2: Unit | E2: Variable_naming
A3: Heating_distribution_fluid | B3: {=_xludf.XLOOKUP(A3,Units!$A$2:$A$100,Units!$C$2:$C$100,"")} -> #NAME? | D3: {=_xludf.XLOOKUP(A3,Units!$A$2:$A$100,Units!$B$2:$B$100,"")} -> #NAME?
A4: Heating_setpoints | B4: {=_xludf.XLOOKUP(A4,Units!$A$2:$A$100,Units!$C$2:$C$100,"")} -> #NAME? | D4: {=_xludf.XLOOKUP(A4,Units!$A$2:$A$100,Units!$B$2:$B$100,"")} -> #NAME?
A5: Heating_distribution_temperature | B5: {=_xludf.XLOOKUP(A5,Units!$A$2:$A$100,Units!$C$2:$C$100,"")} -> #NAME? | D5: {=_xludf.XLOOKUP(A5,Units!$A$2:$A$100,Units!$B$2:$B$100,"")} -> #NAME?
A6: Heating_setpoint_schedule | B6: {=_xludf.XLOOKUP(A6,Units!$A$2:$A$100,Units!$C$2:$C$100,"")} -> #NAME? | D6: {=_xludf.XLOOKUP(A6,Units!$A$2:$A$100,Units!$B$2:$B$100,"")} -> #NAME?
A7: Cooling_setpoints | B7: {=_xludf.XLOOKUP(A7,Units!$A$2:$A$100,Units!$C$2:$C$100,"")} -> #NAME? | D7: {=_xludf.XLOOKUP(A7,Units!$A$2:$A$100,Units!$B$2:$B$100,"")} -> #NAME?
A8: Cooling_setpoint_schedule | B8: {=_xludf.XLOOKUP(A8,Units!$A$2:$A$100,Units!$C$2:$C$100,"")} -> #NAME? | D8: {=_xludf.XLOOKUP(A8,Units!$A$2:$A$100,Units!$B$2:$B$100,"")} -> #NAME?
A9: Cooling_distribution_temperature | B9: {=_xludf.XLOOKUP(A9,Units!$A$2:$A$100,Units!$C$2:$C$100,"")} -> #NAME? | D9: {=_xludf.XLOOKUP(A9,Units!$A$2:$A$100,Units!$B$2:$B$100,"")} -> #NAME?
A10: Cooling_setpoint_schedule | B10: {=_xludf.XLOOKUP(A10,Units!$A$2:$A$100,Units!$C$2:$C$100,"")} -> #NAME? | D10: {=_xludf.XLOOKUP(A10,Units!$A$2:$A$100,Units!$B$2:$B$100,"")} -> #NAME?
A11: Minimum_fresh_air | B11: {=_xludf.XLOOKUP(A11,Units!$A$2:$A$100,Units!$C$2:$C$100,"")} -> #NAME? | D11: {=_xludf.XLOOKUP(A11,Units!$A$2:$A$100,Units!$B$2:$B$100,"")} -> #NAME?
A12: Heating_COP_penalty | B12: {=_xludf.XLOOKUP(A12,Units!$A$2:$A$100,Units!$C$2:$C$100,"")} -> #NAME? | D12: {=_xludf.XLOOKUP(A12,Units!$A$2:$A$100,Units!$B$2:$B$100,"")} -> #NAME?
A13: Cooling_COP_penalty | B13: {=_xludf.XLOOKUP(A13,Units!$A$2:$A$100,Units!$C$2:$C$100,"")} -> #NAME? | D13: {=_xludf.XLOOKUP(A13,Units!$A$2:$A$100,Units!$B$2:$B$100,"")} -> #NAME?
A14: Heating_setpoints | B14: {=IF(_xludf.XLOOKUP(A14,Units!$A$2:$A$100,Units!$C$2:$C$100,"")=0,"",_xludf.XLOOKUP(A14,Units!$A$2:$A$100,Units!$C$2:$C$100,""))} -> #NAME? | D14: {=IF(_xludf.XLOOKUP(A14,Units!$A$2:$A$100,Units!$B$2:$B$100,"")=0,"",_xludf.XLOOKUP(A14,Units!$A$2:$A$100,Units!$B$2:$B$100,""))} -> #NAME?
B15: {=IF(_xludf.XLOOKUP(A15,Units!$A$2:$A$100,Units!$C$2:$C$100,"")=0,"",_xludf.XLOOKUP(A15,Units!$A$2:$A$100,Units!$C$2:$C$100,""))} -> #NAME? | D15: {=IF(_xludf.XLOOKUP(A15,Units!$A$2:$A$100,Units!$B$2:$B$100,"")=0,"",_xludf.XLOOKUP(A15,Units!$A$2:$A$100,Units!$B$2:$B$100,""))} -> #NAME?
A16: Heating_setpoints | B16: {=IF(_xludf.XLOOKUP(A16,Units!$A$2:$A$100,Units!$C$2:$C$100,"")=0,"",_xludf.XLOOKUP(A16,Units!$A$2:$A$100,Units!$C$2:$C$100,""))} -> #NAME? | C16: 15 | D16: {=IF(_xludf.XLOOKUP(A16,Units!$A$2:$A$100,Units!$B$2:$B$100,"")=0,"",_xludf.XLOOKUP(A16,Units!$A$2:$A$100,Units!$B$2:$B$100,""))} -> #NAME?
A17: Heating_COP_penalty | B17: {=IF(_xludf.XLOOKUP(A17,Units!$A$2:$A$100,Units!$C$2:$C$100,"")=0,"",_xludf.XLOOKUP(A17,Units!$A$2:$A$100,Units!$C$2:$C$100,""))} -> #NAME? | C17: 5 | D17: {=IF(_xludf.XLOOKUP(A17,Units!$A$2:$A$100,Units!$B$2:$B$100,"")=0,"",_xludf.XLOOKUP(A17,Units!$A$2:$A$100,Units!$B$2:$B$100,""))} -> #NAME?
B18: {=IF(_xludf.XLOOKUP(A18,Units!$A$2:$A$100,Units!$C$2:$C$100,"")=0,"",_xludf.XLOOKUP(A18,Units!$A$2:$A$100,Units!$C$2:$C$100,""))} -> #NAME? | D18: {=IF(_xludf.XLOOKUP(A18,Units!$A$2:$A$100,Units!$B$2:$B$100,"")=0,"",_xludf.XLOOKUP(A18,Units!$A$2:$A$100,Units!$B$2:$B$100,""))} -> #NAME?
B19: {=IF(_xludf.XLOOKUP(A19,Units!$A$2:$A$100,Units!$C$2:$C$100,"")=0,"",_xludf.XLOOKUP(A19,Units!$A$2:$A$100,Units!$C$2:$C$100,""))} -> #NAME? | D19: {=IF(_xludf.XLOOKUP(A19,Units!$A$2:$A$100,Units!$B$2:$B$100,"")=0,"",_xludf.XLOOKUP(A19,Units!$A$2:$A$100,Units!$B$2:$B$100,""))} -> #NAME?
B20: {=IF(_xludf.XLOOKUP(A20,Units!$A$2:$A$100,Units!$C$2:$C$100,"")=0,"",_xludf.XLOOKUP(A20,Units!$A$2:$A$100,Units!$C$2:$C$100,""))} -> #NAME? | D20: {=IF(_xludf.XLOOKUP(A20,Units!$A$2:$A$100,Units!$B$2:$B$100,"")=0,"",_xludf.XLOOKUP(A20,Units!$A$2:$A$100,Units!$B$2:$B$100,""))} -> #NAME?
B21: {=IF(_xludf.XLOOKUP(A21,Units!$A$2:$A$100,Units!$C$2:$C$100,"")=0,"",_xludf.XLOOKUP(A21,Units!$A$2:$A$100,Units!$C$2:$C$100,""))} -> #NAME? | D21: {=IF(_xludf.XLOOKUP(A21,Units!$A$2:$A$100,Units!$B$2:$B$100,"")=0,"",_xludf.XLOOKUP(A21,Units!$A$2:$A$100,Units!$B$2:$B$100,""))} -> #NAME?
B22: {=IF(_xludf.XLOOKUP(A22,Units!$A$2:$A$100,Units!$C$2:$C$100,"")=0,"",_xludf.XLOOKUP(A22,Units!$A$2:$A$100,Units!$C$2:$C$100,""))} -> #NAME? | D22: {=IF(_xludf.XLOOKUP(A22,Units!$A$2:$A$100,Units!$B$2:$B$100,"")=0,"",_xludf.XLOOKUP(A22,Units!$A$2:$A$100,Units!$B$2:$B$100,""))} -> #NAME?
B23: {=IF(_xludf.XLOOKUP(A23,Units!$A$2:$A$100,Units!$C$2:$C$100,"")=0,"",_xludf.XLOOKUP(A23,Units!$A$2:$A$100,Units!$C$2:$C$100,""))} -> #NAME? | D23: {=IF(_xludf.XLOOKUP(A23,Units!$A$2:$A$100,Units!$B$2:$B$100,"")=0,"",_xludf.XLOOKUP(A23,Units!$A$2:$A$100,Units!$B$2:$B$100,""))} -> #NAME?
B24: {=IF(_xludf.XLOOKUP(A24,Units!$A$2:$A$100,Units!$C$2:$C$100,"")=0,"",_xludf.XLOOKUP(A24,Units!$A$2:$A$100,Units!$C$2:$C$100,""))} -> #NAME? | D24: {=IF(_xludf.XLOOKUP(A24,Units!$A$2:$A$100,Units!$B$2:$B$100,"")=0,"",_xludf.XLOOKUP(A24,Units!$A$2:$A$100,Units!$B$2:$B$100,""))} -> #NAME?
B25: {=IF(_xludf.XLOOKUP(A25,Units!$A$2:$A$100,Units!$C$2:$C$100,"")=0,"",_xludf.XLOOKUP(A25,Units!$A$2:$A$100,Units!$C$2:$C$100,""))} -> #NAME? | D25: {=IF(_xludf.XLOOKUP(A25,Units!$A$2:$A$100,Units!$B$2:$B$100,"")=0,"",_xludf.XLOOKUP(A25,Units!$A$2:$A$100,Units!$B$2:$B$100,""))} -> #NAME?
B26: {=IF(_xludf.XLOOKUP(A26,Units!$A$2:$A$100,Units!$C$2:$C$100,"")=0,"",_xludf.XLOOKUP(A26,Units!$A$2:$A$100,Units!$C$2:$C$100,""))} -> #NAME? | D26: {=IF(_xludf.XLOOKUP(A26,Units!$A$2:$A$100,Units!$B$2:$B$100,"")=0,"",_xludf.XLOOKUP(A26,Units!$A$2:$A$100,Units!$B$2:$B$100,""))} -> #NAME?
B27: {=IF(_xludf.XLOOKUP(A27,Units!$A$2:$A$100,Units!$C$2:$C$100,"")=0,"",_xludf.XLOOKUP(A27,Units!$A$2:$A$100,Units!$C$2:$C$100,""))} -> #NAME? | D27: {=IF(_xludf.XLOOKUP(A27,Units!$A$2:$A$100,Units!$B$2:$B$100,"")=0,"",_xludf.XLOOKUP(A27,Units!$A$2:$A$100,Units!$B$2:$B$100,""))} -> #NAME?
B28: {=IF(_xludf.XLOOKUP(A28,Units!$A$2:$A$100,Units!$C$2:$C$100,"")=0,"",_xludf.XLOOKUP(A28,Units!$A$2:$A$100,Units!$C$2:$C$100,""))} -> #NAME? | D28: {=IF(_xludf.XLOOKUP(A28,Units!$A$2:$A$100,Units!$B$2:$B$100,"")=0,"",_xludf.XLOOKUP(A28,Units!$A$2:$A$100,Units!$B$2:$B$100,""))} -> #NAME?
B29: {=IF(_xludf.XLOOKUP(A29,Units!$A$2:$A$100,Units!$C$2:$C$100,"")=0,"",_xludf.XLOOKUP(A29,Units!$A$2:$A$100,Units!$C$2:$C$100,""))} -> #NAME? | D29: {=IF(_xludf.XLOOKUP(A29,Units!$A$2:$A$100,Units!$B$2:$B$100,"")=0,"",_xludf.XLOOKUP(A29,Units!$A$2:$A$100,Units!$B$2:$B$100,""))} -> #NAME?
... B72: {=IF(_xludf.XLOOKUP(A72,Units!$A$2:$A$100,Units!$C$2:$C$100,"")=0,"",_xludf.XLOOKUP(A72,Units!$A$2:$A$100,Units!$C$2:$C$100,""))} -> #NAME? | D72: {=IF(_xludf.XLOOKUP(A72,Units!$A$2:$A$100,Units!$B$2:$B$100,"")=0,"",_xludf.XLOOKUP(A72,Units!$A$2:$A$100,Units!$B$2:$B$100,""))} -> #NAME?

Sheet Setpoints
A1: Name your variable. This should be something to recognize for the template assignment
A2: Name | B2: Setpoint_type | C2: Heating_setpoint | D2: Heating_schedule | E2: Cooling_setpoint | F2: Cooling_schedule | G2: Setpoint_units | H2: Sources
A3: KR_res_sf_NoControl | B3: Constant | C3: 20 | D3: Residential_Heating_Year | E3: 26 | F3: Residential_Cooling_Year | G3: Celsius | H3: 건축물 에너지효율등급 인증제도 운영규정 [별표2] 주거 및 주거용 이외 건축물 용도프로필 / Operating Regulations for the Building Energy Rating System [Appendix 2]: Use Profiles for Residential and Non-Residential Buildings
A4: KR_res_mf_low_NoControl | B4: Constant | C4: 20 | D4: Residential_Heating_Year | E4: 26 | F4: Residential_Cooling_Year | G4: Celsius | H4: 건축물 에너지효율등급 인증제도 운영규정 [별표2] 주거 및 주거용 이외 건축물 용도프로필 / Operating Regulations for the Building Energy Rating System [Appendix 2]: Use Profiles for Residential and Non-Residential Buildings
A5: KR_res_mf_high_NoControl | B5: Constant | C5: 20 | D5: Residential_Heating_Year | E5: 26 | F5: Residential_Cooling_Year | G5: Celsius | H5: 건축물 에너지효율등급 인증제도 운영규정 [별표2] 주거 및 주거용 이외 건축물 용도프로필 / Operating Regulations for the Building Energy Rating System [Appendix 2]: Use Profiles for Residential and Non-Residential Buildings
A6: KR_office_small_NoControl | B6: Constant | C6: 20 | D6: Office_Heating_Year | E6: 26 | F6: Office_Cooling_Year | G6: Celsius | H6: 건축물 에너지효율등급 인증제도 운영규정 [별표2] 주거 및 주거용 이외 건축물 용도프로필 / Operating Regulations for the Building Energy Rating System [Appendix 2]: Use Profiles for Residential and Non-Residential Buildings
A7: KR_office_medium_NoControl | B7: Constant | C7: 20 | D7: Office_Heating_Year | E7: 26 | F7: Office_Cooling_Year | G7: Celsius | H7: 건축물 에너지효율등급 인증제도 운영규정 [별표2] 주거 및 주거용 이외 건축물 용도프로필 / Operating Regulations for the Building Energy Rating System [Appendix 2]: Use Profiles for Residential and Non-Residential Buildings
A8: KR_office_large_NoControl | B8: Constant | C8: 20 | D8: Office_Heating_Year | E8: 26 | F8: Office_Cooling_Year | G8: Celsius | H8: 건축물 에너지효율등급 인증제도 운영규정 [별표2] 주거 및 주거용 이외 건축물 용도프로필 / Operating Regulations for the Building Energy Rating System [Appendix 2]: Use Profiles for Residential and Non-Residential Buildings
A9: KR_retail_small_NoControl | B9: Constant | C9: 20 | D9: Retail_Heating_Year | E9: 26 | F9: Retail_Cooling_Year | G9: Celsius | H9: 건축물 에너지효율등급 인증제도 운영규정 [별표2] 주거 및 주거용 이외 건축물 용도프로필 / Operating Regulations for the Building Energy Rating System [Appendix 2]: Use Profiles for Residential and Non-Residential Buildings
A10: KR_retail_medium_NoControl | B10: Constant | C10: 20 | D10: Retail_Heating_Year | E10: 26 | F10: Retail_Cooling_Year | G10: Celsius | H10: 건축물 에너지효율등급 인증제도 운영규정 [별표2] 주거 및 주거용 이외 건축물 용도프로필 / Operating Regulations for the Building Energy Rating System [Appendix 2]: Use Profiles for Residential and Non-Residential Buildings
A11: KR_retail_large_NoControl | B11: Constant | C11: 20 | D11: Retail_Heating_Year | E11: 26 | F11: Retail_Cooling_Year | G11: Celsius | H11: 건축물 에너지효율등급 인증제도 운영규정 [별표2] 주거 및 주거용 이외 건축물 용도프로필 / Operating Regulations for the Building Energy Rating System [Appendix 2]: Use Profiles for Residential and Non-Residential Buildings
A12: KR_school_NoControl | B12: Constant | C12: 20 | D12: School_Heating_Year | E12: 26 | F12: School_Cooling_Year | G12: Celsius | H12: 건축물 에너지효율등급 인증제도 운영규정 [별표2] 주거 및 주거용 이외 건축물 용도프로필 / Operating Regulations for the Building Energy Rating System [Appendix 2]: Use Profiles for Residential and Non-Residential Buildings
A13: KR_hospital_NoControl | B13: Constant | C13: 20 | D13: Hospital_Heating_Year | E13: 26 | F13: Hospital_Cooling_Year | G13: Celsius | H13: 건축물 에너지효율등급 인증제도 운영규정 [별표2] 주거 및 주거용 이외 건축물 용도프로필 / Operating Regulations for the Building Energy Rating System [Appendix 2]: Use Profiles for Residential and Non-Residential Buildings
A14: KR_welfare_NoControl | B14: Constant | C14: 20 | D14: Hospital_Heating_Year | E14: 26 | F14: Hospital_Cooling_Year | G14: Celsius | H14: 건축물 에너지효율등급 인증제도 운영규정 [별표2] 주거 및 주거용 이외 건축물 용도프로필 / Operating Regulations for the Building Energy Rating System [Appendix 2]: Use Profiles for Residential and Non-Residential Buildings
... A21: KR_etc_NoControl | B21: Constant | C21: 20 | D21: Industrial_Heating_Year | E21: 26 | F21: Industrial_Cooling_Year | G21: Celsius | H21: 건축물 에너지효율등급 인증제도 운영규정 [별표2] 주거 및 주거용 이외 건축물 용도프로필 / Operating Regulations for the Building Energy Rating System [Appendix 2]: Use Profiles for Residential and Non-Residential Buildings

Sheet Water_flow
A1: Name your variable. This should be something to recognize for the template assignment
A2: Name | B2: DHW_flow_rate | C2: Water_schedule | D2: Flow_rate_unit | E2: Source
A3: KR_res_sf | B3: 0.054 | C3: KR_res_sf_water | D3: m3/day/person | E3: 건축물 에너지효율등급 인증제도 운영규정 [별표2] 주거 및 주거용 이외 건축물 용도프로필 / Operating Regulations for the Building Energy Rating System [Appendix 2]: Use Profiles for Residential and Non-Residential Buildings
A4: KR_res_mf_low | B4: 0.054 | C4: KR_res_mf_low_water | D4: m3/day/person | E4: 건축물 에너지효율등급 인증제도 운영규정 [별표2] 주거 및 주거용 이외 건축물 용도프로필 / Operating Regulations for the Building Energy Rating System [Appendix 2]: Use Profiles for Residential and Non-Residential Buildings
A5: KR_res_mf_high | B5: 0.054 | C5: KR_res_mf_high_water | D5: m3/day/person | E5: 건축물 에너지효율등급 인증제도 운영규정 [별표2] 주거 및 주거용 이외 건축물 용도프로필 / Operating Regulations for the Building Energy Rating System [Appendix 2]: Use Profiles for Residential and Non-Residential Buildings
A6: KR_office_small | B6: 0.011 | C6: KR_office_small_water | D6: m3/day/person | E6: 건축물 에너지효율등급 인증제도 운영규정 [별표2] 주거 및 주거용 이외 건축물 용도프로필 / Operating Regulations for the Building Energy Rating System [Appendix 2]: Use Profiles for Residential and Non-Residential Buildings
A7: KR_office_medium | B7: 0.011 | C7: KR_office_medium_water | D7: m3/day/person | E7: 건축물 에너지효율등급 인증제도 운영규정 [별표2] 주거 및 주거용 이외 건축물 용도프로필 / Operating Regulations for the Building Energy Rating System [Appendix 2]: Use Profiles for Residential and Non-Residential Buildings
A8: KR_office_large | B8: 0.011 | C8: KR_office_large_water | D8: m3/day/person | E8: 건축물 에너지효율등급 인증제도 운영규정 [별표2] 주거 및 주거용 이외 건축물 용도프로필 / Operating Regulations for the Building Energy Rating System [Appendix 2]: Use Profiles for Residential and Non-Residential Buildings
A9: KR_retail_small | B9: 0.011 | C9: KR_retail_small_water | D9: m3/day/person | E9: 건축물 에너지효율등급 인증제도 운영규정 [별표2] 주거 및 주거용 이외 건축물 용도프로필 / Operating Regulations for the Building Energy Rating System [Appendix 2]: Use Profiles for Residential and Non-Residential Buildings
A10: KR_retail_medium | B10: 0.011 | C10: KR_retail_medium_water | D10: m3/day/person | E10: 건축물 에너지효율등급 인증제도 운영규정 [별표2] 주거 및 주거용 이외 건축물 용도프로필 / Operating Regulations for the Building Energy Rating System [Appendix 2]: Use Profiles for Residential and Non-Residential Buildings
A11: KR_retail_large | B11: 0.011 | C11: KR_retail_large_water | D11: m3/day/person | E11: 건축물 에너지효율등급 인증제도 운영규정 [별표2] 주거 및 주거용 이외 건축물 용도프로필 / Operating Regulations for the Building Energy Rating System [Appendix 2]: Use Profiles for Residential and Non-Residential Buildings
A12: KR_school | B12: 0.004 | C12: KR_school_water | D12: m3/day/person | E12: 건축물 에너지효율등급 인증제도 운영규정 [별표2] 주거 및 주거용 이외 건축물 용도프로필 / Operating Regulations for the Building Energy Rating System [Appendix 2]: Use Profiles for Residential and Non-Residential Buildings
A13: KR_hospital | B13: 0.031 | C13: KR_hospital_water | D13: m3/day/person | E13: 건축물 에너지효율등급 인증제도 운영규정 [별표2] 주거 및 주거용 이외 건축물 용도프로필 / Operating Regulations for the Building Energy Rating System [Appendix 2]: Use Profiles for Residential and Non-Residential Buildings
A14: KR_welfare | B14: 0.031 | C14: KR_welfare_water | D14: m3/day/person | E14: 건축물 에너지효율등급 인증제도 운영규정 [별표2] 주거 및 주거용 이외 건축물 용도프로필 / Operating Regulations for the Building Energy Rating System [Appendix 2]: Use Profiles for Residential and Non-Residential Buildings
... A21: KR_etc | B21: 0 | C21: KR_etc_water | D21: m3/day/person | E21: 건축물 에너지효율등급 인증제도 운영규정 [별표2] 주거 및 주거용 이외 건축물 용도프로필 / Operating Regulations for the Building Energy Efficiency Rating Certification System [Appendix 2]: Use Profiles for Residential and Non-Residential Buildings

Sheet Space_use_assembly
A1: Name your variable. This should be something to recognize for the template assignment | B1: Create a package from your generated space uses. Ensure that they fit within your semantic schema
A2: Name | B2: Occupancy | C2: Lighting | D2: Equipment | E2: Setpoints | F2: WaterUse

Sheet HVAC>>>

Sheet Conditioning_constructor
A1: Name your variable. This should be something to recognize for the template assignment | B1: Fill in the value for the chosen metric | G1: Calculated column. Please check that you agree with this value, otherwise change the COP_equipment and/or Distribution_loss
A2: Name | B2: Type | C2: Fuel | D2: Distribution_type | E2: COP_equipment | F2: Distribution_efficiency | G2: System_COP | H2: Source
A3: KR_CentralCooling_CAV | B3: Cooling | C3: Electricity | D3: Air | E3: 3.64 | F3: 0.75 | G3: =E3*F3 -> 2.73 | H3: 2020년 에너지총조사_공개용 마이크로데이터/ 2020 Energy Consumption Survey: Public-Use Microdata
A4: KR_CentralCooling_VAV | B4: Cooling | C4: Electricity | D4: Air | E4: 3.64 | F4: 0.78 | G4: =E4*F4 -> 2.8392 | H4: 2020년 에너지총조사_공개용 마이크로데이터/ 2020 Energy Consumption Survey: Public-Use Microdata
A5: KR_CentralCooling_FCU | B5: Cooling | C5: Electricity | D5: Water | E5: 3.64 | F5: 0.88 | G5: =E5*F5 -> 3.2032 | H5: 2020년 에너지총조사_공개용 마이크로데이터/ 2020 Energy Consumption Survey: Public-Use Microdata
A6: KR_CentralHeating_CAV | B6: Heating | C6: NaturalGas | D6: Air | E6: 0.86 | F6: 0.75 | G6: =E6*F6 -> 0.645 | H6: 2020년 에너지총조사_공개용 마이크로데이터/ 2020 Energy Consumption Survey: Public-Use Microdata
A7: KR_CentralHeating_VAV | B7: Heating | C7: NaturalGas | D7: Air | E7: 0.86 | F7: 0.78 | G7: =E7*F7 -> 0.6708 | H7: 2020년 에너지총조사_공개용 마이크로데이터/ 2020 Energy Consumption Survey: Public-Use Microdata
A8: KR_CentralHeating_FCU | B8: Heating | C8: NaturalGas | D8: Water | E8: 0.86 | F8: 0.88 | G8: =E8*F8 -> 0.7568 | H8: 2020년 에너지총조사_공개용 마이크로데이터/ 2020 Energy Consumption Survey: Public-Use Microdata
A9: KR_CentralHeating_Radiator | B9: Heating | C9: NaturalGas | D9: Water | E9: 0.86 | F9: 0.92 | G9: =E9*F9 -> 0.7912 | H9: 2020년 에너지총조사_공개용 마이크로데이터/ 2020 Energy Consumption Survey: Public-Use Microdata
A10: KR_Central_PackagedHVAC | B10: HeatingAndCooling | C10: Electricity | D10: Air | E10: 3.64 | F10: 0.85 | G10: =E10*F10 -> 3.094 | H10: 2020년 에너지총조사_공개용 마이크로데이터/ 2020 Energy Consumption Survey: Public-Use Microdata
A11: KR_IndividualCooling_AC | B11: Cooling | C11: Electricity | D11: Air | E11: 3.64 | F11: 0.92 | G11: =E11*F11 -> 3.3488 | H11: 2020년 에너지총조사_공개용 마이크로데이터/ 2020 Energy Consumption Survey: Public-Use Microdata
A12: KR_IndividualCooling_ElectricHP | B12: Cooling | C12: Electricity | D12: Air | E12: 3.64 | F12: 0.92 | G12: =E12*F12 -> 3.3488 | H12: 2020년 에너지총조사_공개용 마이크로데이터/ 2020 Energy Consumption Survey: Public-Use Microdata
A13: KR_IndividualCooling_GasHP | B13: Cooling | C13: NaturalGas | D13: Air | E13: 1.51 | F13: 0.9 | G13: =E13*F13 -> 1.359 | H13: 2020년 에너지총조사_공개용 마이크로데이터/ 2020 Energy Consumption Survey: Public-Use Microdata
A14: KR_IndividualCooling_GSHP | B14: Cooling | C14: Electricity | D14: Air | E14: 4.5 | F14: 0.93 | G14: =E14*F14 -> 4.185 | H14: 2020년 에너지총조사_공개용 마이크로데이터/ 2020 Energy Consumption Survey: Public-Use Microdata
... A44: KR_NoneCooling | B44: Cooling | C44: CustomFuel | D44: Air | E44: 0 | F44: 0 | G44: =E44*F44 -> 0 | H44: 2020년 에너지총조사_공개용 마이크로데이터/ 2020 Energy Consumption Survey: Public-Use Microdata

Sheet Ventilation_constructor
A1: Name your variable. This should be something to recognize for the template assignment
A2: Name | B2: Fresh_air_per_m2 | C2: Fresh_air_per_unit | D2: Fresh_air_per_person | E2: Ventilation_type | F2: Tech_type | G2: Window_schedule | H2: Economizer | I2: HRV | J2: DCV | K2: Source
A3: KR_res_LeakyEnvelope | B3: 0.00031 | C3: m3/s/m2 | D3: 0.0072 | E3: Natural | F3: Custom | G3: Window | H3: NoEconomizer | I3: NoHRV | J3: NoDCV | K3: 건축물의 설비기준 등에 관한 규칙(공동주택 환기) / Rules on Building Equipment Standards (Residential Ventilation)
A4: KR_res_SomewhatLeakyEnvelope | B4: 0.00031 | C4: m3/s/m2 | D4: 0.0072 | E4: Natural | F4: Custom | G4: Window | H4: NoEconomizer | I4: NoHRV | J4: NoDCV | K4: 건축물의 설비기준 등에 관한 규칙(공동주택 환기) / Rules on Building Equipment Standards (Residential Ventilation)
A5: KR_res_TightEnvelope | B5: 0.00031 | C5: m3/s/m2 | D5: 0.0072 | E5: Natural | F5: Custom | G5: Window | H5: NoEconomizer | I5: NoHRV | J5: NoDCV | K5: 건축물의 설비기준 등에 관한 규칙(공동주택 환기) / Rules on Building Equipment Standards (Residential Ventilation)
A6: KR_res_TightEnvelopeHRV | B6: 0.00031 | C6: m3/s/m2 | D6: 0.0072 | E6: Mechanical | F6: HRV | G6: Window | H6: NoEconomizer | I6: Sensible | J6: NoDCV | K6: 건축물의 설비기준 등에 관한 규칙(공동주택 환기) / Rules on Building Equipment Standards (Residential Ventilation)
A7: KR_office_LeakyEnvelope | B7: 0.00139 | C7: m3/s/m2 | D7: 0.0072 | E7: Mechanical | F7: Custom | G7: Window | H7: DifferentialDryBulb | I7: NoHRV | J7: NoDCV | K7: 건축물의 설비기준 등에 관한 규칙(다중이용시설 기계환기) / Rules on Building Equipment Standards (Mechanical Ventilation for Public-use Buildings)
A8: KR_office_SomewhatLeakyEnvelope | B8: 0.00139 | C8: m3/s/m2 | D8: 0.0072 | E8: Mechanical | F8: Custom | G8: Window | H8: DifferentialDryBulb | I8: NoHRV | J8: NoDCV | K8: 건축물의 설비기준 등에 관한 규칙(다중이용시설 기계환기) / Rules on Building Equipment Standards (Mechanical Ventilation for Public-use Buildings)
A9: KR_office_TightEnvelope | B9: 0.00139 | C9: m3/s/m2 | D9: 0.0072 | E9: Mechanical | F9: Custom | G9: Window | H9: DifferentialDryBulb | I9: NoHRV | J9: NoDCV | K9: 건축물의 설비기준 등에 관한 규칙(다중이용시설 기계환기) / Rules on Building Equipment Standards (Mechanical Ventilation for Public-use Buildings)
A10: KR_office_TightEnvelopeDCV | B10: 0.00139 | C10: m3/s/m2 | D10: 0.0072 | E10: Mechanical | F10: DCV | G10: Window | H10: DifferentialDryBulb | I10: NoHRV | J10: NoDCV | K10: 건축물의 설비기준 등에 관한 규칙(다중이용시설 기계환기) / Rules on Building Equipment Standards (Mechanical Ventilation for Public-use Buildings)
A11: KR_retail_LeakyEnvelope | B11: 0.00111 | C11: m3/s/m2 | D11: 0.0072 | E11: Mechanical | F11: Custom | G11: Window | H11: DifferentialDryBulb | I11: NoHRV | J11: NoDCV | K11: 건축물의 설비기준 등에 관한 규칙(다중이용시설 기계환기) / Rules on Building Equipment Standards (Mechanical Ventilation for Public-use Buildings)
A12: KR_retail_SomewhatLeakyEnvelope | B12: 0.00111 | C12: m3/s/m2 | D12: 0.0072 | E12: Mechanical | F12: Custom | G12: Window | H12: DifferentialDryBulb | I12: NoHRV | J12: NoDCV | K12: 건축물의 설비기준 등에 관한 규칙(다중이용시설 기계환기) / Rules on Building Equipment Standards (Mechanical Ventilation for Public-use Buildings)
A13: KR_retail_TightEnvelope | B13: 0.00111 | C13: m3/s/m2 | D13: 0.0072 | E13: Mechanical | F13: Custom | G13: Window | H13: DifferentialDryBulb | I13: NoHRV | J13: NoDCV | K13: 건축물의 설비기준 등에 관한 규칙(다중이용시설 기계환기) / Rules on Building Equipment Standards (Mechanical Ventilation for Public-use Buildings)
A14: KR_retail_TightEnvelopeDCV | B14: 0.00111 | C14: m3/s/m2 | D14: 0.0072 | E14: Mechanical | F14: DCV | G14: Window | H14: DifferentialDryBulb | I14: NoHRV | J14: NoDCV | K14: 건축물의 설비기준 등에 관한 규칙(다중이용시설 기계환기) / Rules on Building Equipment Standards (Mechanical Ventilation for Public-use Buildings)
... A33: KR_hotel_TightEnvelopeHRV | B33: 0.00083 | C33: m3/s/m2 | D33: 0.0072 | E33: Mechanical | F33: HRV | G33: Window | H33: NoEconomizer | I33: Enthalpy | J33: NoDCV | K33: 건축물의 설비기준 등에 관한 규칙(공동주택 환기) / Rules on Building Equipment Standards (Residential Ventilation)
C73: m3/s/p
C74: m3/s/p
C75: m3/s/p
C76: m3/s/p
C77: m3/s/p
C78: m3/s/p
C79: m3/s/p
C80: m3/s/p
C81: m3/s/p
C82: m3/s/p
C83: m3/s/p
C84: m3/s/p
... C164: m3/s/p

Sheet DHW
A1: Choose the metric you want to define from the dropdown | B1: Does not need to be filled in, will automatically populate | C1: Fill in the value for the chosen metric | D1: Does not need to be filled in, will automatically populate | E1: Name your variable. This should be something to recognize for the template assignment
A2: Variable | B2: Description | C2: Value | D2: Unit | E2: Variable_naming
A3: Flow_rate_per_person | B3: {=_xludf.XLOOKUP(A3,Units!$A$2:$A$100,Units!$C$2:$C$100,"")} -> #NAME? | D3: {=_xludf.XLOOKUP(A3,Units!$A$2:$A$100,Units!$B$2:$B$100,"")} -> #NAME?
A4: DHW_temperature | B4: {=_xludf.XLOOKUP(A4,Units!$A$2:$A$100,Units!$C$2:$C$100,"")} -> #NAME? | D4: {=_xludf.XLOOKUP(A4,Units!$A$2:$A$100,Units!$B$2:$B$100,"")} -> #NAME?
A5: DHW_COP | B5: {=_xludf.XLOOKUP(A5,Units!$A$2:$A$100,Units!$C$2:$C$100,"")} -> #NAME? | D5: {=_xludf.XLOOKUP(A5,Units!$A$2:$A$100,Units!$B$2:$B$100,"")} -> #NAME?
A6: DHW_energy_source | B6: {=_xludf.XLOOKUP(A6,Units!$A$2:$A$100,Units!$C$2:$C$100,"")} -> #NAME? | D6: {=_xludf.XLOOKUP(A6,Units!$A$2:$A$100,Units!$B$2:$B$100,"")} -> #NAME?
A7: Flow_rate_per_person | B7: {=_xludf.XLOOKUP(A7,Units!$A$2:$A$100,Units!$C$2:$C$100,"")} -> #NAME? | D7: {=_xludf.XLOOKUP(A7,Units!$A$2:$A$100,Units!$B$2:$B$100,"")} -> #NAME?
A8: DHW_temperature | B8: {=_xludf.XLOOKUP(A8,Units!$A$2:$A$100,Units!$C$2:$C$100,"")} -> #NAME? | D8: {=_xludf.XLOOKUP(A8,Units!$A$2:$A$100,Units!$B$2:$B$100,"")} -> #NAME?
A9: DHW_COP | B9: {=_xludf.XLOOKUP(A9,Units!$A$2:$A$100,Units!$C$2:$C$100,"")} -> #NAME? | D9: {=_xludf.XLOOKUP(A9,Units!$A$2:$A$100,Units!$B$2:$B$100,"")} -> #NAME?
A10: DHW_energy_source | B10: {=_xludf.XLOOKUP(A10,Units!$A$2:$A$100,Units!$C$2:$C$100,"")} -> #NAME? | D10: {=_xludf.XLOOKUP(A10,Units!$A$2:$A$100,Units!$B$2:$B$100,"")} -> #NAME?
A11: Flow_rate_per_person | B11: {=_xludf.XLOOKUP(A11,Units!$A$2:$A$100,Units!$C$2:$C$100,"")} -> #NAME? | D11: {=_xludf.XLOOKUP(A11,Units!$A$2:$A$100,Units!$B$2:$B$100,"")} -> #NAME?
A12: DHW_temperature | B12: {=_xludf.XLOOKUP(A12,Units!$A$2:$A$100,Units!$C$2:$C$100,"")} -> #NAME? | D12: {=_xludf.XLOOKUP(A12,Units!$A$2:$A$100,Units!$B$2:$B$100,"")} -> #NAME?
A13: DHW_COP | B13: {=_xludf.XLOOKUP(A13,Units!$A$2:$A$100,Units!$C$2:$C$100,"")} -> #NAME? | D13: {=_xludf.XLOOKUP(A13,Units!$A$2:$A$100,Units!$B$2:$B$100,"")} -> #NAME?
A14: DHW_energy_source | B14: {=_xludf.XLOOKUP(A14,Units!$A$2:$A$100,Units!$C$2:$C$100,"")} -> #NAME? | D14: {=_xludf.XLOOKUP(A14,Units!$A$2:$A$100,Units!$B$2:$B$100,"")} -> #NAME?
... A22: DHW_energy_source | B22: {=_xludf.XLOOKUP(A22,Units!$A$2:$A$100,Units!$C$2:$C$100,"")} -> #NAME? | D22: {=_xludf.XLOOKUP(A22,Units!$A$2:$A$100,Units!$B$2:$B$100,"")} -> #NAME?

Sheet DHW_Constructor
A1: Name your variable. This should be something to recognize for the template assignment | B1: Fill in the value for the chosen metric
A2: Name | B2: DHW_energy_source | C2: Water_temperature_inlet | D2: Water_supply_temperature | E2: Heat generation efficiency | F2: Distribution_efficiency | G2: System_COP | H2: Source
A3: KR_Central_NaturalGas | B3: NaturalGas | C3: 10 | D3: 60 | E3: 0.91 | F3: 0.7 | G3: =E3*F3 -> 0.637 | H3: 2020년 에너지총조사_공개용 마이크로데이터/ 2020 Energy Consumption Survey: Public-Use Microdata
A4: KR_Central_DistrictHeating | B4: Steam | C4: 10 | D4: 60 | E4: 0.75 | F4: 0.7 | G4: =E4*F4 -> 0.525 | H4: 2020년 에너지총조사_공개용 마이크로데이터/ 2020 Energy Consumption Survey: Public-Use Microdata
A5: KR_Individual_NaturalGas | B5: NaturalGas | C5: 10 | D5: 60 | E5: 0.91 | F5: 0.85 | G5: =E5*F5 -> 0.7735 | H5: 2020년 에너지총조사_공개용 마이크로데이터/ 2020 Energy Consumption Survey: Public-Use Microdata
A6: KR_Individual_DistrictHeating | B6: Steam | C6: 10 | D6: 60 | E6: 0.75 | F6: 0.85 | G6: =E6*F6 -> 0.6375 | H6: 2020년 에너지총조사_공개용 마이크로데이터/ 2020 Energy Consumption Survey: Public-Use Microdata
A7: KR_None | B7: NaturalGas | C7: 10 | D7: 60 | E7: 0 | F7: 0 | G7: 0 | H7: 2020년 에너지총조사_공개용 마이크로데이터/ 2020 Energy Consumption Survey: Public-Use Microdata

Sheet Systems_assembly
A1: Name your variable. This should be something to recognize for the template assignment | B1: Choose the specific construction for each of these features for your overall construction from the drop downs. If you don't see your construction generated, then check the names you attributed in the previous steps
A2: Name | B2: Heating | C2: Cooling | D2: Ventilation | E2: DHW

Sheet Building_construction>>>>

Sheet Construction_generator
A1: Does not need to be filled in, will automatically populate | B1: Fill in your constructions material by material. The outermost material should be Material_1 and you can build inwards from there. Materials available will appear in the dropdown menu. Enter a thickness for each material in meters (m). You do not need to fill in values for all 6 materials, but need at least 1 material and thickness. | O1: Concat_column
A2: CONSTRUCTION OPTIONS | B2: Material_1 (outermost material) | C2: Thickness_1 | D2: Material_2 | E2: Thickness_2 | F2: Material_3 | G2: Thickness_3 | H2: Material_4 | I2: Thickness_4 | J2: Material_5 | K2: Thickness_5 | L2: Material_6 | M2: Thickness_6 | O2: =_xludf.CONCAT("[",_xludf.TEXTJOIN(",",TRUE,B3,C3,D3,E3,F3,G3,H3,I3,J3,K3,L3,M3),"]") -> #NAME?
A3: =O2 -> #NAME? | B3: Oriented strand board | C3: 0.019 | D3: Oriented strand board | E3: 0.019 | F3: Oriented strand board | G3: 0.019 | H3: Oriented strand board | I3: 0.019 | O3: =_xludf.CONCAT("[",_xludf.TEXTJOIN(",",TRUE,B4,C4,D4,E4,F4,G4,H4,I4,J4,K4,L4,M4),"]") -> #NAME?
A4: =O3 -> #NAME? | B4: Shale | C4: 0.017 | O4: =_xludf.CONCAT("[",_xludf.TEXTJOIN(",",TRUE,B5,C5,D5,E5,F5,G5,H5,I5,J5,K5,L5,M5),"]") -> #NAME?
A5: =O4 -> #NAME? | B5: Stucco | C5: 0.02 | D5: Oriented strand board | E5: 0.03 | O5: =_xludf.CONCAT("[",_xludf.TEXTJOIN(",",TRUE,B6,C6,D6,E6,F6,G6,H6,I6,J6,K6,L6,M6),"]") -> #NAME?
A6: =O5 -> #NAME? | O6: =_xludf.CONCAT("[",_xludf.TEXTJOIN(",",TRUE,B7,C7,D7,E7,F7,G7,H7,I7,J7,K7,L7,M7),"]") -> #NAME?
A7: =O6 -> #NAME? | O7: =_xludf.CONCAT("[",_xludf.TEXTJOIN(",",TRUE,B8,C8,D8,E8,F8,G8,H8,I8,J8,K8,L8,M8),"]") -> #NAME?
A8: =O7 -> #NAME? | O8: =_xludf.CONCAT("[",_xludf.TEXTJOIN(",",TRUE,B9,C9,D9,E9,F9,G9,H9,I9,J9,K9,L9,M9),"]") -> #NAME?
A9: =O8 -> #NAME? | O9: =_xludf.CONCAT("[",_xludf.TEXTJOIN(",",TRUE,B10,C10,D10,E10,F10,G10,H10,I10,J10,K10,L10,M10),"]") -> #NAME?
A10: =O9 -> #NAME? | O10: =_xludf.CONCAT("[",_xludf.TEXTJOIN(",",TRUE,B11,C11,D11,E11,F11,G11,H11,I11,J11,K11,L11,M11),"]") -> #NAME?
A11: =O10 -> #NAME? | O11: =_xludf.CONCAT("[",_xludf.TEXTJOIN(",",TRUE,B12,C12,D12,E12,F12,G12,H12,I12,J12,K12,L12,M12),"]") -> #NAME?
A12: =O11 -> #NAME? | O12: =_xludf.CONCAT("[",_xludf.TEXTJOIN(",",TRUE,B13,C13,D13,E13,F13,G13,H13,I13,J13,K13,L13,M13),"]") -> #NAME?
A13: =O12 -> #NAME? | O13: =_xludf.CONCAT("[",_xludf.TEXTJOIN(",",TRUE,B14,C14,D14,E14,F14,G14,H14,I14,J14,K14,L14,M14),"]") -> #NAME?
A14: =O13 -> #NAME? | O14: =_xludf.CONCAT("[",_xludf.TEXTJOIN(",",TRUE,B15,C15,D15,E15,F15,G15,H15,I15,J15,K15,L15,M15),"]") -> #NAME?
A15: =O14 -> #NAME? | O15: =_xludf.CONCAT("[",_xludf.TEXTJOIN(",",TRUE,B16,C16,D16,E16,F16,G16,H16,I16,J16,K16,L16,M16),"]") -> #NAME?
A16: =O15 -> #NAME? | O16: =_xludf.CONCAT("[",_xludf.TEXTJOIN(",",TRUE,B17,C17,D17,E17,F17,G17,H17,I17,J17,K17,L17,M17),"]") -> #NAME?
A17: =O16 -> #NAME? | O17: =_xludf.CONCAT("[",_xludf.TEXTJOIN(",",TRUE,B18,C18,D18,E18,F18,G18,H18,I18,J18,K18,L18,M18),"]") -> #NAME?
... A103: =O102 -> #NAME? | O103: =_xludf.CONCAT("[",_xludf.TEXTJOIN(",",TRUE,B104,C104,D104,E104,F104,G104,H104,I104,J104,K104,L104,M104),"]") -> #NAME?
O104: =_xludf.CONCAT("[",_xludf.TEXTJOIN(",",TRUE,B105,C105,D105,E105,F105,G105,H105,I105,J105,K105,L105,M105),"]") -> #NAME?
O105: =_xludf.CONCAT("[",_xludf.TEXTJOIN(",",TRUE,B106,C106,D106,E106,F106,G106,H106,I106,J106,K106,L106,M106),"]") -> #NAME?
O106: =_xludf.CONCAT("[",_xludf.TEXTJOIN(",",TRUE,B107,C107,D107,E107,F107,G107,H107,I107,J107,K107,L107,M107),"]") -> #NAME?
O107: =_xludf.CONCAT("[",_xludf.TEXTJOIN(",",TRUE,B108,C108,D108,E108,F108,G108,H108,I108,J108,K108,L108,M108),"]") -> #NAME?
O108: =_xludf.CONCAT("[",_xludf.TEXTJOIN(",",TRUE,B109,C109,D109,E109,F109,G109,H109,I109,J109,K109,L109,M109),"]") -> #NAME?
O109: =_xludf.CONCAT("[",_xludf.TEXTJOIN(",",TRUE,B110,C110,D110,E110,F110,G110,H110,I110,J110,K110,L110,M110),"]") -> #NAME?
O110: =_xludf.CONCAT("[",_xludf.TEXTJOIN(",",TRUE,B111,C111,D111,E111,F111,G111,H111,I111,J111,K111,L111,M111),"]") -> #NAME?
O111: =_xludf.CONCAT("[",_xludf.TEXTJOIN(",",TRUE,B112,C112,D112,E112,F112,G112,H112,I112,J112,K112,L112,M112),"]") -> #NAME?
O112: =_xludf.CONCAT("[",_xludf.TEXTJOIN(",",TRUE,B113,C113,D113,E113,F113,G113,H113,I113,J113,K113,L113,M113),"]") -> #NAME?
O113: =_xludf.CONCAT("[",_xludf.TEXTJOIN(",",TRUE,B114,C114,D114,E114,F114,G114,H114,I114,J114,K114,L114,M114),"]") -> #NAME?
O114: =_xludf.CONCAT("[",_xludf.TEXTJOIN(",",TRUE,B115,C115,D115,E115,F115,G115,H115,I115,J115,K115,L115,M115),"]") -> #NAME?

Sheet Materials
A1: Check the material list to determine if there is any material missing for your country. Include the materials you need here with the appropriate values in columns C - J. Please write the name in the local language in column A, and the english name in column B
A2: Name | B2: English_name | C2: Type | D2: Roughness | E2: ThermalAbsorptance | F2: VisibleAbsorptance | G2: SolarAbsorptance | H2: TemperatureCoefficientThermalConductivity | I2: Conductivity [W/m.K] | J2: Density [kg/m3] | K2: Hatch_pattern | L2: Roughness | M2: SpecificHeat [J/kg.K]
A3: 철근콘크리트 | B3: reinforced_concrete_korea | C3: Concrete | D3: MediumRough | E3: 0.9 | F3: 0.65 | G3: 0.65 | H3: 0 | I3: 1.95 | J3: 2400 | K3: concrete | L3: MediumRough | M3: 1000
A4: 점토벽돌 | B4: clay_brick_korea | C4: Masonry | D4: Rough | E4: 0.9 | F4: 0.7 | G4: 0.7 | H4: 0 | I4: 0.77 | J4: 1800 | K4: brick | L4: Rough | M4: 840
A5: 시멘트몰탈 | B5: cement_mortar_korea | C5: Masonry | D5: MediumSmooth | E5: 0.9 | F5: 0.6 | G5: 0.6 | H5: 0 | I5: 1.4 | J5: 2000 | K5: mortar | L5: MediumSmooth | M5: 900
A6: 석고보드 | B6: gypsum_board_korea | C6: Timber | D6: Smooth | E6: 0.9 | F6: 0.5 | G6: 0.5 | H6: 0 | I6: 0.25 | J6: 800 | K6: gypsum | L6: Smooth | M6: 1090
A7: 공기층(비통기) | B7: air_gap_unventilated_korea | C7: Other | D7: MediumRough | E7: 0.9 | F7: 0.2 | G7: 0.2 | H7: 0 | I7: 0.025 | J7: 1.2 | K7: air | L7: MediumRough | M7: 1005
A8: 비드법단열재(EPS) | B8: eps_insulation_korea | C8: Insulation | D8: MediumSmooth | E8: 0.9 | F8: 0.5 | G8: 0.5 | H8: 0 | I8: 0.036 | J8: 25 | K8: insulation | L8: MediumSmooth | M8: 1400
A9: 압출법단열재(XPS) | B9: xps_insulation_korea | C9: Insulation | D9: MediumSmooth | E9: 0.9 | F9: 0.5 | G9: 0.5 | H9: 0 | I9: 0.029 | J9: 35 | K9: insulation | L9: MediumSmooth | M9: 1450
A10: 미네랄울 | B10: mineral_wool_korea | C10: Insulation | D10: Rough | E10: 0.9 | F10: 0.5 | G10: 0.5 | H10: 0 | I10: 0.037 | J10: 40 | K10: insulation | L10: Rough | M10: 1030
A11: 구조용합판 | B11: wood_sheathing_korea | C11: Timber | D11: MediumSmooth | E11: 0.9 | F11: 0.5 | G11: 0.5 | H11: 0 | I11: 0.13 | J11: 550 | K11: wood | L11: MediumSmooth | M11: 1600
A12: Vaporpermeable Felt | B12: Vaporpermeable Felt | C12: Concrete | D12: Rough | E12: 0.9 | F12: 0.7 | G12: 0.7 | H12: 0 | I12: 0.90909091 | J12: 0.5 | K12: Rough | L12: Rough | M12: 1800
A13: Oriented strand board | B13: Oriented strand board | C13: Concrete | D13: Rough | E13: 0.9 | F13: 0.7 | G13: 0.7 | H13: 0 | I13: 0.13 | J13: 650 | K13: Rough | L13: Rough | M13: 1700
A14: Air | B14: Air | C14: Concrete | D14: Rough | E14: 0.8 | F14: 0.7 | G14: 0.7 | H14: 0.0001 | I14: 0.03 | J14: 1.2 | K14: Rough | L14: Rough | M14: 1000
A15: Gypsum Board | B15: Gypsum Board | C15: Concrete | D15: MediumSmooth | E15: 0.9 | F15: 0.7 | G15: 0.7 | H15: 0 | I15: 0.09 | J15: 800 | K15: MediumSmooth | L15: MediumSmooth | M15: 1090
A16: Wood joist | B16: Wood joist | C16: Timber | D16: Rough | E16: 0.9 | F16: 0.5 | G16: 0.6 | H16: 0.002 | I16: 0.17 | J16: 500 | K16: Rough | M16: 2000
A17: Wood rafter | B17: Wood rafter | C17: Timber | D17: Rough | E17: 0.9 | F17: 0.5 | G17: 0.6 | H17: 0.002 | I17: 0.17 | J17: 500 | K17: Rough | M17: 2000
A18: Polyethylene | B18: Polyethylene | C18: Concrete | D18: Rough | E18: 0.1 | F18: 0.1 | G18: 0.1 | H18: 5e-05 | I18: 0.33 | J18: 950 | K18: Rough | M18: 1550
A19: Drywall | B19: Drywall | C19: Concrete | D19: Rough | E19: 0.9 | F19: 0.7 | G19: 0.7 | H19: 0 | I19: 0.16 | J19: 800 | K19: Rough | M19: 891
A20: Roof felt | B20: Roof felt | C20: Concrete | D20: Rough | E20: 0.5 | F20: 0.5 | G20: 0.5 | H20: 0.0001 | I20: 0.19 | J20: 960 | K20: Rough | M20: 837
A21: Synthetic felt | B21: Synthetic felt | C21: Concrete | D21: Rough | E21: 0.5 | F21: 0.5 | G21: 0.5 | H21: 0.0001 | I21: 0.16 | J21: 800 | K21: Rough | M21: 837
A22: Modified Bitumin | B22: Modified Bitumin | C22: Concrete | D22: Rough | E22: 0.9 | F22: 0.9 | G22: 0.9 | H22: 0.0008 | I22: 0.2 | J22: 1100 | K22: Rough | M22: 2000
A23: Vapor Retarder | B23: Vapor Retarder | C23: Concrete | D23: Rough | E23: 0.1 | F23: 0.1 | G23: 0.1 | H23: 5e-05 | I23: 0.33 | J23: 950 | K23: Rough | L23: 0.0005 | M23: 2000
A24: EPDM | B24: EPDM | C24: Concrete | D24: Rough | E24: 0.8 | F24: 0.8 | G24: 0.8 | H24: 0.0005 | I24: 0.25 | J24: 900 | K24: Rough | M24: 2000
A25: SIP Panel | B25: SIP Panel | C25: Concrete | D25: Rough | E25: 0.9 | F25: 0.5 | G25: 0.55 | H25: 0.001 | I25: 0.14 | J25: 540 | K25: Rough | M25: 1030
A26: Spray foam | B26: Spray foam | C26: Concrete | D26: MediumRough | E26: 0.9 | F26: 0.5 | G26: 0.6 | H26: 0.002 | I26: 0.025 | J26: 35 | K26: MediumRough | M26: 1090
A27: Stucco | B27: Stucco | C27: Concrete | D27: Smooth | E27: 0.9 | F27: 0.7 | G27: 0.7 | H27: 0 | I27: 0.72 | J27: 1856 | K27: Smooth | L27: Smooth | M27: 840
A28: Vinyl siding | B28: Vinyl siding | C28: Concrete | D28: Smooth | E28: 0.9 | F28: 0.4 | G28: 0.5 | H28: 0.001 | I28: 0.16 | J28: 540 | K28: Smooth | M28: 1400
A29: Fiber cement siding | B29: Fiber cement siding | C29: Concrete | D29: MediumRough | E29: 0.9 | F29: 0.5 | G29: 0.6 | H29: 0.001 | I29: 0.3 | J29: 1300 | K29: MediumRough | M29: 840
A30: Concrete | B30: Concrete | C30: Concrete | D30: Rough | E30: 0.9 | F30: 0.7 | G30: 0.7 | H30: 0 | I30: 2 | J30: 2400 | K30: Rough | L30: Rough | M30: 950
A31: Foam glass | B31: Foam glass | C31: Concrete | D31: Rough | E31: 0.9 | F31: 0.7 | G31: 0.7 | H31: 0 | I31: 0.056 | J31: 130 | K31: Rough | L31: Rough | M31: 750
A32: Wood stud | B32: Wood stud | C32: Concrete | D32: MediumRough | E32: 0.9 | F32: 0.5 | G32: 0.6 | H32: 0.002 | I32: 0.12 | J32: 500 | K32: MediumRough | M32: 1600
A33: Plaster | B33: Plaster | C33: Concrete | D33: Rough | E33: 0.9 | F33: 0.7 | G33: 0.7 | H33: 0 | I33: 1 | J33: 2000 | K33: Rough | L33: Rough | M33: 1130
A34: Sheathing - Regular Density | B34: Sheathing - Regular Density | C34: Concrete | D34: Smooth | E34: 0.9 | F34: 0.7 | G34: 0.7 | H34: 0 | I34: 0.055 | J34: 290 | K34: Smooth | L34: Smooth | M34: 1300
A35: Sheathing Intermediate Density | B35: Sheathing Intermediate Density | C35: Concrete | D35: Smooth | E35: 0.9 | F35: 0.7 | G35: 0.7 | H35: 0 | I35: 0.057 | J35: 350 | K35: Smooth | L35: Smooth | M35: 1300
A36: Mineral Wool | B36: Mineral Wool | C36: Concrete | D36: Rough | E36: 0.9 | F36: 0.7 | G36: 0.7 | H36: 0 | I36: 0.041 | J36: 155 | K36: Rough | L36: Rough | M36: 1130
A37: Carpet | B37: Carpet | C37: Concrete | D37: MediumRough | E37: 0.9 | F37: 0.7 | G37: 0.7 | H37: 0 | I37: 0.06 | J37: 288 | K37: MediumRough | L37: MediumRough | M37: 1380
A38: XPS Board | B38: XPS Board | C38: Concrete | D38: Rough | E38: 0.9 | F38: 0.7 | G38: 0.7 | H38: 0 | I38: 0.034 | J38: 35 | K38: Rough | L38: Rough | M38: 1400
A39: Asphalt Shingles | B39: Asphalt Shingles | C39: Concrete | D39: Rough | E39: 0.9 | F39: 0.7 | G39: 0.7 | H39: 0 | I39: 0.12987013 | J39: 0.5 | K39: Rough | L39: Rough | M39: 1800
A40: Pine wood | B40: Pine wood | C40: Concrete | D40: Rough | E40: 0.9 | F40: 0.7 | G40: 0.7 | H40: 0 | I40: 0.13 | J40: 520 | K40: Rough | L40: Rough | M40: 1600
A41: Douglas fir | B41: Douglas fir | C41: Concrete | D41: Rough | E41: 0.9 | F41: 0.7 | G41: 0.7 | H41: 0 | I41: 0.12 | J41: 530 | K41: Rough | L41: Rough | M41: 1600
A42: Oak EU | B42: Oak EU | C42: Concrete | D42: Rough | E42: 0.9 | F42: 0.7 | G42: 0.7 | H42: 0 | I42: 0.18 | J42: 690 | K42: Rough | L42: Rough | M42: 2400
A43: Spruce | B43: Spruce | C43: Concrete | D43: Rough | E43: 0.9 | F43: 0.7 | G43: 0.7 | H43: 0 | I43: 0.13 | J43: 450 | K43: Rough | L43: Rough | M43: 1600
A44: Larch | B44: Larch | C44: Concrete | D44: Rough | E44: 0.9 | F44: 0.7 | G44: 0.7 | H44: 0 | I44: 0.13 | J44: 460 | K44: Rough | L44: Rough | M44: 1600
... A292: Plaster Board with PCM | B292: Plaster Board with PCM | C292: Concrete | D292: Smooth | E292: 0.9 | F292: 0.7 | G292: 0.7 | H292: 0 | I292: 0.7264224 | J292: 1601.846 | K292: Smooth | L292: Smooth | M292: 836.8

Sheet Construction_components
A1: Add a name for your construction - this should be recognizable to you for future assignment. Examples are provided here. | B1: Define what part of the envelope this construction is associated with from the drop down | C1: Does not need to be filled in, will automatically populate | D1: Generated value. Do not change | E1: Calculated value. Do not change | G1: Fill in your constructions material by material. The outermost material should be Material_1 and you can build inwards from there. Materials available will appear in the dropdown menu. Enter a thickness for each material in meters (m). You do not need to fill in values for all 6 materials, but need at least 1 material and thickness. | U1: Add the source for this construction | V1: (OPTIONAL) Add performance values for this construction | AB1: R_value
A2: Base_name | B2: Type | C2: Description | D2: Construction | E2: u_value_W_per_m2K | F2: Name | G2: Material_1 | H2: Thickness_1 | I2: Material_2 | J2: Thickness_2 | K2: Material_3 | L2: Thickness_3 | M2: Material_4 | N2: Thickness_4 | O2: Material_5 | P2: Thickness_5 | Q2: Material_6 | R2: Thickness_6 | S2: Material_7 | T2: Thickness_7 | U2: DataSource | V2: EmbodiedEnergy [MJ/m¬≤] | W2: EmbodiedCarbon [kgCO2eq/m¬≤] | X2: Cost [$/m¬≤] | Y2: Life [yr]
A3: KR_res_sf_pre1988 | B3: Facade | C3: 외벽(외피) | D3: =AA3 -> #NAME? | E3: =IFERROR(1/AB3, "Not enough information entered") -> Not enough information entered | F3: KR_res_sf_pre1988_Facade | G3: 철근콘크리트 | H3: 0.18 | I3: 공기층(비통기) | J3: 0.02 | K3: 석고보드 | L3: 0.012 | U3: Korean Energy Saving Design Standards (derived) | V3: =H3+J3+L3+N3+P3+R3+T3 -> 0.212 | W3: 0 | X3: 0 | Y3: 10 | AA3: ="[" & _xludf.TEXTJOIN(",",TRUE,G3:T3) & "]" -> #NAME? | AB3: {=IFERROR(J3/_xludf.XLOOKUP(I3,Materials!$A$3:$A$292,Materials!$I$3:$I$292),0) +IFERROR(L3/_xludf.XLOOKUP(K3,Materials!$A$3:$A$292,Materials!$I$3:$I$292),0) +IFERROR(N3/_xludf.XLOOKUP(M3,Materials!$A$3:$A$292,Materials!$I$3:$I$292),0) +IFERROR(P3/_xludf.XLOOKUP(O3,Materials!$A$3:$A$292,Materials!$I$3:$I$292),0) +IFERROR(R3/_xludf.XLOOKUP(Q3,Materials!$A$3:$A$292,Materials!$I$3:$I$292),0) +IFERROR(H3/_xludf.XLOOKUP(G3,Materials!$A$3:$A$292,Materials!$I$3:$I$292),0)} -> 0
A4: KR_res_sf_pre1988 | B4: FlatRoof | C4: 지붕(평지붕) | D4: =AA4 -> #NAME? | E4: =IFERROR(1/AB4, "Not enough information entered") -> Not enough information entered | F4: KR_res_sf_pre1988_FlatRoof | G4: 철근콘크리트 | H4: 0.15 | I4: 시멘트몰탈 | J4: 0.03 | U4: Korean Energy Saving Design Standards (derived) | V4: =H4+J4+L4+N4+P4+R4+T4 -> 0.18 | AA4: ="[" & _xludf.TEXTJOIN(",",TRUE,G4:T4) & "]" -> #NAME? | AB4: {=IFERROR(J4/_xludf.XLOOKUP(I4,Materials!$A$3:$A$292,Materials!$I$3:$I$292),0) +IFERROR(L4/_xludf.XLOOKUP(K4,Materials!$A$3:$A$292,Materials!$I$3:$I$292),0) +IFERROR(N4/_xludf.XLOOKUP(M4,Materials!$A$3:$A$292,Materials!$I$3:$I$292),0) +IFERROR(P4/_xludf.XLOOKUP(O4,Materials!$A$3:$A$292,Materials!$I$3:$I$292),0) +IFERROR(R4/_xludf.XLOOKUP(Q4,Materials!$A$3:$A$292,Materials!$I$3:$I$292),0) +IFERROR(H4/_xludf.XLOOKUP(G4,Materials!$A$3:$A$292,Materials!$I$3:$I$292),0)} -> 0
A5: KR_res_sf_pre1988 | B5: AtticRoof | C5: 다락 지붕 | D5: =AA5 -> #NAME? | E5: =IFERROR(1/AB5, "Not enough information entered") -> Not enough information entered | F5: KR_res_sf_pre1988_AtticRoof | G5: 구조용합판 | H5: 0.2 | I5: 공기층(비통기) | J5: 0.04 | K5: 석고보드 | L5: 0.012 | U5: Korean Energy Saving Design Standards (derived) | V5: =H5+J5+L5+N5+P5+R5+T5 -> 0.252 | W5: 0 | X5: 0 | Y5: 10 | AA5: ="[" & _xludf.TEXTJOIN(",",TRUE,G5:T5) & "]" -> #NAME? | AB5: {=IFERROR(J5/_xludf.XLOOKUP(I5,Materials!$A$3:$A$292,Materials!$I$3:$I$292),0) +IFERROR(L5/_xludf.XLOOKUP(K5,Materials!$A$3:$A$292,Materials!$I$3:$I$292),0) +IFERROR(N5/_xludf.XLOOKUP(M5,Materials!$A$3:$A$292,Materials!$I$3:$I$292),0) +IFERROR(P5/_xludf.XLOOKUP(O5,Materials!$A$3:$A$292,Materials!$I$3:$I$292),0) +IFERROR(R5/_xludf.XLOOKUP(Q5,Materials!$A$3:$A$292,Materials!$I$3:$I$292),0) +IFERROR(H5/_xludf.XLOOKUP(G5,Materials!$A$3:$A$292,Materials!$I$3:$I$292),0)} -> 0
A6: KR_res_sf_pre1988 | B6: GroundSlab | C6: 지면접촉 바닥 | D6: =AA6 -> #NAME? | E6: =IFERROR(1/AB6, "Not enough information entered") -> Not enough information entered | F6: KR_res_sf_pre1988_GroundSlab | G6: 철근콘크리트 | H6: 0.18 | I6: 시멘트몰탈 | J6: 0.03 | U6: Korean Energy Saving Design Standards (derived) | V6: =H6+J6+L6+N6+P6+R6+T6 -> 0.21 | W6: 0 | X6: 0 | Y6: 10 | AA6: ="[" & _xludf.TEXTJOIN(",",TRUE,G6:T6) & "]" -> #NAME? | AB6: {=IFERROR(J6/_xludf.XLOOKUP(I6,Materials!$A$3:$A$292,Materials!$I$3:$I$292),0) +IFERROR(L6/_xludf.XLOOKUP(K6,Materials!$A$3:$A$292,Materials!$I$3:$I$292),0) +IFERROR(N6/_xludf.XLOOKUP(M6,Materials!$A$3:$A$292,Materials!$I$3:$I$292),0) +IFERROR(P6/_xludf.XLOOKUP(O6,Materials!$A$3:$A$292,Materials!$I$3:$I$292),0) +IFERROR(R6/_xludf.XLOOKUP(Q6,Materials!$A$3:$A$292,Materials!$I$3:$I$292),0) +IFERROR(H6/_xludf.XLOOKUP(G6,Materials!$A$3:$A$292,Materials!$I$3:$I$292),0)} -> 0
A7: KR_res_sf_1988_2000 | B7: Facade | C7: 외벽(외피) | D7: =AA7 -> #NAME? | E7: =IFERROR(1/AB7, "Not enough information entered") -> Not enough information entered | F7: KR_res_sf_1988_2000_Facade | G7: 압출법단열재(XPS) | H7: 0.03 | I7: 철근콘크리트 | J7: 0.18 | K7: 공기층(비통기) | L7: 0.02 | M7: 석고보드 | N7: 0.012 | U7: Korean Energy Saving Design Standards (derived) | V7: =H7+J7+L7+N7+P7+R7+T7 -> 0.242 | W7: 0 | X7: 0 | Y7: 10 | AA7: ="[" & _xludf.TEXTJOIN(",",TRUE,G7:T7) & "]" -> #NAME? | AB7: {=IFERROR(J7/_xludf.XLOOKUP(I7,Materials!$A$3:$A$292,Materials!$I$3:$I$292),0) +IFERROR(L7/_xludf.XLOOKUP(K7,Materials!$A$3:$A$292,Materials!$I$3:$I$292),0) +IFERROR(N7/_xludf.XLOOKUP(M7,Materials!$A$3:$A$292,Materials!$I$3:$I$292),0) +IFERROR(P7/_xludf.XLOOKUP(O7,Materials!$A$3:$A$292,Materials!$I$3:$I$292),0) +IFERROR(R7/_xludf.XLOOKUP(Q7,Materials!$A$3:$A$292,Materials!$I$3:$I$292),0) +IFERROR(H7/_xludf.XLOOKUP(G7,Materials!$A$3:$A$292,Materials!$I$3:$I$292),0)} -> 0
A8: KR_res_sf_1988_2000 | B8: FlatRoof | C8: 지붕(평지붕) | D8: =AA8 -> #NAME? | E8: =IFERROR(1/AB8, "Not enough information entered") -> Not enough information entered | F8: KR_res_sf_1988_2000_FlatRoof | G8: 압출법단열재(XPS) | H8: 0.047 | I8: 철근콘크리트 | J8: 0.15 | K8: 시멘트몰탈 | L8: 0.03 | U8: Korean Energy Saving Design Standards (derived) | V8: =H8+J8+L8+N8+P8+R8+T8 -> 0.227 | AA8: ="[" & _xludf.TEXTJOIN(",",TRUE,G8:T8) & "]" -> #NAME? | AB8: {=IFERROR(J8/_xludf.XLOOKUP(I8,Materials!$A$3:$A$292,Materials!$I$3:$I$292),0) +IFERROR(L8/_xludf.XLOOKUP(K8,Materials!$A$3:$A$292,Materials!$I$3:$I$292),0) +IFERROR(N8/_xludf.XLOOKUP(M8,Materials!$A$3:$A$292,Materials!$I$3:$I$292),0) +IFERROR(P8/_xludf.XLOOKUP(O8,Materials!$A$3:$A$292,Materials!$I$3:$I$292),0) +IFERROR(R8/_xludf.XLOOKUP(Q8,Materials!$A$3:$A$292,Materials!$I$3:$I$292),0) +IFERROR(H8/_xludf.XLOOKUP(G8,Materials!$A$3:$A$292,Materials!$I$3:$I$292),0)} -> 0
A9: KR_res_sf_1988_2000 | B9: AtticRoof | C9: 다락 지붕 | D9: =AA9 -> #NAME? | E9: =IFERROR(1/AB9, "Not enough information entered") -> Not enough information entered | F9: KR_res_sf_1988_2000_AtticRoof | G9: 구조용합판 | H9: 0.2 | I9: 공기층(비통기) | J9: 0.04 | K9: 석고보드 | L9: 0.012 | U9: Korean Energy Saving Design Standards (derived) | V9: =H9+J9+L9+N9+P9+R9+T9 -> 0.252 | W9: 0 | X9: 0 | Y9: 10 | AA9: ="[" & _xludf.TEXTJOIN(",",TRUE,G9:T9) & "]" -> #NAME? | AB9: {=IFERROR(J9/_xludf.XLOOKUP(I9,Materials!$A$3:$A$292,Materials!$I$3:$I$292),0) +IFERROR(L9/_xludf.XLOOKUP(K9,Materials!$A$3:$A$292,Materials!$I$3:$I$292),0) +IFERROR(N9/_xludf.XLOOKUP(M9,Materials!$A$3:$A$292,Materials!$I$3:$I$292),0) +IFERROR(P9/_xludf.XLOOKUP(O9,Materials!$A$3:$A$292,Materials!$I$3:$I$292),0) +IFERROR(R9/_xludf.XLOOKUP(Q9,Materials!$A$3:$A$292,Materials!$I$3:$I$292),0) +IFERROR(H9/_xludf.XLOOKUP(G9,Materials!$A$3:$A$292,Materials!$I$3:$I$292),0)} -> 0
A10: KR_res_sf_1988_2000 | B10: GroundSlab | C10: 지면접촉 바닥 | D10: =AA10 -> #NAME? | E10: =IFERROR(1/AB10, "Not enough information entered") -> Not enough information entered | F10: KR_res_sf_1988_2000_GroundSlab | G10: 철근콘크리트 | H10: 0.18 | I10: 시멘트몰탈 | J10: 0.03 | U10: Korean Energy Saving Design Standards (derived) | V10: =H10+J10+L10+N10+P10+R10+T10 -> 0.21 | W10: 0 | X10: 0 | Y10: 10 | AA10: ="[" & _xludf.TEXTJOIN(",",TRUE,G10:T10) & "]" -> #NAME? | AB10: {=IFERROR(J10/_xludf.XLOOKUP(I10,Materials!$A$3:$A$292,Materials!$I$3:$I$292),0) +IFERROR(L10/_xludf.XLOOKUP(K10,Materials!$A$3:$A$292,Materials!$I$3:$I$292),0) +IFERROR(N10/_xludf.XLOOKUP(M10,Materials!$A$3:$A$292,Materials!$I$3:$I$292),0) +IFERROR(P10/_xludf.XLOOKUP(O10,Materials!$A$3:$A$292,Materials!$I$3:$I$292),0) +IFERROR(R10/_xludf.XLOOKUP(Q10,Materials!$A$3:$A$292,Materials!$I$3:$I$292),0) +IFERROR(H10/_xludf.XLOOKUP(G10,Materials!$A$3:$A$292,Materials!$I$3:$I$292),0)} -> 0
A11: KR_res_sf_2001_2010 | B11: Facade | C11: 외벽(외피) | D11: =AA11 -> #NAME? | E11: =IFERROR(1/AB11, "Not enough information entered") -> Not enough information entered | F11: KR_res_sf_2001_2010_Facade | G11: 압출법단열재(XPS) | H11: 0.04 | I11: 철근콘크리트 | J11: 0.18 | K11: 공기층(비통기) | L11: 0.02 | M11: 석고보드 | N11: 0.012 | U11: Korean Energy Saving Design Standards (derived) | V11: =H11+J11+L11+N11+P11+R11+T11 -> 0.252 | W11: 0 | X11: 0 | Y11: 10 | AA11: ="[" & _xludf.TEXTJOIN(",",TRUE,G11:T11) & "]" -> #NAME? | AB11: {=IFERROR(J11/_xludf.XLOOKUP(I11,Materials!$A$3:$A$292,Materials!$I$3:$I$292),0) +IFERROR(L11/_xludf.XLOOKUP(K11,Materials!$A$3:$A$292,Materials!$I$3:$I$292),0) +IFERROR(N11/_xludf.XLOOKUP(M11,Materials!$A$3:$A$292,Materials!$I$3:$I$292),0) +IFERROR(P11/_xludf.XLOOKUP(O11,Materials!$A$3:$A$292,Materials!$I$3:$I$292),0) +IFERROR(R11/_xludf.XLOOKUP(Q11,Materials!$A$3:$A$292,Materials!$I$3:$I$292),0) +IFERROR(H11/_xludf.XLOOKUP(G11,Materials!$A$3:$A$292,Materials!$I$3:$I$292),0)} -> 0
A12: KR_res_sf_2001_2010 | B12: FlatRoof | C12: 지붕(평지붕) | D12: =AA12 -> #NAME? | E12: =IFERROR(1/AB12, "Not enough information entered") -> Not enough information entered | F12: KR_res_sf_2001_2010_FlatRoof | G12: 압출법단열재(XPS) | H12: 0.059 | I12: 철근콘크리트 | J12: 0.15 | K12: 시멘트몰탈 | L12: 0.03 | U12: Korean Energy Saving Design Standards (derived) | V12: =H12+J12+L12+N12+P12+R12+T12 -> 0.239 | AA12: ="[" & _xludf.TEXTJOIN(",",TRUE,G12:T12) & "]" -> #NAME? | AB12: {=IFERROR(J12/_xludf.XLOOKUP(I12,Materials!$A$3:$A$292,Materials!$I$3:$I$292),0) +IFERROR(L12/_xludf.XLOOKUP(K12,Materials!$A$3:$A$292,Materials!$I$3:$I$292),0) +IFERROR(N12/_xludf.XLOOKUP(M12,Materials!$A$3:$A$292,Materials!$I$3:$I$292),0) +IFERROR(P12/_xludf.XLOOKUP(O12,Materials!$A$3:$A$292,Materials!$I$3:$I$292),0) +IFERROR(R12/_xludf.XLOOKUP(Q12,Materials!$A$3:$A$292,Materials!$I$3:$I$292),0) +IFERROR(H12/_xludf.XLOOKUP(G12,Materials!$A$3:$A$292,Materials!$I$3:$I$292),0)} -> 0
A13: KR_res_sf_2001_2010 | B13: AtticRoof | C13: 다락 지붕 | D13: =AA13 -> #NAME? | E13: =IFERROR(1/AB13, "Not enough information entered") -> Not enough information entered | F13: KR_res_sf_2001_2010_AtticRoof | G13: 구조용합판 | H13: 0.2 | I13: 공기층(비통기) | J13: 0.04 | K13: 석고보드 | L13: 0.012 | U13: Korean Energy Saving Design Standards (derived) | V13: =H13+J13+L13+N13+P13+R13+T13 -> 0.252 | W13: 0 | X13: 0 | Y13: 10 | AA13: ="[" & _xludf.TEXTJOIN(",",TRUE,G13:T13) & "]" -> #NAME? | AB13: {=IFERROR(J13/_xludf.XLOOKUP(I13,Materials!$A$3:$A$292,Materials!$I$3:$I$292),0) +IFERROR(L13/_xludf.XLOOKUP(K13,Materials!$A$3:$A$292,Materials!$I$3:$I$292),0) +IFERROR(N13/_xludf.XLOOKUP(M13,Materials!$A$3:$A$292,Materials!$I$3:$I$292),0) +IFERROR(P13/_xludf.XLOOKUP(O13,Materials!$A$3:$A$292,Materials!$I$3:$I$292),0) +IFERROR(R13/_xludf.XLOOKUP(Q13,Materials!$A$3:$A$292,Materials!$I$3:$I$292),0) +IFERROR(H13/_xludf.XLOOKUP(G13,Materials!$A$3:$A$292,Materials!$I$3:$I$292),0)} -> 0
A14: KR_res_sf_2001_2010 | B14: GroundSlab | C14: 지면접촉 바닥 | D14: =AA14 -> #NAME? | E14: =IFERROR(1/AB14, "Not enough information entered") -> Not enough information entered | F14: KR_res_sf_2001_2010_GroundSlab | G14: 압출법단열재(XPS) | H14: 0.03 | I14: 철근콘크리트 | J14: 0.18 | K14: 시멘트몰탈 | L14: 0.03 | U14: Korean Energy Saving Design Standards (derived) | V14: =H14+J14+L14+N14+P14+R14+T14 -> 0.24 | W14: 0 | X14: 0 | Y14: 10 | AA14: ="[" & _xludf.TEXTJOIN(",",TRUE,G14:T14) & "]" -> #NAME? | AB14: {=IFERROR(J14/_xludf.XLOOKUP(I14,Materials!$A$3:$A$292,Materials!$I$3:$I$292),0) +IFERROR(L14/_xludf.XLOOKUP(K14,Materials!$A$3:$A$292,Materials!$I$3:$I$292),0) +IFERROR(N14/_xludf.XLOOKUP(M14,Materials!$A$3:$A$292,Materials!$I$3:$I$292),0) +IFERROR(P14/_xludf.XLOOKUP(O14,Materials!$A$3:$A$292,Materials!$I$3:$I$292),0) +IFERROR(R14/_xludf.XLOOKUP(Q14,Materials!$A$3:$A$292,Materials!$I$3:$I$292),0) +IFERROR(H14/_xludf.XLOOKUP(G14,Materials!$A$3:$A$292,Materials!$I$3:$I$292),0)} -> 0
A15: KR_res_sf_2011_2018 | B15: Facade | C15: 외벽(외피) | D15: =AA15 -> #NAME? | E15: =IFERROR(1/AB15, "Not enough information entered") -> Not enough information entered | F15: KR_res_sf_2011_2018_Facade | G15: 압출법단열재(XPS) | H15: 0.06 | I15: 철근콘크리트 | J15: 0.18 | K15: 공기층(비통기) | L15: 0.02 | M15: 석고보드 | N15: 0.012 | U15: Korean Energy Saving Design Standards (derived) | V15: =H15+J15+L15+N15+P15+R15+T15 -> 0.272 | W15: 0 | X15: 0 | Y15: 10 | AA15: ="[" & _xludf.TEXTJOIN(",",TRUE,G15:T15) & "]" -> #NAME? | AB15: {=IFERROR(J15/_xludf.XLOOKUP(I15,Materials!$A$3:$A$292,Materials!$I$3:$I$292),0) +IFERROR(L15/_xludf.XLOOKUP(K15,Materials!$A$3:$A$292,Materials!$I$3:$I$292),0) +IFERROR(N15/_xludf.XLOOKUP(M15,Materials!$A$3:$A$292,Materials!$I$3:$I$292),0) +IFERROR(P15/_xludf.XLOOKUP(O15,Materials!$A$3:$A$292,Materials!$I$3:$I$292),0) +IFERROR(R15/_xludf.XLOOKUP(Q15,Materials!$A$3:$A$292,Materials!$I$3:$I$292),0) +IFERROR(H15/_xludf.XLOOKUP(G15,Materials!$A$3:$A$292,Materials!$I$3:$I$292),0)} -> 0
A16: KR_res_sf_2011_2018 | B16: FlatRoof | C16: 지붕(평지붕) | D16: =AA16 -> #NAME? | E16: =IFERROR(1/AB16, "Not enough information entered") -> Not enough information entered | F16: KR_res_sf_2011_2018_FlatRoof | G16: 압출법단열재(XPS) | H16: 0.078 | I16: 철근콘크리트 | J16: 0.15 | K16: 시멘트몰탈 | L16: 0.03 | U16: Korean Energy Saving Design Standards (derived) | V16: =H16+J16+L16+N16+P16+R16+T16 -> 0.258 | AA16: ="[" & _xludf.TEXTJOIN(",",TRUE,G16:T16) & "]" -> #NAME? | AB16: {=IFERROR(J16/_xludf.XLOOKUP(I16,Materials!$A$3:$A$292,Materials!$I$3:$I$292),0) +IFERROR(L16/_xludf.XLOOKUP(K16,Materials!$A$3:$A$292,Materials!$I$3:$I$292),0) +IFERROR(N16/_xludf.XLOOKUP(M16,Materials!$A$3:$A$292,Materials!$I$3:$I$292),0) +IFERROR(P16/_xludf.XLOOKUP(O16,Materials!$A$3:$A$292,Materials!$I$3:$I$292),0) +IFERROR(R16/_xludf.XLOOKUP(Q16,Materials!$A$3:$A$292,Materials!$I$3:$I$292),0) +IFERROR(H16/_xludf.XLOOKUP(G16,Materials!$A$3:$A$292,Materials!$I$3:$I$292),0)} -> 0
A17: KR_res_sf_2011_2018 | B17: AtticRoof | C17: 다락 지붕 | D17: =AA17 -> #NAME? | E17: =IFERROR(1/AB17, "Not enough information entered") -> Not enough information entered | F17: KR_res_sf_2011_2018_AtticRoof | G17: 구조용합판 | H17: 0.2 | I17: 공기층(비통기) | J17: 0.04 | K17: 석고보드 | L17: 0.012 | U17: Korean Energy Saving Design Standards (derived) | V17: =H17+J17+L17+N17+P17+R17+T17 -> 0.252 | W17: 0 | X17: 0 | Y17: 10 | AA17: ="[" & _xludf.TEXTJOIN(",",TRUE,G17:T17) & "]" -> #NAME? | AB17: {=IFERROR(J17/_xludf.XLOOKUP(I17,Materials!$A$3:$A$292,Materials!$I$3:$I$292),0) +IFERROR(L17/_xludf.XLOOKUP(K17,Materials!$A$3:$A$292,Materials!$I$3:$I$292),0) +IFERROR(N17/_xludf.XLOOKUP(M17,Materials!$A$3:$A$292,Materials!$I$3:$I$292),0) +IFERROR(P17/_xludf.XLOOKUP(O17,Materials!$A$3:$A$292,Materials!$I$3:$I$292),0) +IFERROR(R17/_xludf.XLOOKUP(Q17,Materials!$A$3:$A$292,Materials!$I$3:$I$292),0) +IFERROR(H17/_xludf.XLOOKUP(G17,Materials!$A$3:$A$292,Materials!$I$3:$I$292),0)} -> 0
A18: KR_res_sf_2011_2018 | B18: GroundSlab | C18: 지면접촉 바닥 | D18: =AA18 -> #NAME? | E18: =IFERROR(1/AB18, "Not enough information entered") -> Not enough information entered | F18: KR_res_sf_2011_2018_GroundSlab | G18: 압출법단열재(XPS) | H18: 0.05 | I18: 철근콘크리트 | J18: 0.18 | K18: 시멘트몰탈 | L18: 0.03 | U18: Korean Energy Saving Design Standards (derived) | V18: =H18+J18+L18+N18+P18+R18+T18 -> 0.26 | W18: 0 | X18: 0 | Y18: 10 | AA18: ="[" & _xludf.TEXTJOIN(",",TRUE,G18:T18) & "]" -> #NAME? | AB18: {=IFERROR(J18/_xludf.XLOOKUP(I18,Materials!$A$3:$A$292,Materials!$I$3:$I$292),0) +IFERROR(L18/_xludf.XLOOKUP(K18,Materials!$A$3:$A$292,Materials!$I$3:$I$292),0) +IFERROR(N18/_xludf.XLOOKUP(M18,Materials!$A$3:$A$292,Materials!$I$3:$I$292),0) +IFERROR(P18/_xludf.XLOOKUP(O18,Materials!$A$3:$A$292,Materials!$I$3:$I$292),0) +IFERROR(R18/_xludf.XLOOKUP(Q18,Materials!$A$3:$A$292,Materials!$I$3:$I$292),0) +IFERROR(H18/_xludf.XLOOKUP(G18,Materials!$A$3:$A$292,Materials!$I$3:$I$292),0)} -> 0
A19: KR_res_sf_post2019 | B19: Facade | C19: 외벽(외피) | D19: =AA19 -> #NAME? | E19: =IFERROR(1/AB19, "Not enough information entered") -> Not enough information entered | F19: KR_res_sf_post2019_Facade | G19: 압출법단열재(XPS) | H19: 0.069 | I19: 철근콘크리트 | J19: 0.18 | K19: 공기층(비통기) | L19: 0.02 | M19: 석고보드 | N19: 0.012 | U19: Korean Energy Saving Design Standards (derived) | V19: =H19+J19+L19+N19+P19+R19+T19 -> 0.281 | W19: 0 | X19: 0 | Y19: 10 | AA19: ="[" & _xludf.TEXTJOIN(",",TRUE,G19:T19) & "]" -> #NAME? | AB19: {=IFERROR(J19/_xludf.XLOOKUP(I19,Materials!$A$3:$A$292,Materials!$I$3:$I$292),0) +IFERROR(L19/_xludf.XLOOKUP(K19,Materials!$A$3:$A$292,Materials!$I$3:$I$292),0) +IFERROR(N19/_xludf.XLOOKUP(M19,Materials!$A$3:$A$292,Materials!$I$3:$I$292),0) +IFERROR(P19/_xludf.XLOOKUP(O19,Materials!$A$3:$A$292,Materials!$I$3:$I$292),0) +IFERROR(R19/_xludf.XLOOKUP(Q19,Materials!$A$3:$A$292,Materials!$I$3:$I$292),0) +IFERROR(H19/_xludf.XLOOKUP(G19,Materials!$A$3:$A$292,Materials!$I$3:$I$292),0)} -> 0
A20: KR_res_sf_post2019 | B20: FlatRoof | C20: 지붕(평지붕) | D20: =AA20 -> #NAME? | E20: =IFERROR(1/AB20, "Not enough information entered") -> Not enough information entered | F20: KR_res_sf_post2019_FlatRoof | G20: 압출법단열재(XPS) | H20: 0.094 | I20: 철근콘크리트 | J20: 0.15 | K20: 시멘트몰탈 | L20: 0.03 | U20: Korean Energy Saving Design Standards (derived) | V20: =H20+J20+L20+N20+P20+R20+T20 -> 0.274 | AA20: ="[" & _xludf.TEXTJOIN(",",TRUE,G20:T20) & "]" -> #NAME? | AB20: {=IFERROR(J20/_xludf.XLOOKUP(I20,Materials!$A$3:$A$292,Materials!$I$3:$I$292),0) +IFERROR(L20/_xludf.XLOOKUP(K20,Materials!$A$3:$A$292,Materials!$I$3:$I$292),0) +IFERROR(N20/_xludf.XLOOKUP(M20,Materials!$A$3:$A$292,Materials!$I$3:$I$292),0) +IFERROR(P20/_xludf.XLOOKUP(O20,Materials!$A$3:$A$292,Materials!$I$3:$I$292),0) +IFERROR(R20/_xludf.XLOOKUP(Q20,Materials!$A$3:$A$292,Materials!$I$3:$I$292),0) +IFERROR(H20/_xludf.XLOOKUP(G20,Materials!$A$3:$A$292,Materials!$I$3:$I$292),0)} -> 0
A21: KR_res_sf_post2019 | B21: AtticRoof | C21: 다락 지붕 | D21: =AA21 -> #NAME? | E21: =IFERROR(1/AB21, "Not enough information entered") -> Not enough information entered | F21: KR_res_sf_post2019_AtticRoof | G21: 압출법단열재(XPS) | H21: 0.004 | I21: 구조용합판 | J21: 0.2 | K21: 공기층(비통기) | L21: 0.04 | M21: 석고보드 | N21: 0.012 | U21: Korean Energy Saving Design Standards (derived) | V21: =H21+J21+L21+N21+P21+R21+T21 -> 0.256 | W21: 0 | X21: 0 | Y21: 10 | AA21: ="[" & _xludf.TEXTJOIN(",",TRUE,G21:T21) & "]" -> #NAME? | AB21: {=IFERROR(J21/_xludf.XLOOKUP(I21,Materials!$A$3:$A$292,Materials!$I$3:$I$292),0) +IFERROR(L21/_xludf.XLOOKUP(K21,Materials!$A$3:$A$292,Materials!$I$3:$I$292),0) +IFERROR(N21/_xludf.XLOOKUP(M21,Materials!$A$3:$A$292,Materials!$I$3:$I$292),0) +IFERROR(P21/_xludf.XLOOKUP(O21,Materials!$A$3:$A$292,Materials!$I$3:$I$292),0) +IFERROR(R21/_xludf.XLOOKUP(Q21,Materials!$A$3:$A$292,Materials!$I$3:$I$292),0) +IFERROR(H21/_xludf.XLOOKUP(G21,Materials!$A$3:$A$292,Materials!$I$3:$I$292),0)} -> 0
A22: KR_res_sf_post2019 | B22: GroundSlab | C22: 지면접촉 바닥 | D22: =AA22 -> #NAME? | E22: =IFERROR(1/AB22, "Not enough information entered") -> Not enough information entered | F22: KR_res_sf_post2019_GroundSlab | G22: 압출법단열재(XPS) | H22: 0.093 | I22: 철근콘크리트 | J22: 0.18 | K22: 시멘트몰탈 | L22: 0.03 | U22: Korean Energy Saving Design Standards (derived) | V22: =H22+J22+L22+N22+P22+R22+T22 -> 0.303 | W22: 0 | X22: 0 | Y22: 10 | AA22: ="[" & _xludf.TEXTJOIN(",",TRUE,G22:T22) & "]" -> #NAME? | AB22: {=IFERROR(J22/_xludf.XLOOKUP(I22,Materials!$A$3:$A$292,Materials!$I$3:$I$292),0) +IFERROR(L22/_xludf.XLOOKUP(K22,Materials!$A$3:$A$292,Materials!$I$3:$I$292),0) +IFERROR(N22/_xludf.XLOOKUP(M22,Materials!$A$3:$A$292,Materials!$I$3:$I$292),0) +IFERROR(P22/_xludf.XLOOKUP(O22,Materials!$A$3:$A$292,Materials!$I$3:$I$292),0) +IFERROR(R22/_xludf.XLOOKUP(Q22,Materials!$A$3:$A$292,Materials!$I$3:$I$292),0) +IFERROR(H22/_xludf.XLOOKUP(G22,Materials!$A$3:$A$292,Materials!$I$3:$I$292),0)} -> 0
A23: KR_res_sf | B23: Partition | C23: Partition (연식 무관) | D23: =AA23 -> #NAME? | E23: =IFERROR(1/AB23, "Not enough information entered") -> Not enough information entered | F23: KR_res_sf_Partition | G23: 석고보드 | H23: 0.0125 | I23: 공기층(비통기) | J23: 0.05 | K23: 석고보드 | L23: 0.0125 | U23: Korean Energy Saving Design Standards (derived) | V23: =H23+J23+L23+N23+P23+R23+T23 -> 0.075 | AA23: ="[" & _xludf.TEXTJOIN(",",TRUE,G23:T23) & "]" -> #NAME? | AB23: {=IFERROR(J23/_xludf.XLOOKUP(I23,Materials!$A$3:$A$292,Materials!$I$3:$I$292),0) +IFERROR(L23/_xludf.XLOOKUP(K23,Materials!$A$3:$A$292,Materials!$I$3:$I$292),0) +IFERROR(N23/_xludf.XLOOKUP(M23,Materials!$A$3:$A$292,Materials!$I$3:$I$292),0) +IFERROR(P23/_xludf.XLOOKUP(O23,Materials!$A$3:$A$292,Materials!$I$3:$I$292),0) +IFERROR(R23/_xludf.XLOOKUP(Q23,Materials!$A$3:$A$292,Materials!$I$3:$I$292),0) +IFERROR(H23/_xludf.XLOOKUP(G23,Materials!$A$3:$A$292,Materials!$I$3:$I$292),0)} -> 0
A24: KR | B24: ExternalFloor | C24: ExternalFloor (연식 무관) | D24: =AA24 -> #NAME? | E24: =IFERROR(1/AB24, "Not enough information entered") -> Not enough information entered | F24: KR_ExternalFloor | G24: 철근콘크리트 | H24: 0.18 | I24: 압출법단열재(XPS) | J24: 0.08 | K24: 시멘트몰탈 | L24: 0.03 | U24: Korean Energy Saving Design Standards (derived) | V24: =H24+J24+L24+N24+P24+R24+T24 -> 0.29 | AA24: ="[" & _xludf.TEXTJOIN(",",TRUE,G24:T24) & "]" -> #NAME? | AB24: {=IFERROR(J24/_xludf.XLOOKUP(I24,Materials!$A$3:$A$292,Materials!$I$3:$I$292),0) +IFERROR(L24/_xludf.XLOOKUP(K24,Materials!$A$3:$A$292,Materials!$I$3:$I$292),0) +IFERROR(N24/_xludf.XLOOKUP(M24,Materials!$A$3:$A$292,Materials!$I$3:$I$292),0) +IFERROR(P24/_xludf.XLOOKUP(O24,Materials!$A$3:$A$292,Materials!$I$3:$I$292),0) +IFERROR(R24/_xludf.XLOOKUP(Q24,Materials!$A$3:$A$292,Materials!$I$3:$I$292),0) +IFERROR(H24/_xludf.XLOOKUP(G24,Materials!$A$3:$A$292,Materials!$I$3:$I$292),0)} -> 0
A25: KR_res_sf | B25: FloorCeiling | C25: FloorCeiling (연식 무관) | D25: =AA25 -> #NAME? | E25: =IFERROR(1/AB25, "Not enough information entered") -> Not enough information entered | F25: KR_res_sf_FloorCeiling | G25: 철근콘크리트 | H25: 0.18 | I25: 시멘트몰탈 | J25: 0.03 | U25: Korean Energy Saving Design Standards (derived) | V25: =H25+J25+L25+N25+P25+R25+T25 -> 0.21 | AA25: ="[" & _xludf.TEXTJOIN(",",TRUE,G25:T25) & "]" -> #NAME? | AB25: {=IFERROR(J25/_xludf.XLOOKUP(I25,Materials!$A$3:$A$292,Materials!$I$3:$I$292),0) +IFERROR(L25/_xludf.XLOOKUP(K25,Materials!$A$3:$A$292,Materials!$I$3:$I$292),0) +IFERROR(N25/_xludf.XLOOKUP(M25,Materials!$A$3:$A$292,Materials!$I$3:$I$292),0) +IFERROR(P25/_xludf.XLOOKUP(O25,Materials!$A$3:$A$292,Materials!$I$3:$I$292),0) +IFERROR(R25/_xludf.XLOOKUP(Q25,Materials!$A$3:$A$292,Materials!$I$3:$I$292),0) +IFERROR(H25/_xludf.XLOOKUP(G25,Materials!$A$3:$A$292,Materials!$I$3:$I$292),0)} -> 0
A26: KR_res_sf | B26: GroundWall | C26: GroundWall (연식 무관) | D26: =AA26 -> #NAME? | E26: =IFERROR(1/AB26, "Not enough information entered") -> Not enough information entered | F26: KR_res_sf_GroundWall | G26: 철근콘크리트 | H26: 0.2 | I26: 압출법단열재(XPS) | J26: 0.05 | U26: Korean Energy Saving Design Standards (derived) | V26: =H26+J26+L26+N26+P26+R26+T26 -> 0.25 | AA26: ="[" & _xludf.TEXTJOIN(",",TRUE,G26:T26) & "]" -> #NAME? | AB26: {=IFERROR(J26/_xludf.XLOOKUP(I26,Materials!$A$3:$A$292,Materials!$I$3:$I$292),0) +IFERROR(L26/_xludf.XLOOKUP(K26,Materials!$A$3:$A$292,Materials!$I$3:$I$292),0) +IFERROR(N26/_xludf.XLOOKUP(M26,Materials!$A$3:$A$292,Materials!$I$3:$I$292),0) +IFERROR(P26/_xludf.XLOOKUP(O26,Materials!$A$3:$A$292,Materials!$I$3:$I$292),0) +IFERROR(R26/_xludf.XLOOKUP(Q26,Materials!$A$3:$A$292,Materials!$I$3:$I$292),0) +IFERROR(H26/_xludf.XLOOKUP(G26,Materials!$A$3:$A$292,Materials!$I$3:$I$292),0)} -> 0
C27: InternalMass (연식 무관)
A28: KR_res_sf | B28: BasementCeiling | C28: BasementCeiling (연식 무관) | D28: =AA28 -> #NAME? | E28: =IFERROR(1/AB28, "Not enough information entered") -> Not enough information entered | F28: KR_res_sf_BasementCeiling | G28: 철근콘크리트 | H28: 0.18 | I28: 비드법단열재(EPS) | J28: 0.06 | K28: 석고보드 | L28: 0.0125 | U28: Korean Energy Saving Design Standards (derived) | V28: =H28+J28+L28+N28+P28+R28+T28 -> 0.2525 | AA28: ="[" & _xludf.TEXTJOIN(",",TRUE,G28:T28) & "]" -> #NAME? | AB28: {=IFERROR(J28/_xludf.XLOOKUP(I28,Materials!$A$3:$A$292,Materials!$I$3:$I$292),0) +IFERROR(L28/_xludf.XLOOKUP(K28,Materials!$A$3:$A$292,Materials!$I$3:$I$292),0) +IFERROR(N28/_xludf.XLOOKUP(M28,Materials!$A$3:$A$292,Materials!$I$3:$I$292),0) +IFERROR(P28/_xludf.XLOOKUP(O28,Materials!$A$3:$A$292,Materials!$I$3:$I$292),0) +IFERROR(R28/_xludf.XLOOKUP(Q28,Materials!$A$3:$A$292,Materials!$I$3:$I$292),0) +IFERROR(H28/_xludf.XLOOKUP(G28,Materials!$A$3:$A$292,Materials!$I$3:$I$292),0)} -> 0
A29: KR | B29: AtticFloor | C29: AtticFloor (연식 무관) | D29: =AA29 -> #NAME? | E29: =IFERROR(1/AB29, "Not enough information entered") -> Not enough information entered | F29: KR_AtticFloor | G29: 구조용합판 | H29: 0.018 | I29: 미네랄울 | J29: 0.12 | K29: 석고보드 | L29: 0.0125 | U29: Korean Energy Saving Design Standards (derived) | V29: =H29+J29+L29+N29+P29+R29+T29 -> 0.1505 | AA29: ="[" & _xludf.TEXTJOIN(",",TRUE,G29:T29) & "]" -> #NAME? | AB29: {=IFERROR(J29/_xludf.XLOOKUP(I29,Materials!$A$3:$A$292,Materials!$I$3:$I$292),0) +IFERROR(L29/_xludf.XLOOKUP(K29,Materials!$A$3:$A$292,Materials!$I$3:$I$292),0) +IFERROR(N29/_xludf.XLOOKUP(M29,Materials!$A$3:$A$292,Materials!$I$3:$I$292),0) +IFERROR(P29/_xludf.XLOOKUP(O29,Materials!$A$3:$A$292,Materials!$I$3:$I$292),0) +IFERROR(R29/_xludf.XLOOKUP(Q29,Materials!$A$3:$A$292,Materials!$I$3:$I$292),0) +IFERROR(H29/_xludf.XLOOKUP(G29,Materials!$A$3:$A$292,Materials!$I$3:$I$292),0)} -> 0
A30: KR_res_mf_low_pre1988 | B30: Facade | C30: 외벽(외피) | D30: =AA30 -> #NAME? | E30: =IFERROR(1/AB30, "Not enough information entered") -> Not enough information entered | F30: KR_res_mf_low_pre1988_Facade | G30: 철근콘크리트 | H30: 0.18 | I30: 공기층(비통기) | J30: 0.02 | K30: 석고보드 | L30: 0.012 | U30: Korean Energy Saving Design Standards (derived) | V30: =H30+J30+L30+N30+P30+R30+T30 -> 0.212 | W30: 0 | X30: 0 | Y30: 10 | AA30: ="[" & _xludf.TEXTJOIN(",",TRUE,G30:T30) & "]" -> #NAME? | AB30: {=IFERROR(J30/_xludf.XLOOKUP(I30,Materials!$A$3:$A$292,Materials!$I$3:$I$292),0) +IFERROR(L30/_xludf.XLOOKUP(K30,Materials!$A$3:$A$292,Materials!$I$3:$I$292),0) +IFERROR(N30/_xludf.XLOOKUP(M30,Materials!$A$3:$A$292,Materials!$I$3:$I$292),0) +IFERROR(P30/_xludf.XLOOKUP(O30,Materials!$A$3:$A$292,Materials!$I$3:$I$292),0) +IFERROR(R30/_xludf.XLOOKUP(Q30,Materials!$A$3:$A$292,Materials!$I$3:$I$292),0) +IFERROR(H30/_xludf.XLOOKUP(G30,Materials!$A$3:$A$292,Materials!$I$3:$I$292),0)} -> 0
A31: KR_res_mf_low_pre1988 | B31: FlatRoof | C31: 지붕(평지붕) | D31: =AA31 -> #NAME? | E31: =IFERROR(1/AB31, "Not enough information entered") -> Not enough information entered | F31: KR_res_mf_low_pre1988_FlatRoof | G31: 철근콘크리트 | H31: 0.15 | I31: 시멘트몰탈 | J31: 0.03 | U31: Korean Energy Saving Design Standards (derived) | V31: =H31+J31+L31+N31+P31+R31+T31 -> 0.18 | AA31: ="[" & _xludf.TEXTJOIN(",",TRUE,G31:T31) & "]" -> #NAME? | AB31: {=IFERROR(J31/_xludf.XLOOKUP(I31,Materials!$A$3:$A$292,Materials!$I$3:$I$292),0) +IFERROR(L31/_xludf.XLOOKUP(K31,Materials!$A$3:$A$292,Materials!$I$3:$I$292),0) +IFERROR(N31/_xludf.XLOOKUP(M31,Materials!$A$3:$A$292,Materials!$I$3:$I$292),0) +IFERROR(P31/_xludf.XLOOKUP(O31,Materials!$A$3:$A$292,Materials!$I$3:$I$292),0) +IFERROR(R31/_xludf.XLOOKUP(Q31,Materials!$A$3:$A$292,Materials!$I$3:$I$292),0) +IFERROR(H31/_xludf.XLOOKUP(G31,Materials!$A$3:$A$292,Materials!$I$3:$I$292),0)} -> 0
A32: KR_res_mf_low_pre1988 | B32: GroundSlab | C32: 지면접촉 바닥 | D32: =AA32 -> #NAME? | E32: =IFERROR(1/AB32, "Not enough information entered") -> Not enough information entered | F32: KR_res_mf_low_pre1988_GroundSlab | G32: 철근콘크리트 | H32: 0.18 | I32: 시멘트몰탈 | J32: 0.03 | U32: Korean Energy Saving Design Standards (derived) | V32: =H32+J32+L32+N32+P32+R32+T32 -> 0.21 | W32: 0 | X32: 0 | Y32: 10 | AA32: ="[" & _xludf.TEXTJOIN(",",TRUE,G32:T32) & "]" -> #NAME? | AB32: {=IFERROR(J32/_xludf.XLOOKUP(I32,Materials!$A$3:$A$292,Materials!$I$3:$I$292),0) +IFERROR(L32/_xludf.XLOOKUP(K32,Materials!$A$3:$A$292,Materials!$I$3:$I$292),0) +IFERROR(N32/_xludf.XLOOKUP(M32,Materials!$A$3:$A$292,Materials!$I$3:$I$292),0) +IFERROR(P32/_xludf.XLOOKUP(O32,Materials!$A$3:$A$292,Materials!$I$3:$I$292),0) +IFERROR(R32/_xludf.XLOOKUP(Q32,Materials!$A$3:$A$292,Materials!$I$3:$I$292),0) +IFERROR(H32/_xludf.XLOOKUP(G32,Materials!$A$3:$A$292,Materials!$I$3:$I$292),0)} -> 0
A33: KR_res_mf_low_1988_2000 | B33: Facade | C33: 외벽(외피) | D33: =AA33 -> #NAME? | E33: =IFERROR(1/AB33, "Not enough information entered") -> Not enough information entered | F33: KR_res_mf_low_1988_2000_Facade | G33: 압출법단열재(XPS) | H33: 0.03 | I33: 철근콘크리트 | J33: 0.18 | K33: 공기층(비통기) | L33: 0.02 | M33: 석고보드 | N33: 0.012 | U33: Korean Energy Saving Design Standards (derived) | V33: =H33+J33+L33+N33+P33+R33+T33 -> 0.242 | W33: 0 | X33: 0 | Y33: 10 | AA33: ="[" & _xludf.TEXTJOIN(",",TRUE,G33:T33) & "]" -> #NAME? | AB33: {=IFERROR(J33/_xludf.XLOOKUP(I33,Materials!$A$3:$A$292,Materials!$I$3:$I$292),0) +IFERROR(L33/_xludf.XLOOKUP(K33,Materials!$A$3:$A$292,Materials!$I$3:$I$292),0) +IFERROR(N33/_xludf.XLOOKUP(M33,Materials!$A$3:$A$292,Materials!$I$3:$I$292),0) +IFERROR(P33/_xludf.XLOOKUP(O33,Materials!$A$3:$A$292,Materials!$I$3:$I$292),0) +IFERROR(R33/_xludf.XLOOKUP(Q33,Materials!$A$3:$A$292,Materials!$I$3:$I$292),0) +IFERROR(H33/_xludf.XLOOKUP(G33,Materials!$A$3:$A$292,Materials!$I$3:$I$292),0)} -> 0
A34: KR_res_mf_low_1988_2000 | B34: FlatRoof | C34: 지붕(평지붕) | D34: =AA34 -> #NAME? | E34: =IFERROR(1/AB34, "Not enough information entered") -> Not enough information entered | F34: KR_res_mf_low_1988_2000_FlatRoof | G34: 압출법단열재(XPS) | H34: 0.058 | I34: 철근콘크리트 | J34: 0.15 | K34: 시멘트몰탈 | L34: 0.03 | U34: Korean Energy Saving Design Standards (derived) | V34: =H34+J34+L34+N34+P34+R34+T34 -> 0.238 | AA34: ="[" & _xludf.TEXTJOIN(",",TRUE,G34:T34) & "]" -> #NAME? | AB34: {=IFERROR(J34/_xludf.XLOOKUP(I34,Materials!$A$3:$A$292,Materials!$I$3:$I$292),0) +IFERROR(L34/_xludf.XLOOKUP(K34,Materials!$A$3:$A$292,Materials!$I$3:$I$292),0) +IFERROR(N34/_xludf.XLOOKUP(M34,Materials!$A$3:$A$292,Materials!$I$3:$I$292),0) +IFERROR(P34/_xludf.XLOOKUP(O34,Materials!$A$3:$A$292,Materials!$I$3:$I$292),0) +IFERROR(R34/_xludf.XLOOKUP(Q34,Materials!$A$3:$A$292,Materials!$I$3:$I$292),0) +IFERROR(H34/_xludf.XLOOKUP(G34,Materials!$A$3:$A$292,Materials!$I$3:$I$292),0)} -> 0
A35: KR_res_mf_low_1988_2000 | B35: GroundSlab | C35: 지면접촉 바닥 | D35: =AA35 -> #NAME? | E35: =IFERROR(1/AB35, "Not enough information entered") -> Not enough information entered | F35: KR_res_mf_low_1988_2000_GroundSlab | G35: 압출법단열재(XPS) | H35: 0.047 | I35: 철근콘크리트 | J35: 0.18 | K35: 시멘트몰탈 | L35: 0.03 | U35: Korean Energy Saving Design Standards (derived) | V35: =H35+J35+L35+N35+P35+R35+T35 -> 0.257 | W35: 0 | X35: 0 | Y35: 10 | AA35: ="[" & _xludf.TEXTJOIN(",",TRUE,G35:T35) & "]" -> #NAME? | AB35: {=IFERROR(J35/_xludf.XLOOKUP(I35,Materials!$A$3:$A$292,Materials!$I$3:$I$292),0) +IFERROR(L35/_xludf.XLOOKUP(K35,Materials!$A$3:$A$292,Materials!$I$3:$I$292),0) +IFERROR(N35/_xludf.XLOOKUP(M35,Materials!$A$3:$A$292,Materials!$I$3:$I$292),0) +IFERROR(P35/_xludf.XLOOKUP(O35,Materials!$A$3:$A$292,Materials!$I$3:$I$292),0) +IFERROR(R35/_xludf.XLOOKUP(Q35,Materials!$A$3:$A$292,Materials!$I$3:$I$292),0) +IFERROR(H35/_xludf.XLOOKUP(G35,Materials!$A$3:$A$292,Materials!$I$3:$I$292),0)} -> 0
A36: KR_res_mf_low_2001_2010 | B36: Facade | C36: 외벽(외피) | D36: =AA36 -> #NAME? | E36: =IFERROR(1/AB36, "Not enough information entered") -> Not enough information entered | F36: KR_res_mf_low_2001_2010_Facade | G36: 압출법단열재(XPS) | H36: 0.04 | I36: 철근콘크리트 | J36: 0.18 | K36: 공기층(비통기) | L36: 0.02 | M36: 석고보드 | N36: 0.012 | U36: Korean Energy Saving Design Standards (derived) | V36: =H36+J36+L36+N36+P36+R36+T36 -> 0.252 | W36: 0 | X36: 0 | Y36: 10 | AA36: ="[" & _xludf.TEXTJOIN(",",TRUE,G36:T36) & "]" -> #NAME? | AB36: {=IFERROR(J36/_xludf.XLOOKUP(I36,Materials!$A$3:$A$292,Materials!$I$3:$I$292),0) +IFERROR(L36/_xludf.XLOOKUP(K36,Materials!$A$3:$A$292,Materials!$I$3:$I$292),0) +IFERROR(N36/_xludf.XLOOKUP(M36,Materials!$A$3:$A$292,Materials!$I$3:$I$292),0) +IFERROR(P36/_xludf.XLOOKUP(O36,Materials!$A$3:$A$292,Materials!$I$3:$I$292),0) +IFERROR(R36/_xludf.XLOOKUP(Q36,Materials!$A$3:$A$292,Materials!$I$3:$I$292),0) +IFERROR(H36/_xludf.XLOOKUP(G36,Materials!$A$3:$A$292,Materials!$I$3:$I$292),0)} -> 0
A37: KR_res_mf_low_2001_2010 | B37: FlatRoof | C37: 지붕(평지붕) | D37: =AA37 -> #NAME? | E37: =IFERROR(1/AB37, "Not enough information entered") -> Not enough information entered | F37: KR_res_mf_low_2001_2010_FlatRoof | G37: 압출법단열재(XPS) | H37: 0.059 | I37: 철근콘크리트 | J37: 0.15 | K37: 시멘트몰탈 | L37: 0.03 | U37: Korean Energy Saving Design Standards (derived) | V37: =H37+J37+L37+N37+P37+R37+T37 -> 0.239 | AA37: ="[" & _xludf.TEXTJOIN(",",TRUE,G37:T37) & "]" -> #NAME? | AB37: {=IFERROR(J37/_xludf.XLOOKUP(I37,Materials!$A$3:$A$292,Materials!$I$3:$I$292),0) +IFERROR(L37/_xludf.XLOOKUP(K37,Materials!$A$3:$A$292,Materials!$I$3:$I$292),0) +IFERROR(N37/_xludf.XLOOKUP(M37,Materials!$A$3:$A$292,Materials!$I$3:$I$292),0) +IFERROR(P37/_xludf.XLOOKUP(O37,Materials!$A$3:$A$292,Materials!$I$3:$I$292),0) +IFERROR(R37/_xludf.XLOOKUP(Q37,Materials!$A$3:$A$292,Materials!$I$3:$I$292),0) +IFERROR(H37/_xludf.XLOOKUP(G37,Materials!$A$3:$A$292,Materials!$I$3:$I$292),0)} -> 0
A38: KR_res_mf_low_2001_2010 | B38: GroundSlab | C38: 지면접촉 바닥 | D38: =AA38 -> #NAME? | E38: =IFERROR(1/AB38, "Not enough information entered") -> Not enough information entered | F38: KR_res_mf_low_2001_2010_GroundSlab | G38: 압출법단열재(XPS) | H38: 0.058 | I38: 철근콘크리트 | J38: 0.18 | K38: 시멘트몰탈 | L38: 0.03 | U38: Korean Energy Saving Design Standards (derived) | V38: =H38+J38+L38+N38+P38+R38+T38 -> 0.268 | W38: 0 | X38: 0 | Y38: 10 | AA38: ="[" & _xludf.TEXTJOIN(",",TRUE,G38:T38) & "]" -> #NAME? | AB38: {=IFERROR(J38/_xludf.XLOOKUP(I38,Materials!$A$3:$A$292,Materials!$I$3:$I$292),0) +IFERROR(L38/_xludf.XLOOKUP(K38,Materials!$A$3:$A$292,Materials!$I$3:$I$292),0) +IFERROR(N38/_xludf.XLOOKUP(M38,Materials!$A$3:$A$292,Materials!$I$3:$I$292),0) +IFERROR(P38/_xludf.XLOOKUP(O38,Materials!$A$3:$A$292,Materials!$I$3:$I$292),0) +IFERROR(R38/_xludf.XLOOKUP(Q38,Materials!$A$3:$A$292,Materials!$I$3:$I$292),0) +IFERROR(H38/_xludf.XLOOKUP(G38,Materials!$A$3:$A$292,Materials!$I$3:$I$292),0)} -> 0
A39: KR_res_mf_low_2011_2018 | B39: Facade | C39: 외벽(외피) | D39: =AA39 -> #NAME? | E39: =IFERROR(1/AB39, "Not enough information entered") -> Not enough information entered | F39: KR_res_mf_low_2011_2018_Facade | G39: 압출법단열재(XPS) | H39: 0.06 | I39: 철근콘크리트 | J39: 0.18 | K39: 공기층(비통기) | L39: 0.02 | M39: 석고보드 | N39: 0.012 | U39: Korean Energy Saving Design Standards (derived) | V39: =H39+J39+L39+N39+P39+R39+T39 -> 0.272 | W39: 0 | X39: 0 | Y39: 10 | AA39: ="[" & _xludf.TEXTJOIN(",",TRUE,G39:T39) & "]" -> #NAME? | AB39: {=IFERROR(J39/_xludf.XLOOKUP(I39,Materials!$A$3:$A$292,Materials!$I$3:$I$292),0) +IFERROR(L39/_xludf.XLOOKUP(K39,Materials!$A$3:$A$292,Materials!$I$3:$I$292),0) +IFERROR(N39/_xludf.XLOOKUP(M39,Materials!$A$3:$A$292,Materials!$I$3:$I$292),0) +IFERROR(P39/_xludf.XLOOKUP(O39,Materials!$A$3:$A$292,Materials!$I$3:$I$292),0) +IFERROR(R39/_xludf.XLOOKUP(Q39,Materials!$A$3:$A$292,Materials!$I$3:$I$292),0) +IFERROR(H39/_xludf.XLOOKUP(G39,Materials!$A$3:$A$292,Materials!$I$3:$I$292),0)} -> 0
A40: KR_res_mf_low_2011_2018 | B40: FlatRoof | C40: 지붕(평지붕) | D40: =AA40 -> #NAME? | E40: =IFERROR(1/AB40, "Not enough information entered") -> Not enough information entered | F40: KR_res_mf_low_2011_2018_FlatRoof | G40: 압출법단열재(XPS) | H40: 0.078 | I40: 철근콘크리트 | J40: 0.15 | K40: 시멘트몰탈 | L40: 0.03 | U40: Korean Energy Saving Design Standards (derived) | V40: =H40+J40+L40+N40+P40+R40+T40 -> 0.258 | AA40: ="[" & _xludf.TEXTJOIN(",",TRUE,G40:T40) & "]" -> #NAME? | AB40: {=IFERROR(J40/_xludf.XLOOKUP(I40,Materials!$A$3:$A$292,Materials!$I$3:$I$292),0) +IFERROR(L40/_xludf.XLOOKUP(K40,Materials!$A$3:$A$292,Materials!$I$3:$I$292),0) +IFERROR(N40/_xludf.XLOOKUP(M40,Materials!$A$3:$A$292,Materials!$I$3:$I$292),0) +IFERROR(P40/_xludf.XLOOKUP(O40,Materials!$A$3:$A$292,Materials!$I$3:$I$292),0) +IFERROR(R40/_xludf.XLOOKUP(Q40,Materials!$A$3:$A$292,Materials!$I$3:$I$292),0) +IFERROR(H40/_xludf.XLOOKUP(G40,Materials!$A$3:$A$292,Materials!$I$3:$I$292),0)} -> 0
A41: KR_res_mf_low_2011_2018 | B41: GroundSlab | C41: 지면접촉 바닥 | D41: =AA41 -> #NAME? | E41: =IFERROR(1/AB41, "Not enough information entered") -> Not enough information entered | F41: KR_res_mf_low_2011_2018_GroundSlab | G41: 압출법단열재(XPS) | H41: 0.077 | I41: 철근콘크리트 | J41: 0.18 | K41: 시멘트몰탈 | L41: 0.03 | U41: Korean Energy Saving Design Standards (derived) | V41: =H41+J41+L41+N41+P41+R41+T41 -> 0.287 | W41: 0 | X41: 0 | Y41: 10 | AA41: ="[" & _xludf.TEXTJOIN(",",TRUE,G41:T41) & "]" -> #NAME? | AB41: {=IFERROR(J41/_xludf.XLOOKUP(I41,Materials!$A$3:$A$292,Materials!$I$3:$I$292),0) +IFERROR(L41/_xludf.XLOOKUP(K41,Materials!$A$3:$A$292,Materials!$I$3:$I$292),0) +IFERROR(N41/_xludf.XLOOKUP(M41,Materials!$A$3:$A$292,Materials!$I$3:$I$292),0) +IFERROR(P41/_xludf.XLOOKUP(O41,Materials!$A$3:$A$292,Materials!$I$3:$I$292),0) +IFERROR(R41/_xludf.XLOOKUP(Q41,Materials!$A$3:$A$292,Materials!$I$3:$I$292),0) +IFERROR(H41/_xludf.XLOOKUP(G41,Materials!$A$3:$A$292,Materials!$I$3:$I$292),0)} -> 0
A42: KR_res_mf_low_post2019 | B42: Facade | C42: 외벽(외피) | D42: =AA42 -> #NAME? | E42: =IFERROR(1/AB42, "Not enough information entered") -> Not enough information entered | F42: KR_res_mf_low_post2019_Facade | G42: 압출법단열재(XPS) | H42: 0.069 | I42: 철근콘크리트 | J42: 0.18 | K42: 공기층(비통기) | L42: 0.02 | M42: 석고보드 | N42: 0.012 | U42: Korean Energy Saving Design Standards (derived) | V42: =H42+J42+L42+N42+P42+R42+T42 -> 0.281 | W42: 0 | X42: 0 | Y42: 10 | AA42: ="[" & _xludf.TEXTJOIN(",",TRUE,G42:T42) & "]" -> #NAME? | AB42: {=IFERROR(J42/_xludf.XLOOKUP(I42,Materials!$A$3:$A$292,Materials!$I$3:$I$292),0) +IFERROR(L42/_xludf.XLOOKUP(K42,Materials!$A$3:$A$292,Materials!$I$3:$I$292),0) +IFERROR(N42/_xludf.XLOOKUP(M42,Materials!$A$3:$A$292,Materials!$I$3:$I$292),0) +IFERROR(P42/_xludf.XLOOKUP(O42,Materials!$A$3:$A$292,Materials!$I$3:$I$292),0) +IFERROR(R42/_xludf.XLOOKUP(Q42,Materials!$A$3:$A$292,Materials!$I$3:$I$292),0) +IFERROR(H42/_xludf.XLOOKUP(G42,Materials!$A$3:$A$292,Materials!$I$3:$I$292),0)} -> 0
A43: KR_res_mf_low_post2019 | B43: FlatRoof | C43: 지붕(평지붕) | D43: =AA43 -> #NAME? | E43: =IFERROR(1/AB43, "Not enough information entered") -> Not enough information entered | F43: KR_res_mf_low_post2019_FlatRoof | G43: 압출법단열재(XPS) | H43: 0.094 | I43: 철근콘크리트 | J43: 0.15 | K43: 시멘트몰탈 | L43: 0.03 | U43: Korean Energy Saving Design Standards (derived) | V43: =H43+J43+L43+N43+P43+R43+T43 -> 0.274 | AA43: ="[" & _xludf.TEXTJOIN(",",TRUE,G43:T43) & "]" -> #NAME? | AB43: {=IFERROR(J43/_xludf.XLOOKUP(I43,Materials!$A$3:$A$292,Materials!$I$3:$I$292),0) +IFERROR(L43/_xludf.XLOOKUP(K43,Materials!$A$3:$A$292,Materials!$I$3:$I$292),0) +IFERROR(N43/_xludf.XLOOKUP(M43,Materials!$A$3:$A$292,Materials!$I$3:$I$292),0) +IFERROR(P43/_xludf.XLOOKUP(O43,Materials!$A$3:$A$292,Materials!$I$3:$I$292),0) +IFERROR(R43/_xludf.XLOOKUP(Q43,Materials!$A$3:$A$292,Materials!$I$3:$I$292),0) +IFERROR(H43/_xludf.XLOOKUP(G43,Materials!$A$3:$A$292,Materials!$I$3:$I$292),0)} -> 0
A44: KR_res_mf_low_post2019 | B44: GroundSlab | C44: 지면접촉 바닥 | D44: =AA44 -> #NAME? | E44: =IFERROR(1/AB44, "Not enough information entered") -> Not enough information entered | F44: KR_res_mf_low_post2019_GroundSlab | G44: 압출법단열재(XPS) | H44: 0.093 | I44: 철근콘크리트 | J44: 0.18 | K44: 시멘트몰탈 | L44: 0.03 | U44: Korean Energy Saving Design Standards (derived) | V44: =H44+J44+L44+N44+P44+R44+T44 -> 0.303 | W44: 0 | X44: 0 | Y44: 10 | AA44: ="[" & _xludf.TEXTJOIN(",",TRUE,G44:T44) & "]" -> #NAME? | AB44: {=IFERROR(J44/_xludf.XLOOKUP(I44,Materials!$A$3:$A$292,Materials!$I$3:$I$292),0) +IFERROR(L44/_xludf.XLOOKUP(K44,Materials!$A$3:$A$292,Materials!$I$3:$I$292),0) +IFERROR(N44/_xludf.XLOOKUP(M44,Materials!$A$3:$A$292,Materials!$I$3:$I$292),0) +IFERROR(P44/_xludf.XLOOKUP(O44,Materials!$A$3:$A$292,Materials!$I$3:$I$292),0) +IFERROR(R44/_xludf.XLOOKUP(Q44,Materials!$A$3:$A$292,Materials!$I$3:$I$292),0) +IFERROR(H44/_xludf.XLOOKUP(G44,Materials!$A$3:$A$292,Materials!$I$3:$I$292),0)} -> 0
A45: KR_res_mf_low | B45: Partition | C45: Partition (연식 무관) | D45: =AA45 -> #NAME? | E45: =IFERROR(1/AB45, "Not enough information entered") -> Not enough information entered | F45: KR_res_mf_low_Partition | G45: 석고보드 | H45: 0.0125 | I45: 공기층(비통기) | J45: 0.05 | K45: 석고보드 | L45: 0.0125 | U45: Korean Energy Saving Design Standards (derived) | V45: =H45+J45+L45+N45+P45+R45+T45 -> 0.075 | AA45: ="[" & _xludf.TEXTJOIN(",",TRUE,G45:T45) & "]" -> #NAME? | AB45: {=IFERROR(J45/_xludf.XLOOKUP(I45,Materials!$A$3:$A$292,Materials!$I$3:$I$292),0) +IFERROR(L45/_xludf.XLOOKUP(K45,Materials!$A$3:$A$292,Materials!$I$3:$I$292),0) +IFERROR(N45/_xludf.XLOOKUP(M45,Materials!$A$3:$A$292,Materials!$I$3:$I$292),0) +IFERROR(P45/_xludf.XLOOKUP(O45,Materials!$A$3:$A$292,Materials!$I$3:$I$292),0) +IFERROR(R45/_xludf.XLOOKUP(Q45,Materials!$A$3:$A$292,Materials!$I$3:$I$292),0) +IFERROR(H45/_xludf.XLOOKUP(G45,Materials!$A$3:$A$292,Materials!$I$3:$I$292),0)} -> 0
A46: KR_res_mf_low | B46: ExternalFloor | C46: ExternalFloor (연식 무관) | D46: =AA46 -> #NAME? | E46: =IFERROR(1/AB46, "Not enough information entered") -> Not enough information entered | F46: KR_res_mf_low_ExternalFloor | G46: 철근콘크리트 | H46: 0.18 | I46: 압출법단열재(XPS) | J46: 0.08 | K46: 시멘트몰탈 | L46: 0.03 | U46: Korean Energy Saving Design Standards (derived) | V46: =H46+J46+L46+N46+P46+R46+T46 -> 0.29 | AA46: ="[" & _xludf.TEXTJOIN(",",TRUE,G46:T46) & "]" -> #NAME? | AB46: {=IFERROR(J46/_xludf.XLOOKUP(I46,Materials!$A$3:$A$292,Materials!$I$3:$I$292),0) +IFERROR(L46/_xludf.XLOOKUP(K46,Materials!$A$3:$A$292,Materials!$I$3:$I$292),0) +IFERROR(N46/_xludf.XLOOKUP(M46,Materials!$A$3:$A$292,Materials!$I$3:$I$292),0) +IFERROR(P46/_xludf.XLOOKUP(O46,Materials!$A$3:$A$292,Materials!$I$3:$I$292),0) +IFERROR(R46/_xludf.XLOOKUP(Q46,Materials!$A$3:$A$292,Materials!$I$3:$I$292),0) +IFERROR(H46/_xludf.XLOOKUP(G46,Materials!$A$3:$A$292,Materials!$I$3:$I$292),0)} -> 0
A47: KR_res_mf_low | B47: FloorCeiling | C47: FloorCeiling (연식 무관) | D47: =AA47 -> #NAME? | E47: =IFERROR(1/AB47, "Not enough information entered") -> Not enough information entered | F47: KR_res_mf_low_FloorCeiling | G47: 철근콘크리트 | H47: 0.18 | I47: 시멘트몰탈 | J47: 0.03 | U47: Korean Energy Saving Design Standards (derived) | V47: =H47+J47+L47+N47+P47+R47+T47 -> 0.21 | AA47: ="[" & _xludf.TEXTJOIN(",",TRUE,G47:T47) & "]" -> #NAME? | AB47: {=IFERROR(J47/_xludf.XLOOKUP(I47,Materials!$A$3:$A$292,Materials!$I$3:$I$292),0) +IFERROR(L47/_xludf.XLOOKUP(K47,Materials!$A$3:$A$292,Materials!$I$3:$I$292),0) +IFERROR(N47/_xludf.XLOOKUP(M47,Materials!$A$3:$A$292,Materials!$I$3:$I$292),0) +IFERROR(P47/_xludf.XLOOKUP(O47,Materials!$A$3:$A$292,Materials!$I$3:$I$292),0) +IFERROR(R47/_xludf.XLOOKUP(Q47,Materials!$A$3:$A$292,Materials!$I$3:$I$292),0) +IFERROR(H47/_xludf.XLOOKUP(G47,Materials!$A$3:$A$292,Materials!$I$3:$I$292),0)} -> 0
A48: KR_res_mf_low | B48: GroundWall | C48: GroundWall (연식 무관) | D48: =AA48 -> #NAME? | E48: =IFERROR(1/AB48, "Not enough information entered") -> Not enough information entered | F48: KR_res_mf_low_GroundWall | G48: 철근콘크리트 | H48: 0.2 | I48: 압출법단열재(XPS) | J48: 0.05 | U48: Korean Energy Saving Design Standards (derived) | V48: =H48+J48+L48+N48+P48+R48+T48 -> 0.25 | AA48: ="[" & _xludf.TEXTJOIN(",",TRUE,G48:T48) & "]" -> #NAME? | AB48: {=IFERROR(J48/_xludf.XLOOKUP(I48,Materials!$A$3:$A$292,Materials!$I$3:$I$292),0) +IFERROR(L48/_xludf.XLOOKUP(K48,Materials!$A$3:$A$292,Materials!$I$3:$I$292),0) +IFERROR(N48/_xludf.XLOOKUP(M48,Materials!$A$3:$A$292,Materials!$I$3:$I$292),0) +IFERROR(P48/_xludf.XLOOKUP(O48,Materials!$A$3:$A$292,Materials!$I$3:$I$292),0) +IFERROR(R48/_xludf.XLOOKUP(Q48,Materials!$A$3:$A$292,Materials!$I$3:$I$292),0) +IFERROR(H48/_xludf.XLOOKUP(G48,Materials!$A$3:$A$292,Materials!$I$3:$I$292),0)} -> 0
C49: InternalMass (연식 무관)
A50: KR_res_mf_low | B50: BasementCeiling | C50: BasementCeiling (연식 무관) | D50: =AA50 -> #NAME? | E50: =IFERROR(1/AB50, "Not enough information entered") -> Not enough information entered | F50: KR_res_mf_low_BasementCeiling | G50: 철근콘크리트 | H50: 0.18 | I50: 비드법단열재(EPS) | J50: 0.06 | K50: 석고보드 | L50: 0.0125 | U50: Korean Energy Saving Design Standards (derived) | V50: =H50+J50+L50+N50+P50+R50+T50 -> 0.2525 | AA50: ="[" & _xludf.TEXTJOIN(",",TRUE,G50:T50) & "]" -> #NAME? | AB50: {=IFERROR(J50/_xludf.XLOOKUP(I50,Materials!$A$3:$A$292,Materials!$I$3:$I$292),0) +IFERROR(L50/_xludf.XLOOKUP(K50,Materials!$A$3:$A$292,Materials!$I$3:$I$292),0) +IFERROR(N50/_xludf.XLOOKUP(M50,Materials!$A$3:$A$292,Materials!$I$3:$I$292),0) +IFERROR(P50/_xludf.XLOOKUP(O50,Materials!$A$3:$A$292,Materials!$I$3:$I$292),0) +IFERROR(R50/_xludf.XLOOKUP(Q50,Materials!$A$3:$A$292,Materials!$I$3:$I$292),0) +IFERROR(H50/_xludf.XLOOKUP(G50,Materials!$A$3:$A$292,Materials!$I$3:$I$292),0)} -> 0
A51: KR_res_mf_high_pre1988 | B51: Facade | C51: 외벽(외피) | D51: =AA51 -> #NAME? | E51: =IFERROR(1/AB51, "Not enough information entered") -> Not enough information entered | F51: KR_res_mf_high_pre1988_Facade | G51: 철근콘크리트 | H51: 0.18 | I51: 공기층(비통기) | J51: 0.02 | K51: 석고보드 | L51: 0.012 | U51: Korean Energy Saving Design Standards (derived) | V51: =H51+J51+L51+N51+P51+R51+T51 -> 0.212 | W51: 0 | X51: 0 | Y51: 10 | AA51: ="[" & _xludf.TEXTJOIN(",",TRUE,G51:T51) & "]" -> #NAME? | AB51: {=IFERROR(J51/_xludf.XLOOKUP(I51,Materials!$A$3:$A$292,Materials!$I$3:$I$292),0) +IFERROR(L51/_xludf.XLOOKUP(K51,Materials!$A$3:$A$292,Materials!$I$3:$I$292),0) +IFERROR(N51/_xludf.XLOOKUP(M51,Materials!$A$3:$A$292,Materials!$I$3:$I$292),0) +IFERROR(P51/_xludf.XLOOKUP(O51,Materials!$A$3:$A$292,Materials!$I$3:$I$292),0) +IFERROR(R51/_xludf.XLOOKUP(Q51,Materials!$A$3:$A$292,Materials!$I$3:$I$292),0) +IFERROR(H51/_xludf.XLOOKUP(G51,Materials!$A$3:$A$292,Materials!$I$3:$I$292),0)} -> 0
A52: KR_res_mf_high_pre1988 | B52: FlatRoof | C52: 지붕(평지붕) | D52: =AA52 -> #NAME? | E52: =IFERROR(1/AB52, "Not enough information entered") -> Not enough information entered | F52: KR_res_mf_high_pre1988_FlatRoof | G52: 철근콘크리트 | H52: 0.15 | I52: 시멘트몰탈 | J52: 0.03 | U52: Korean Energy Saving Design Standards (derived) | V52: =H52+J52+L52+N52+P52+R52+T52 -> 0.18 | AA52: ="[" & _xludf.TEXTJOIN(",",TRUE,G52:T52) & "]" -> #NAME? | AB52: {=IFERROR(J52/_xludf.XLOOKUP(I52,Materials!$A$3:$A$292,Materials!$I$3:$I$292),0) +IFERROR(L52/_xludf.XLOOKUP(K52,Materials!$A$3:$A$292,Materials!$I$3:$I$292),0) +IFERROR(N52/_xludf.XLOOKUP(M52,Materials!$A$3:$A$292,Materials!$I$3:$I$292),0) +IFERROR(P52/_xludf.XLOOKUP(O52,Materials!$A$3:$A$292,Materials!$I$3:$I$292),0) +IFERROR(R52/_xludf.XLOOKUP(Q52,Materials!$A$3:$A$292,Materials!$I$3:$I$292),0) +IFERROR(H52/_xludf.XLOOKUP(G52,Materials!$A$3:$A$292,Materials!$I$3:$I$292),0)} -> 0
A53: KR_res_mf_high_pre1988 | B53: GroundSlab | C53: 지면접촉 바닥 | D53: =AA53 -> #NAME? | E53: =IFERROR(1/AB53, "Not enough information entered") -> Not enough information entered | F53: KR_res_mf_high_pre1988_GroundSlab | G53: 철근콘크리트 | H53: 0.18 | I53: 시멘트몰탈 | J53: 0.03 | U53: Korean Energy Saving Design Standards (derived) | V53: =H53+J53+L53+N53+P53+R53+T53 -> 0.21 | W53: 0 | X53: 0 | Y53: 10 | AA53: ="[" & _xludf.TEXTJOIN(",",TRUE,G53:T53) & "]" -> #NAME? | AB53: {=IFERROR(J53/_xludf.XLOOKUP(I53,Materials!$A$3:$A$292,Materials!$I$3:$I$292),0) +IFERROR(L53/_xludf.XLOOKUP(K53,Materials!$A$3:$A$292,Materials!$I$3:$I$292),0) +IFERROR(N53/_xludf.XLOOKUP(M53,Materials!$A$3:$A$292,Materials!$I$3:$I$292),0) +IFERROR(P53/_xludf.XLOOKUP(O53,Materials!$A$3:$A$292,Materials!$I$3:$I$292),0) +IFERROR(R53/_xludf.XLOOKUP(Q53,Materials!$A$3:$A$292,Materials!$I$3:$I$292),0) +IFERROR(H53/_xludf.XLOOKUP(G53,Materials!$A$3:$A$292,Materials!$I$3:$I$292),0)} -> 0
A54: KR_res_mf_high_1988_2000 | B54: Facade | C54: 외벽(외피) | D54: =AA54 -> #NAME? | E54: =IFERROR(1/AB54, "Not enough information entered") -> Not enough information entered | F54: KR_res_mf_high_1988_2000_Facade | G54: 압출법단열재(XPS) | H54: 0.03 | I54: 철근콘크리트 | J54: 0.18 | K54: 공기층(비통기) | L54: 0.02 | M54: 석고보드 | N54: 0.012 | U54: Korean Energy Saving Design Standards (derived) | V54: =H54+J54+L54+N54+P54+R54+T54 -> 0.242 | W54: 0 | X54: 0 | Y54: 10 | AA54: ="[" & _xludf.TEXTJOIN(",",TRUE,G54:T54) & "]" -> #NAME? | AB54: {=IFERROR(J54/_xludf.XLOOKUP(I54,Materials!$A$3:$A$292,Materials!$I$3:$I$292),0) +IFERROR(L54/_xludf.XLOOKUP(K54,Materials!$A$3:$A$292,Materials!$I$3:$I$292),0) +IFERROR(N54/_xludf.XLOOKUP(M54,Materials!$A$3:$A$292,Materials!$I$3:$I$292),0) +IFERROR(P54/_xludf.XLOOKUP(O54,Materials!$A$3:$A$292,Materials!$I$3:$I$292),0) +IFERROR(R54/_xludf.XLOOKUP(Q54,Materials!$A$3:$A$292,Materials!$I$3:$I$292),0) +IFERROR(H54/_xludf.XLOOKUP(G54,Materials!$A$3:$A$292,Materials!$I$3:$I$292),0)} -> 0
A55: KR_res_mf_high_1988_2000 | B55: FlatRoof | C55: 지붕(평지붕) | D55: =AA55 -> #NAME? | E55: =IFERROR(1/AB55, "Not enough information entered") -> Not enough information entered | F55: KR_res_mf_high_1988_2000_FlatRoof | G55: 압출법단열재(XPS) | H55: 0.058 | I55: 철근콘크리트 | J55: 0.15 | K55: 시멘트몰탈 | L55: 0.03 | U55: Korean Energy Saving Design Standards (derived) | V55: =H55+J55+L55+N55+P55+R55+T55 -> 0.238 | AA55: ="[" & _xludf.TEXTJOIN(",",TRUE,G55:T55) & "]" -> #NAME? | AB55: {=IFERROR(J55/_xludf.XLOOKUP(I55,Materials!$A$3:$A$292,Materials!$I$3:$I$292),0) +IFERROR(L55/_xludf.XLOOKUP(K55,Materials!$A$3:$A$292,Materials!$I$3:$I$292),0) +IFERROR(N55/_xludf.XLOOKUP(M55,Materials!$A$3:$A$292,Materials!$I$3:$I$292),0) +IFERROR(P55/_xludf.XLOOKUP(O55,Materials!$A$3:$A$292,Materials!$I$3:$I$292),0) +IFERROR(R55/_xludf.XLOOKUP(Q55,Materials!$A$3:$A$292,Materials!$I$3:$I$292),0) +IFERROR(H55/_xludf.XLOOKUP(G55,Materials!$A$3:$A$292,Materials!$I$3:$I$292),0)} -> 0
A56: KR_res_mf_high_1988_2000 | B56: GroundSlab | C56: 지면접촉 바닥 | D56: =AA56 -> #NAME? | E56: =IFERROR(1/AB56, "Not enough information entered") -> Not enough information entered | F56: KR_res_mf_high_1988_2000_GroundSlab | G56: 압출법단열재(XPS) | H56: 0.047 | I56: 철근콘크리트 | J56: 0.18 | K56: 시멘트몰탈 | L56: 0.03 | U56: Korean Energy Saving Design Standards (derived) | V56: =H56+J56+L56+N56+P56+R56+T56 -> 0.257 | W56: 0 | X56: 0 | Y56: 10 | AA56: ="[" & _xludf.TEXTJOIN(",",TRUE,G56:T56) & "]" -> #NAME? | AB56: {=IFERROR(J56/_xludf.XLOOKUP(I56,Materials!$A$3:$A$292,Materials!$I$3:$I$292),0) +IFERROR(L56/_xludf.XLOOKUP(K56,Materials!$A$3:$A$292,Materials!$I$3:$I$292),0) +IFERROR(N56/_xludf.XLOOKUP(M56,Materials!$A$3:$A$292,Materials!$I$3:$I$292),0) +IFERROR(P56/_xludf.XLOOKUP(O56,Materials!$A$3:$A$292,Materials!$I$3:$I$292),0) +IFERROR(R56/_xludf.XLOOKUP(Q56,Materials!$A$3:$A$292,Materials!$I$3:$I$292),0) +IFERROR(H56/_xludf.XLOOKUP(G56,Materials!$A$3:$A$292,Materials!$I$3:$I$292),0)} -> 0
A57: KR_res_mf_high_2001_2010 | B57: Facade | C57: 외벽(외피) | D57: =AA57 -> #NAME? | E57: =IFERROR(1/AB57, "Not enough information entered") -> Not enough information entered | F57: KR_res_mf_high_2001_2010_Facade | G57: 압출법단열재(XPS) | H57: 0.04 | I57: 철근콘크리트 | J57: 0.18 | K57: 공기층(비통기) | L57: 0.02 | M57: 석고보드 | N57: 0.012 | U57: Korean Energy Saving Design Standards (derived) | V57: =H57+J57+L57+N57+P57+R57+T57 -> 0.252 | W57: 0 | X57: 0 | Y57: 10 | AA57: ="[" & _xludf.TEXTJOIN(",",TRUE,G57:T57) & "]" -> #NAME? | AB57: {=IFERROR(J57/_xludf.XLOOKUP(I57,Materials!$A$3:$A$292,Materials!$I$3:$I$292),0) +IFERROR(L57/_xludf.XLOOKUP(K57,Materials!$A$3:$A$292,Materials!$I$3:$I$292),0) +IFERROR(N57/_xludf.XLOOKUP(M57,Materials!$A$3:$A$292,Materials!$I$3:$I$292),0) +IFERROR(P57/_xludf.XLOOKUP(O57,Materials!$A$3:$A$292,Materials!$I$3:$I$292),0) +IFERROR(R57/_xludf.XLOOKUP(Q57,Materials!$A$3:$A$292,Materials!$I$3:$I$292),0) +IFERROR(H57/_xludf.XLOOKUP(G57,Materials!$A$3:$A$292,Materials!$I$3:$I$292),0)} -> 0
A58: KR_res_mf_high_2001_2010 | B58: FlatRoof | C58: 지붕(평지붕) | D58: =AA58 -> #NAME? | E58: =IFERROR(1/AB58, "Not enough information entered") -> Not enough information entered | F58: KR_res_mf_high_2001_2010_FlatRoof | G58: 압출법단열재(XPS) | H58: 0.059 | I58: 철근콘크리트 | J58: 0.15 | K58: 시멘트몰탈 | L58: 0.03 | U58: Korean Energy Saving Design Standards (derived) | V58: =H58+J58+L58+N58+P58+R58+T58 -> 0.239 | AA58: ="[" & _xludf.TEXTJOIN(",",TRUE,G58:T58) & "]" -> #NAME? | AB58: {=IFERROR(J58/_xludf.XLOOKUP(I58,Materials!$A$3:$A$292,Materials!$I$3:$I$292),0) +IFERROR(L58/_xludf.XLOOKUP(K58,Materials!$A$3:$A$292,Materials!$I$3:$I$292),0) +IFERROR(N58/_xludf.XLOOKUP(M58,Materials!$A$3:$A$292,Materials!$I$3:$I$292),0) +IFERROR(P58/_xludf.XLOOKUP(O58,Materials!$A$3:$A$292,Materials!$I$3:$I$292),0) +IFERROR(R58/_xludf.XLOOKUP(Q58,Materials!$A$3:$A$292,Materials!$I$3:$I$292),0) +IFERROR(H58/_xludf.XLOOKUP(G58,Materials!$A$3:$A$292,Materials!$I$3:$I$292),0)} -> 0
A59: KR_res_mf_high_2001_2010 | B59: GroundSlab | C59: 지면접촉 바닥 | D59: =AA59 -> #NAME? | E59: =IFERROR(1/AB59, "Not enough information entered") -> Not enough information entered | F59: KR_res_mf_high_2001_2010_GroundSlab | G59: 압출법단열재(XPS) | H59: 0.058 | I59: 철근콘크리트 | J59: 0.18 | K59: 시멘트몰탈 | L59: 0.03 | U59: Korean Energy Saving Design Standards (derived) | V59: =H59+J59+L59+N59+P59+R59+T59 -> 0.268 | W59: 0 | X59: 0 | Y59: 10 | AA59: ="[" & _xludf.TEXTJOIN(",",TRUE,G59:T59) & "]" -> #NAME? | AB59: {=IFERROR(J59/_xludf.XLOOKUP(I59,Materials!$A$3:$A$292,Materials!$I$3:$I$292),0) +IFERROR(L59/_xludf.XLOOKUP(K59,Materials!$A$3:$A$292,Materials!$I$3:$I$292),0) +IFERROR(N59/_xludf.XLOOKUP(M59,Materials!$A$3:$A$292,Materials!$I$3:$I$292),0) +IFERROR(P59/_xludf.XLOOKUP(O59,Materials!$A$3:$A$292,Materials!$I$3:$I$292),0) +IFERROR(R59/_xludf.XLOOKUP(Q59,Materials!$A$3:$A$292,Materials!$I$3:$I$292),0) +IFERROR(H59/_xludf.XLOOKUP(G59,Materials!$A$3:$A$292,Materials!$I$3:$I$292),0)} -> 0
A60: KR_res_mf_high_2011_2018 | B60: Facade | C60: 외벽(외피) | D60: =AA60 -> #NAME? | E60: =IFERROR(1/AB60, "Not enough information entered") -> Not enough information entered | F60: KR_res_mf_high_2011_2018_Facade | G60: 압출법단열재(XPS) | H60: 0.06 | I60: 철근콘크리트 | J60: 0.18 | K60: 공기층(비통기) | L60: 0.02 | M60: 석고보드 | N60: 0.012 | U60: Korean Energy Saving Design Standards (derived) | V60: =H60+J60+L60+N60+P60+R60+T60 -> 0.272 | W60: 0 | X60: 0 | Y60: 10 | AA60: ="[" & _xludf.TEXTJOIN(",",TRUE,G60:T60) & "]" -> #NAME? | AB60: {=IFERROR(J60/_xludf.XLOOKUP(I60,Materials!$A$3:$A$292,Materials!$I$3:$I$292),0) +IFERROR(L60/_xludf.XLOOKUP(K60,Materials!$A$3:$A$292,Materials!$I$3:$I$292),0) +IFERROR(N60/_xludf.XLOOKUP(M60,Materials!$A$3:$A$292,Materials!$I$3:$I$292),0) +IFERROR(P60/_xludf.XLOOKUP(O60,Materials!$A$3:$A$292,Materials!$I$3:$I$292),0) +IFERROR(R60/_xludf.XLOOKUP(Q60,Materials!$A$3:$A$292,Materials!$I$3:$I$292),0) +IFERROR(H60/_xludf.XLOOKUP(G60,Materials!$A$3:$A$292,Materials!$I$3:$I$292),0)} -> 0
A61: KR_res_mf_high_2011_2018 | B61: FlatRoof | C61: 지붕(평지붕) | D61: =AA61 -> #NAME? | E61: =IFERROR(1/AB61, "Not enough information entered") -> Not enough information entered | F61: KR_res_mf_high_2011_2018_FlatRoof | G61: 압출법단열재(XPS) | H61: 0.078 | I61: 철근콘크리트 | J61: 0.15 | K61: 시멘트몰탈 | L61: 0.03 | U61: Korean Energy Saving Design Standards (derived) | V61: =H61+J61+L61+N61+P61+R61+T61 -> 0.258 | AA61: ="[" & _xludf.TEXTJOIN(",",TRUE,G61:T61) & "]" -> #NAME? | AB61: {=IFERROR(J61/_xludf.XLOOKUP(I61,Materials!$A$3:$A$292,Materials!$I$3:$I$292),0) +IFERROR(L61/_xludf.XLOOKUP(K61,Materials!$A$3:$A$292,Materials!$I$3:$I$292),0) +IFERROR(N61/_xludf.XLOOKUP(M61,Materials!$A$3:$A$292,Materials!$I$3:$I$292),0) +IFERROR(P61/_xludf.XLOOKUP(O61,Materials!$A$3:$A$292,Materials!$I$3:$I$292),0) +IFERROR(R61/_xludf.XLOOKUP(Q61,Materials!$A$3:$A$292,Materials!$I$3:$I$292),0) +IFERROR(H61/_xludf.XLOOKUP(G61,Materials!$A$3:$A$292,Materials!$I$3:$I$292),0)} -> 0
A62: KR_res_mf_high_2011_2018 | B62: GroundSlab | C62: 지면접촉 바닥 | D62: =AA62 -> #NAME? | E62: =IFERROR(1/AB62, "Not enough information entered") -> Not enough information entered | F62: KR_res_mf_high_2011_2018_GroundSlab | G62: 압출법단열재(XPS) | H62: 0.077 | I62: 철근콘크리트 | J62: 0.18 | K62: 시멘트몰탈 | L62: 0.03 | U62: Korean Energy Saving Design Standards (derived) | V62: =H62+J62+L62+N62+P62+R62+T62 -> 0.287 | W62: 0 | X62: 0 | Y62: 10 | AA62: ="[" & _xludf.TEXTJOIN(",",TRUE,G62:T62) & "]" -> #NAME? | AB62: {=IFERROR(J62/_xludf.XLOOKUP(I62,Materials!$A$3:$A$292,Materials!$I$3:$I$292),0) +IFERROR(L62/_xludf.XLOOKUP(K62,Materials!$A$3:$A$292,Materials!$I$3:$I$292),0) +IFERROR(N62/_xludf.XLOOKUP(M62,Materials!$A$3:$A$292,Materials!$I$3:$I$292),0) +IFERROR(P62/_xludf.XLOOKUP(O62,Materials!$A$3:$A$292,Materials!$I$3:$I$292),0) +IFERROR(R62/_xludf.XLOOKUP(Q62,Materials!$A$3:$A$292,Materials!$I$3:$I$292),0) +IFERROR(H62/_xludf.XLOOKUP(G62,Materials!$A$3:$A$292,Materials!$I$3:$I$292),0)} -> 0
A63: KR_res_mf_high_post2019 | B63: Facade | C63: 외벽(외피) | D63: =AA63 -> #NAME? | E63: =IFERROR(1/AB63, "Not enough information entered") -> Not enough information entered | F63: KR_res_mf_high_post2019_Facade | G63: 압출법단열재(XPS) | H63: 0.069 | I63: 철근콘크리트 | J63: 0.18 | K63: 공기층(비통기) | L63: 0.02 | M63: 석고보드 | N63: 0.012 | U63: Korean Energy Saving Design Standards (derived) | V63: =H63+J63+L63+N63+P63+R63+T63 -> 0.281 | W63: 0 | X63: 0 | Y63: 10 | AA63: ="[" & _xludf.TEXTJOIN(",",TRUE,G63:T63) & "]" -> #NAME? | AB63: {=IFERROR(J63/_xludf.XLOOKUP(I63,Materials!$A$3:$A$292,Materials!$I$3:$I$292),0) +IFERROR(L63/_xludf.XLOOKUP(K63,Materials!$A$3:$A$292,Materials!$I$3:$I$292),0) +IFERROR(N63/_xludf.XLOOKUP(M63,Materials!$A$3:$A$292,Materials!$I$3:$I$292),0) +IFERROR(P63/_xludf.XLOOKUP(O63,Materials!$A$3:$A$292,Materials!$I$3:$I$292),0) +IFERROR(R63/_xludf.XLOOKUP(Q63,Materials!$A$3:$A$292,Materials!$I$3:$I$292),0) +IFERROR(H63/_xludf.XLOOKUP(G63,Materials!$A$3:$A$292,Materials!$I$3:$I$292),0)} -> 0
A64: KR_res_mf_high_post2019 | B64: FlatRoof | C64: 지붕(평지붕) | D64: =AA64 -> #NAME? | E64: =IFERROR(1/AB64, "Not enough information entered") -> Not enough information entered | F64: KR_res_mf_high_post2019_FlatRoof | G64: 압출법단열재(XPS) | H64: 0.094 | I64: 철근콘크리트 | J64: 0.15 | K64: 시멘트몰탈 | L64: 0.03 | U64: Korean Energy Saving Design Standards (derived) | V64: =H64+J64+L64+N64+P64+R64+T64 -> 0.274 | AA64: ="[" & _xludf.TEXTJOIN(",",TRUE,G64:T64) & "]" -> #NAME? | AB64: {=IFERROR(J64/_xludf.XLOOKUP(I64,Materials!$A$3:$A$292,Materials!$I$3:$I$292),0) +IFERROR(L64/_xludf.XLOOKUP(K64,Materials!$A$3:$A$292,Materials!$I$3:$I$292),0) +IFERROR(N64/_xludf.XLOOKUP(M64,Materials!$A$3:$A$292,Materials!$I$3:$I$292),0) +IFERROR(P64/_xludf.XLOOKUP(O64,Materials!$A$3:$A$292,Materials!$I$3:$I$292),0) +IFERROR(R64/_xludf.XLOOKUP(Q64,Materials!$A$3:$A$292,Materials!$I$3:$I$292),0) +IFERROR(H64/_xludf.XLOOKUP(G64,Materials!$A$3:$A$292,Materials!$I$3:$I$292),0)} -> 0
A65: KR_res_mf_high_post2019 | B65: GroundSlab | C65: 지면접촉 바닥 | D65: =AA65 -> #NAME? | E65: =IFERROR(1/AB65, "Not enough information entered") -> Not enough information entered | F65: KR_res_mf_high_post2019_GroundSlab | G65: 압출법단열재(XPS) | H65: 0.093 | I65: 철근콘크리트 | J65: 0.18 | K65: 시멘트몰탈 | L65: 0.03 | U65: Korean Energy Saving Design Standards (derived) | V65: =H65+J65+L65+N65+P65+R65+T65 -> 0.303 | W65: 0 | X65: 0 | Y65: 10 | AA65: ="[" & _xludf.TEXTJOIN(",",TRUE,G65:T65) & "]" -> #NAME? | AB65: {=IFERROR(J65/_xludf.XLOOKUP(I65,Materials!$A$3:$A$292,Materials!$I$3:$I$292),0) +IFERROR(L65/_xludf.XLOOKUP(K65,Materials!$A$3:$A$292,Materials!$I$3:$I$292),0) +IFERROR(N65/_xludf.XLOOKUP(M65,Materials!$A$3:$A$292,Materials!$I$3:$I$292),0) +IFERROR(P65/_xludf.XLOOKUP(O65,Materials!$A$3:$A$292,Materials!$I$3:$I$292),0) +IFERROR(R65/_xludf.XLOOKUP(Q65,Materials!$A$3:$A$292,Materials!$I$3:$I$292),0) +IFERROR(H65/_xludf.XLOOKUP(G65,Materials!$A$3:$A$292,Materials!$I$3:$I$292),0)} -> 0
A66: KR_res_mf_high | B66: Partition | C66: Partition (연식 무관) | D66: =AA66 -> #NAME? | E66: =IFERROR(1/AB66, "Not enough information entered") -> Not enough information entered | F66: KR_res_mf_high_Partition | G66: 석고보드 | H66: 0.0125 | I66: 공기층(비통기) | J66: 0.05 | K66: 석고보드 | L66: 0.0125 | U66: Korean Energy Saving Design Standards (derived) | V66: =H66+J66+L66+N66+P66+R66+T66 -> 0.075 | AA66: ="[" & _xludf.TEXTJOIN(",",TRUE,G66:T66) & "]" -> #NAME? | AB66: {=IFERROR(J66/_xludf.XLOOKUP(I66,Materials!$A$3:$A$292,Materials!$I$3:$I$292),0) +IFERROR(L66/_xludf.XLOOKUP(K66,Materials!$A$3:$A$292,Materials!$I$3:$I$292),0) +IFERROR(N66/_xludf.XLOOKUP(M66,Materials!$A$3:$A$292,Materials!$I$3:$I$292),0) +IFERROR(P66/_xludf.XLOOKUP(O66,Materials!$A$3:$A$292,Materials!$I$3:$I$292),0) +IFERROR(R66/_xludf.XLOOKUP(Q66,Materials!$A$3:$A$292,Materials!$I$3:$I$292),0) +IFERROR(H66/_xludf.XLOOKUP(G66,Materials!$A$3:$A$292,Materials!$I$3:$I$292),0)} -> 0
A67: KR_res_mf_high | B67: ExternalFloor | C67: ExternalFloor (연식 무관) | D67: =AA67 -> #NAME? | E67: =IFERROR(1/AB67, "Not enough information entered") -> Not enough information entered | F67: KR_res_mf_high_ExternalFloor | G67: 철근콘크리트 | H67: 0.18 | I67: 압출법단열재(XPS) | J67: 0.08 | K67: 시멘트몰탈 | L67: 0.03 | U67: Korean Energy Saving Design Standards (derived) | V67: =H67+J67+L67+N67+P67+R67+T67 -> 0.29 | AA67: ="[" & _xludf.TEXTJOIN(",",TRUE,G67:T67) & "]" -> #NAME? | AB67: {=IFERROR(J67/_xludf.XLOOKUP(I67,Materials!$A$3:$A$292,Materials!$I$3:$I$292),0) +IFERROR(L67/_xludf.XLOOKUP(K67,Materials!$A$3:$A$292,Materials!$I$3:$I$292),0) +IFERROR(N67/_xludf.XLOOKUP(M67,Materials!$A$3:$A$292,Materials!$I$3:$I$292),0) +IFERROR(P67/_xludf.XLOOKUP(O67,Materials!$A$3:$A$292,Materials!$I$3:$I$292),0) +IFERROR(R67/_xludf.XLOOKUP(Q67,Materials!$A$3:$A$292,Materials!$I$3:$I$292),0) +IFERROR(H67/_xludf.XLOOKUP(G67,Materials!$A$3:$A$292,Materials!$I$3:$I$292),0)} -> 0
A68: KR_res_mf_high | B68: FloorCeiling | C68: FloorCeiling (연식 무관) | D68: =AA68 -> #NAME? | E68: =IFERROR(1/AB68, "Not enough information entered") -> Not enough information entered | F68: KR_res_mf_high_FloorCeiling | G68: 철근콘크리트 | H68: 0.18 | I68: 시멘트몰탈 | J68: 0.03 | U68: Korean Energy Saving Design Standards (derived) | V68: =H68+J68+L68+N68+P68+R68+T68 -> 0.21 | AA68: ="[" & _xludf.TEXTJOIN(",",TRUE,G68:T68) & "]" -> #NAME? | AB68: {=IFERROR(J68/_xludf.XLOOKUP(I68,Materials!$A$3:$A$292,Materials!$I$3:$I$292),0) +IFERROR(L68/_xludf.XLOOKUP(K68,Materials!$A$3:$A$292,Materials!$I$3:$I$292),0) +IFERROR(N68/_xludf.XLOOKUP(M68,Materials!$A$3:$A$292,Materials!$I$3:$I$292),0) +IFERROR(P68/_xludf.XLOOKUP(O68,Materials!$A$3:$A$292,Materials!$I$3:$I$292),0) +IFERROR(R68/_xludf.XLOOKUP(Q68,Materials!$A$3:$A$292,Materials!$I$3:$I$292),0) +IFERROR(H68/_xludf.XLOOKUP(G68,Materials!$A$3:$A$292,Materials!$I$3:$I$292),0)} -> 0
A69: KR_res_mf_high | B69: GroundWall | C69: GroundWall (연식 무관) | D69: =AA69 -> #NAME? | E69: =IFERROR(1/AB69, "Not enough information entered") -> Not enough information entered | F69: KR_res_mf_high_GroundWall | G69: 철근콘크리트 | H69: 0.2 | I69: 압출법단열재(XPS) | J69: 0.05 | U69: Korean Energy Saving Design Standards (derived) | V69: =H69+J69+L69+N69+P69+R69+T69 -> 0.25 | AA69: ="[" & _xludf.TEXTJOIN(",",TRUE,G69:T69) & "]" -> #NAME? | AB69: {=IFERROR(J69/_xludf.XLOOKUP(I69,Materials!$A$3:$A$292,Materials!$I$3:$I$292),0) +IFERROR(L69/_xludf.XLOOKUP(K69,Materials!$A$3:$A$292,Materials!$I$3:$I$292),0) +IFERROR(N69/_xludf.XLOOKUP(M69,Materials!$A$3:$A$292,Materials!$I$3:$I$292),0) +IFERROR(P69/_xludf.XLOOKUP(O69,Materials!$A$3:$A$292,Materials!$I$3:$I$292),0) +IFERROR(R69/_xludf.XLOOKUP(Q69,Materials!$A$3:$A$292,Materials!$I$3:$I$292),0) +IFERROR(H69/_xludf.XLOOKUP(G69,Materials!$A$3:$A$292,Materials!$I$3:$I$292),0)} -> 0
C70: InternalMass (연식 무관)
A71: KR_res_mf_high | B71: BasementCeiling | C71: BasementCeiling (연식 무관) | D71: =AA71 -> #NAME? | E71: =IFERROR(1/AB71, "Not enough information entered") -> Not enough information entered | F71: KR_res_mf_high_BasementCeiling | G71: 철근콘크리트 | H71: 0.18 | I71: 비드법단열재(EPS) | J71: 0.06 | K71: 석고보드 | L71: 0.0125 | U71: Korean Energy Saving Design Standards (derived) | V71: =H71+J71+L71+N71+P71+R71+T71 -> 0.2525 | AA71: ="[" & _xludf.TEXTJOIN(",",TRUE,G71:T71) & "]" -> #NAME? | AB71: {=IFERROR(J71/_xludf.XLOOKUP(I71,Materials!$A$3:$A$292,Materials!$I$3:$I$292),0) +IFERROR(L71/_xludf.XLOOKUP(K71,Materials!$A$3:$A$292,Materials!$I$3:$I$292),0) +IFERROR(N71/_xludf.XLOOKUP(M71,Materials!$A$3:$A$292,Materials!$I$3:$I$292),0) +IFERROR(P71/_xludf.XLOOKUP(O71,Materials!$A$3:$A$292,Materials!$I$3:$I$292),0) +IFERROR(R71/_xludf.XLOOKUP(Q71,Materials!$A$3:$A$292,Materials!$I$3:$I$292),0) +IFERROR(H71/_xludf.XLOOKUP(G71,Materials!$A$3:$A$292,Materials!$I$3:$I$292),0)} -> 0
A72: KR_office_small_pre1988 | B72: Facade | C72: 외벽(외피) | D72: =AA72 -> #NAME? | E72: =IFERROR(1/AB72, "Not enough information entered") -> Not enough information entered | F72: KR_office_small_pre1988_Facade | G72: 철근콘크리트 | H72: 0.18 | I72: 공기층(비통기) | J72: 0.02 | K72: 석고보드 | L72: 0.012 | U72: Korean Energy Saving Design Standards (derived) | V72: =H72+J72+L72+N72+P72+R72+T72 -> 0.212 | W72: 0 | X72: 0 | Y72: 10 | AA72: ="[" & _xludf.TEXTJOIN(",",TRUE,G72:T72) & "]" -> #NAME? | AB72: {=IFERROR(J72/_xludf.XLOOKUP(I72,Materials!$A$3:$A$292,Materials!$I$3:$I$292),0) +IFERROR(L72/_xludf.XLOOKUP(K72,Materials!$A$3:$A$292,Materials!$I$3:$I$292),0) +IFERROR(N72/_xludf.XLOOKUP(M72,Materials!$A$3:$A$292,Materials!$I$3:$I$292),0) +IFERROR(P72/_xludf.XLOOKUP(O72,Materials!$A$3:$A$292,Materials!$I$3:$I$292),0) +IFERROR(R72/_xludf.XLOOKUP(Q72,Materials!$A$3:$A$292,Materials!$I$3:$I$292),0) +IFERROR(H72/_xludf.XLOOKUP(G72,Materials!$A$3:$A$292,Materials!$I$3:$I$292),0)} -> 0
A73: KR_office_small_pre1988 | B73: FlatRoof | C73: 지붕(평지붕) | D73: =AA73 -> #NAME? | E73: =IFERROR(1/AB73, "Not enough information entered") -> Not enough information entered | F73: KR_office_small_pre1988_FlatRoof | G73: 철근콘크리트 | H73: 0.15 | I73: 시멘트몰탈 | J73: 0.03 | U73: Korean Energy Saving Design Standards (derived) | V73: =H73+J73+L73+N73+P73+R73+T73 -> 0.18 | AA73: ="[" & _xludf.TEXTJOIN(",",TRUE,G73:T73) & "]" -> #NAME? | AB73: {=IFERROR(J73/_xludf.XLOOKUP(I73,Materials!$A$3:$A$292,Materials!$I$3:$I$292),0) +IFERROR(L73/_xludf.XLOOKUP(K73,Materials!$A$3:$A$292,Materials!$I$3:$I$292),0) +IFERROR(N73/_xludf.XLOOKUP(M73,Materials!$A$3:$A$292,Materials!$I$3:$I$292),0) +IFERROR(P73/_xludf.XLOOKUP(O73,Materials!$A$3:$A$292,Materials!$I$3:$I$292),0) +IFERROR(R73/_xludf.XLOOKUP(Q73,Materials!$A$3:$A$292,Materials!$I$3:$I$292),0) +IFERROR(H73/_xludf.XLOOKUP(G73,Materials!$A$3:$A$292,Materials!$I$3:$I$292),0)} -> 0
A74: KR_office_small_pre1988 | B74: GroundSlab | C74: 지면접촉 바닥 | D74: =AA74 -> #NAME? | E74: =IFERROR(1/AB74, "Not enough information entered") -> Not enough information entered | F74: KR_office_small_pre1988_GroundSlab | G74: 철근콘크리트 | H74: 0.18 | I74: 시멘트몰탈 | J74: 0.03 | U74: Korean Energy Saving Design Standards (derived) | V74: =H74+J74+L74+N74+P74+R74+T74 -> 0.21 | W74: 0 | X74: 0 | Y74: 10 | AA74: ="[" & _xludf.TEXTJOIN(",",TRUE,G74:T74) & "]" -> #NAME? | AB74: {=IFERROR(J74/_xludf.XLOOKUP(I74,Materials!$A$3:$A$292,Materials!$I$3:$I$292),0) +IFERROR(L74/_xludf.XLOOKUP(K74,Materials!$A$3:$A$292,Materials!$I$3:$I$292),0) +IFERROR(N74/_xludf.XLOOKUP(M74,Materials!$A$3:$A$292,Materials!$I$3:$I$292),0) +IFERROR(P74/_xludf.XLOOKUP(O74,Materials!$A$3:$A$292,Materials!$I$3:$I$292),0) +IFERROR(R74/_xludf.XLOOKUP(Q74,Materials!$A$3:$A$292,Materials!$I$3:$I$292),0) +IFERROR(H74/_xludf.XLOOKUP(G74,Materials!$A$3:$A$292,Materials!$I$3:$I$292),0)} -> 0
A75: KR_office_small_1988_2000 | B75: Facade | C75: 외벽(외피) | D75: =AA75 -> #NAME? | E75: =IFERROR(1/AB75, "Not enough information entered") -> Not enough information entered | F75: KR_office_small_1988_2000_Facade | G75: 압출법단열재(XPS) | H75: 0.03 | I75: 철근콘크리트 | J75: 0.18 | K75: 공기층(비통기) | L75: 0.02 | M75: 석고보드 | N75: 0.012 | U75: Korean Energy Saving Design Standards (derived) | V75: =H75+J75+L75+N75+P75+R75+T75 -> 0.242 | W75: 0 | X75: 0 | Y75: 10 | AA75: ="[" & _xludf.TEXTJOIN(",",TRUE,G75:T75) & "]" -> #NAME? | AB75: {=IFERROR(J75/_xludf.XLOOKUP(I75,Materials!$A$3:$A$292,Materials!$I$3:$I$292),0) +IFERROR(L75/_xludf.XLOOKUP(K75,Materials!$A$3:$A$292,Materials!$I$3:$I$292),0) +IFERROR(N75/_xludf.XLOOKUP(M75,Materials!$A$3:$A$292,Materials!$I$3:$I$292),0) +IFERROR(P75/_xludf.XLOOKUP(O75,Materials!$A$3:$A$292,Materials!$I$3:$I$292),0) +IFERROR(R75/_xludf.XLOOKUP(Q75,Materials!$A$3:$A$292,Materials!$I$3:$I$292),0) +IFERROR(H75/_xludf.XLOOKUP(G75,Materials!$A$3:$A$292,Materials!$I$3:$I$292),0)} -> 0
A76: KR_office_small_1988_2000 | B76: FlatRoof | C76: 지붕(평지붕) | D76: =AA76 -> #NAME? | E76: =IFERROR(1/AB76, "Not enough information entered") -> Not enough information entered | F76: KR_office_small_1988_2000_FlatRoof | G76: 압출법단열재(XPS) | H76: 0.058 | I76: 철근콘크리트 | J76: 0.15 | K76: 시멘트몰탈 | L76: 0.03 | U76: Korean Energy Saving Design Standards (derived) | V76: =H76+J76+L76+N76+P76+R76+T76 -> 0.238 | AA76: ="[" & _xludf.TEXTJOIN(",",TRUE,G76:T76) & "]" -> #NAME? | AB76: {=IFERROR(J76/_xludf.XLOOKUP(I76,Materials!$A$3:$A$292,Materials!$I$3:$I$292),0) +IFERROR(L76/_xludf.XLOOKUP(K76,Materials!$A$3:$A$292,Materials!$I$3:$I$292),0) +IFERROR(N76/_xludf.XLOOKUP(M76,Materials!$A$3:$A$292,Materials!$I$3:$I$292),0) +IFERROR(P76/_xludf.XLOOKUP(O76,Materials!$A$3:$A$292,Materials!$I$3:$I$292),0) +IFERROR(R76/_xludf.XLOOKUP(Q76,Materials!$A$3:$A$292,Materials!$I$3:$I$292),0) +IFERROR(H76/_xludf.XLOOKUP(G76,Materials!$A$3:$A$292,Materials!$I$3:$I$292),0)} -> 0
A77: KR_office_small_1988_2000 | B77: GroundSlab | C77: 지면접촉 바닥 | D77: =AA77 -> #NAME? | E77: =IFERROR(1/AB77, "Not enough information entered") -> Not enough information entered | F77: KR_office_small_1988_2000_GroundSlab | G77: 압출법단열재(XPS) | H77: 0.047 | I77: 철근콘크리트 | J77: 0.18 | K77: 시멘트몰탈 | L77: 0.03 | U77: Korean Energy Saving Design Standards (derived) | V77: =H77+J77+L77+N77+P77+R77+T77 -> 0.257 | W77: 0 | X77: 0 | Y77: 10 | AA77: ="[" & _xludf.TEXTJOIN(",",TRUE,G77:T77) & "]" -> #NAME? | AB77: {=IFERROR(J77/_xludf.XLOOKUP(I77,Materials!$A$3:$A$292,Materials!$I$3:$I$292),0) +IFERROR(L77/_xludf.XLOOKUP(K77,Materials!$A$3:$A$292,Materials!$I$3:$I$292),0) +IFERROR(N77/_xludf.XLOOKUP(M77,Materials!$A$3:$A$292,Materials!$I$3:$I$292),0) +IFERROR(P77/_xludf.XLOOKUP(O77,Materials!$A$3:$A$292,Materials!$I$3:$I$292),0) +IFERROR(R77/_xludf.XLOOKUP(Q77,Materials!$A$3:$A$292,Materials!$I$3:$I$292),0) +IFERROR(H77/_xludf.XLOOKUP(G77,Materials!$A$3:$A$292,Materials!$I$3:$I$292),0)} -> 0
A78: KR_office_small_2001_2010 | B78: Facade | C78: 외벽(외피) | D78: =AA78 -> #NAME? | E78: =IFERROR(1/AB78, "Not enough information entered") -> Not enough information entered | F78: KR_office_small_2001_2010_Facade | G78: 압출법단열재(XPS) | H78: 0.04 | I78: 철근콘크리트 | J78: 0.18 | K78: 공기층(비통기) | L78: 0.02 | M78: 석고보드 | N78: 0.012 | U78: Korean Energy Saving Design Standards (derived) | V78: =H78+J78+L78+N78+P78+R78+T78 -> 0.252 | W78: 0 | X78: 0 | Y78: 10 | AA78: ="[" & _xludf.TEXTJOIN(",",TRUE,G78:T78) & "]" -> #NAME? | AB78: {=IFERROR(J78/_xludf.XLOOKUP(I78,Materials!$A$3:$A$292,Materials!$I$3:$I$292),0) +IFERROR(L78/_xludf.XLOOKUP(K78,Materials!$A$3:$A$292,Materials!$I$3:$I$292),0) +IFERROR(N78/_xludf.XLOOKUP(M78,Materials!$A$3:$A$292,Materials!$I$3:$I$292),0) +IFERROR(P78/_xludf.XLOOKUP(O78,Materials!$A$3:$A$292,Materials!$I$3:$I$292),0) +IFERROR(R78/_xludf.XLOOKUP(Q78,Materials!$A$3:$A$292,Materials!$I$3:$I$292),0) +IFERROR(H78/_xludf.XLOOKUP(G78,Materials!$A$3:$A$292,Materials!$I$3:$I$292),0)} -> 0
A79: KR_office_small_2001_2010 | B79: FlatRoof | C79: 지붕(평지붕) | D79: =AA79 -> #NAME? | E79: =IFERROR(1/AB79, "Not enough information entered") -> Not enough information entered | F79: KR_office_small_2001_2010_FlatRoof | G79: 압출법단열재(XPS) | H79: 0.059 | I79: 철근콘크리트 | J79: 0.15 | K79: 시멘트몰탈 | L79: 0.03 | U79: Korean Energy Saving Design Standards (derived) | V79: =H79+J79+L79+N79+P79+R79+T79 -> 0.239 | AA79: ="[" & _xludf.TEXTJOIN(",",TRUE,G79:T79) & "]" -> #NAME? | AB79: {=IFERROR(J79/_xludf.XLOOKUP(I79,Materials!$A$3:$A$292,Materials!$I$3:$I$292),0) +IFERROR(L79/_xludf.XLOOKUP(K79,Materials!$A$3:$A$292,Materials!$I$3:$I$292),0) +IFERROR(N79/_xludf.XLOOKUP(M79,Materials!$A$3:$A$292,Materials!$I$3:$I$292),0) +IFERROR(P79/_xludf.XLOOKUP(O79,Materials!$A$3:$A$292,Materials!$I$3:$I$292),0) +IFERROR(R79/_xludf.XLOOKUP(Q79,Materials!$A$3:$A$292,Materials!$I$3:$I$292),0) +IFERROR(H79/_xludf.XLOOKUP(G79,Materials!$A$3:$A$292,Materials!$I$3:$I$292),0)} -> 0
A80: KR_office_small_2001_2010 | B80: GroundSlab | C80: 지면접촉 바닥 | D80: =AA80 -> #NAME? | E80: =IFERROR(1/AB80, "Not enough information entered") -> Not enough information entered | F80: KR_office_small_2001_2010_GroundSlab | G80: 압출법단열재(XPS) | H80: 0.058 | I80: 철근콘크리트 | J80: 0.18 | K80: 시멘트몰탈 | L80: 0.03 | U80: Korean Energy Saving Design Standards (derived) | V80: =H80+J80+L80+N80+P80+R80+T80 -> 0.268 | W80: 0 | X80: 0 | Y80: 10 | AA80: ="[" & _xludf.TEXTJOIN(",",TRUE,G80:T80) & "]" -> #NAME? | AB80: {=IFERROR(J80/_xludf.XLOOKUP(I80,Materials!$A$3:$A$292,Materials!$I$3:$I$292),0) +IFERROR(L80/_xludf.XLOOKUP(K80,Materials!$A$3:$A$292,Materials!$I$3:$I$292),0) +IFERROR(N80/_xludf.XLOOKUP(M80,Materials!$A$3:$A$292,Materials!$I$3:$I$292),0) +IFERROR(P80/_xludf.XLOOKUP(O80,Materials!$A$3:$A$292,Materials!$I$3:$I$292),0) +IFERROR(R80/_xludf.XLOOKUP(Q80,Materials!$A$3:$A$292,Materials!$I$3:$I$292),0) +IFERROR(H80/_xludf.XLOOKUP(G80,Materials!$A$3:$A$292,Materials!$I$3:$I$292),0)} -> 0
A81: KR_office_small_2011_2018 | B81: Facade | C81: 외벽(외피) | D81: =AA81 -> #NAME? | E81: =IFERROR(1/AB81, "Not enough information entered") -> Not enough information entered | F81: KR_office_small_2011_2018_Facade | G81: 압출법단열재(XPS) | H81: 0.06 | I81: 철근콘크리트 | J81: 0.18 | K81: 공기층(비통기) | L81: 0.02 | M81: 석고보드 | N81: 0.012 | U81: Korean Energy Saving Design Standards (derived) | V81: =H81+J81+L81+N81+P81+R81+T81 -> 0.272 | W81: 0 | X81: 0 | Y81: 10 | AA81: ="[" & _xludf.TEXTJOIN(",",TRUE,G81:T81) & "]" -> #NAME? | AB81: {=IFERROR(J81/_xludf.XLOOKUP(I81,Materials!$A$3:$A$292,Materials!$I$3:$I$292),0) +IFERROR(L81/_xludf.XLOOKUP(K81,Materials!$A$3:$A$292,Materials!$I$3:$I$292),0) +IFERROR(N81/_xludf.XLOOKUP(M81,Materials!$A$3:$A$292,Materials!$I$3:$I$292),0) +IFERROR(P81/_xludf.XLOOKUP(O81,Materials!$A$3:$A$292,Materials!$I$3:$I$292),0) +IFERROR(R81/_xludf.XLOOKUP(Q81,Materials!$A$3:$A$292,Materials!$I$3:$I$292),0) +IFERROR(H81/_xludf.XLOOKUP(G81,Materials!$A$3:$A$292,Materials!$I$3:$I$292),0)} -> 0
A82: KR_office_small_2011_2018 | B82: FlatRoof | C82: 지붕(평지붕) | D82: =AA82 -> #NAME? | E82: =IFERROR(1/AB82, "Not enough information entered") -> Not enough information entered | F82: KR_office_small_2011_2018_FlatRoof | G82: 압출법단열재(XPS) | H82: 0.078 | I82: 철근콘크리트 | J82: 0.15 | K82: 시멘트몰탈 | L82: 0.03 | U82: Korean Energy Saving Design Standards (derived) | V82: =H82+J82+L82+N82+P82+R82+T82 -> 0.258 | AA82: ="[" & _xludf.TEXTJOIN(",",TRUE,G82:T82) & "]" -> #NAME? | AB82: {=IFERROR(J82/_xludf.XLOOKUP(I82,Materials!$A$3:$A$292,Materials!$I$3:$I$292),0) +IFERROR(L82/_xludf.XLOOKUP(K82,Materials!$A$3:$A$292,Materials!$I$3:$I$292),0) +IFERROR(N82/_xludf.XLOOKUP(M82,Materials!$A$3:$A$292,Materials!$I$3:$I$292),0) +IFERROR(P82/_xludf.XLOOKUP(O82,Materials!$A$3:$A$292,Materials!$I$3:$I$292),0) +IFERROR(R82/_xludf.XLOOKUP(Q82,Materials!$A$3:$A$292,Materials!$I$3:$I$292),0) +IFERROR(H82/_xludf.XLOOKUP(G82,Materials!$A$3:$A$292,Materials!$I$3:$I$292),0)} -> 0
A83: KR_office_small_2011_2018 | B83: GroundSlab | C83: 지면접촉 바닥 | D83: =AA83 -> #NAME? | E83: =IFERROR(1/AB83, "Not enough information entered") -> Not enough information entered | F83: KR_office_small_2011_2018_GroundSlab | G83: 압출법단열재(XPS) | H83: 0.077 | I83: 철근콘크리트 | J83: 0.18 | K83: 시멘트몰탈 | L83: 0.03 | U83: Korean Energy Saving Design Standards (derived) | V83: =H83+J83+L83+N83+P83+R83+T83 -> 0.287 | W83: 0 | X83: 0 | Y83: 10 | AA83: ="[" & _xludf.TEXTJOIN(",",TRUE,G83:T83) & "]" -> #NAME? | AB83: {=IFERROR(J83/_xludf.XLOOKUP(I83,Materials!$A$3:$A$292,Materials!$I$3:$I$292),0) +IFERROR(L83/_xludf.XLOOKUP(K83,Materials!$A$3:$A$292,Materials!$I$3:$I$292),0) +IFERROR(N83/_xludf.XLOOKUP(M83,Materials!$A$3:$A$292,Materials!$I$3:$I$292),0) +IFERROR(P83/_xludf.XLOOKUP(O83,Materials!$A$3:$A$292,Materials!$I$3:$I$292),0) +IFERROR(R83/_xludf.XLOOKUP(Q83,Materials!$A$3:$A$292,Materials!$I$3:$I$292),0) +IFERROR(H83/_xludf.XLOOKUP(G83,Materials!$A$3:$A$292,Materials!$I$3:$I$292),0)} -> 0
A84: KR_office_small_post2019 | B84: Facade | C84: 외벽(외피) | D84: =AA84 -> #NAME? | E84: =IFERROR(1/AB84, "Not enough information entered") -> Not enough information entered | F84: KR_office_small_post2019_Facade | G84: 압출법단열재(XPS) | H84: 0.069 | I84: 철근콘크리트 | J84: 0.18 | K84: 공기층(비통기) | L84: 0.02 | M84: 석고보드 | N84: 0.012 | U84: Korean Energy Saving Design Standards (derived) | V84: =H84+J84+L84+N84+P84+R84+T84 -> 0.281 | W84: 0 | X84: 0 | Y84: 10 | AA84: ="[" & _xludf.TEXTJOIN(",",TRUE,G84:T84) & "]" -> #NAME? | AB84: {=IFERROR(J84/_xludf.XLOOKUP(I84,Materials!$A$3:$A$292,Materials!$I$3:$I$292),0) +IFERROR(L84/_xludf.XLOOKUP(K84,Materials!$A$3:$A$292,Materials!$I$3:$I$292),0) +IFERROR(N84/_xludf.XLOOKUP(M84,Materials!$A$3:$A$292,Materials!$I$3:$I$292),0) +IFERROR(P84/_xludf.XLOOKUP(O84,Materials!$A$3:$A$292,Materials!$I$3:$I$292),0) +IFERROR(R84/_xludf.XLOOKUP(Q84,Materials!$A$3:$A$292,Materials!$I$3:$I$292),0) +IFERROR(H84/_xludf.XLOOKUP(G84,Materials!$A$3:$A$292,Materials!$I$3:$I$292),0)} -> 0
A85: KR_office_small_post2019 | B85: FlatRoof | C85: 지붕(평지붕) | D85: =AA85 -> #NAME? | E85: =IFERROR(1/AB85, "Not enough information entered") -> Not enough information entered | F85: KR_office_small_post2019_FlatRoof | G85: 압출법단열재(XPS) | H85: 0.094 | I85: 철근콘크리트 | J85: 0.15 | K85: 시멘트몰탈 | L85: 0.03 | U85: Korean Energy Saving Design Standards (derived) | V85: =H85+J85+L85+N85+P85+R85+T85 -> 0.274 | AA85: ="[" & _xludf.TEXTJOIN(",",TRUE,G85:T85) & "]" -> #NAME? | AB85: {=IFERROR(J85/_xludf.XLOOKUP(I85,Materials!$A$3:$A$292,Materials!$I$3:$I$292),0) +IFERROR(L85/_xludf.XLOOKUP(K85,Materials!$A$3:$A$292,Materials!$I$3:$I$292),0) +IFERROR(N85/_xludf.XLOOKUP(M85,Materials!$A$3:$A$292,Materials!$I$3:$I$292),0) +IFERROR(P85/_xludf.XLOOKUP(O85,Materials!$A$3:$A$292,Materials!$I$3:$I$292),0) +IFERROR(R85/_xludf.XLOOKUP(Q85,Materials!$A$3:$A$292,Materials!$I$3:$I$292),0) +IFERROR(H85/_xludf.XLOOKUP(G85,Materials!$A$3:$A$292,Materials!$I$3:$I$292),0)} -> 0
A86: KR_office_small_post2019 | B86: GroundSlab | C86: 지면접촉 바닥 | D86: =AA86 -> #NAME? | E86: =IFERROR(1/AB86, "Not enough information entered") -> Not enough information entered | F86: KR_office_small_post2019_GroundSlab | G86: 압출법단열재(XPS) | H86: 0.093 | I86: 철근콘크리트 | J86: 0.18 | K86: 시멘트몰탈 | L86: 0.03 | U86: Korean Energy Saving Design Standards (derived) | V86: =H86+J86+L86+N86+P86+R86+T86 -> 0.303 | W86: 0 | X86: 0 | Y86: 10 | AA86: ="[" & _xludf.TEXTJOIN(",",TRUE,G86:T86) & "]" -> #NAME? | AB86: {=IFERROR(J86/_xludf.XLOOKUP(I86,Materials!$A$3:$A$292,Materials!$I$3:$I$292),0) +IFERROR(L86/_xludf.XLOOKUP(K86,Materials!$A$3:$A$292,Materials!$I$3:$I$292),0) +IFERROR(N86/_xludf.XLOOKUP(M86,Materials!$A$3:$A$292,Materials!$I$3:$I$292),0) +IFERROR(P86/_xludf.XLOOKUP(O86,Materials!$A$3:$A$292,Materials!$I$3:$I$292),0) +IFERROR(R86/_xludf.XLOOKUP(Q86,Materials!$A$3:$A$292,Materials!$I$3:$I$292),0) +IFERROR(H86/_xludf.XLOOKUP(G86,Materials!$A$3:$A$292,Materials!$I$3:$I$292),0)} -> 0
A87: KR_office_small | B87: Partition | C87: Partition (연식 무관) | D87: =AA87 -> #NAME? | E87: =IFERROR(1/AB87, "Not enough information entered") -> Not enough information entered | F87: KR_office_small_Partition | G87: 석고보드 | H87: 0.0125 | I87: 공기층(비통기) | J87: 0.05 | K87: 석고보드 | L87: 0.0125 | U87: Korean Energy Saving Design Standards (derived) | V87: =H87+J87+L87+N87+P87+R87+T87 -> 0.075 | AA87: ="[" & _xludf.TEXTJOIN(",",TRUE,G87:T87) & "]" -> #NAME? | AB87: {=IFERROR(J87/_xludf.XLOOKUP(I87,Materials!$A$3:$A$292,Materials!$I$3:$I$292),0) +IFERROR(L87/_xludf.XLOOKUP(K87,Materials!$A$3:$A$292,Materials!$I$3:$I$292),0) +IFERROR(N87/_xludf.XLOOKUP(M87,Materials!$A$3:$A$292,Materials!$I$3:$I$292),0) +IFERROR(P87/_xludf.XLOOKUP(O87,Materials!$A$3:$A$292,Materials!$I$3:$I$292),0) +IFERROR(R87/_xludf.XLOOKUP(Q87,Materials!$A$3:$A$292,Materials!$I$3:$I$292),0) +IFERROR(H87/_xludf.XLOOKUP(G87,Materials!$A$3:$A$292,Materials!$I$3:$I$292),0)} -> 0
A88: KR_office_small | B88: FloorCeiling | C88: FloorCeiling (연식 무관) | D88: =AA88 -> #NAME? | E88: =IFERROR(1/AB88, "Not enough information entered") -> Not enough information entered | F88: KR_office_small_FloorCeiling | G88: 철근콘크리트 | H88: 0.18 | I88: 시멘트몰탈 | J88: 0.03 | U88: Korean Energy Saving Design Standards (derived) | V88: =H88+J88+L88+N88+P88+R88+T88 -> 0.21 | AA88: ="[" & _xludf.TEXTJOIN(",",TRUE,G88:T88) & "]" -> #NAME? | AB88: {=IFERROR(J88/_xludf.XLOOKUP(I88,Materials!$A$3:$A$292,Materials!$I$3:$I$292),0) +IFERROR(L88/_xludf.XLOOKUP(K88,Materials!$A$3:$A$292,Materials!$I$3:$I$292),0) +IFERROR(N88/_xludf.XLOOKUP(M88,Materials!$A$3:$A$292,Materials!$I$3:$I$292),0) +IFERROR(P88/_xludf.XLOOKUP(O88,Materials!$A$3:$A$292,Materials!$I$3:$I$292),0) +IFERROR(R88/_xludf.XLOOKUP(Q88,Materials!$A$3:$A$292,Materials!$I$3:$I$292),0) +IFERROR(H88/_xludf.XLOOKUP(G88,Materials!$A$3:$A$292,Materials!$I$3:$I$292),0)} -> 0
A89: KR_office_small | B89: GroundWall | C89: GroundWall (연식 무관) | D89: =AA89 -> #NAME? | E89: =IFERROR(1/AB89, "Not enough information entered") -> Not enough information entered | F89: KR_office_small_GroundWall | G89: 철근콘크리트 | H89: 0.2 | I89: 압출법단열재(XPS) | J89: 0.05 | U89: Korean Energy Saving Design Standards (derived) | V89: =H89+J89+L89+N89+P89+R89+T89 -> 0.25 | AA89: ="[" & _xludf.TEXTJOIN(",",TRUE,G89:T89) & "]" -> #NAME? | AB89: {=IFERROR(J89/_xludf.XLOOKUP(I89,Materials!$A$3:$A$292,Materials!$I$3:$I$292),0) +IFERROR(L89/_xludf.XLOOKUP(K89,Materials!$A$3:$A$292,Materials!$I$3:$I$292),0) +IFERROR(N89/_xludf.XLOOKUP(M89,Materials!$A$3:$A$292,Materials!$I$3:$I$292),0) +IFERROR(P89/_xludf.XLOOKUP(O89,Materials!$A$3:$A$292,Materials!$I$3:$I$292),0) +IFERROR(R89/_xludf.XLOOKUP(Q89,Materials!$A$3:$A$292,Materials!$I$3:$I$292),0) +IFERROR(H89/_xludf.XLOOKUP(G89,Materials!$A$3:$A$292,Materials!$I$3:$I$292),0)} -> 0
C90: InternalMass (연식 무관)
A91: KR_office_small | B91: BasementCeiling | C91: BasementCeiling (연식 무관) | D91: =AA91 -> #NAME? | E91: =IFERROR(1/AB91, "Not enough information entered") -> Not enough information entered | F91: KR_office_small_BasementCeiling | G91: 철근콘크리트 | H91: 0.18 | I91: 비드법단열재(EPS) | J91: 0.06 | K91: 석고보드 | L91: 0.0125 | U91: Korean Energy Saving Design Standards (derived) | V91: =H91+J91+L91+N91+P91+R91+T91 -> 0.2525 | AA91: ="[" & _xludf.TEXTJOIN(",",TRUE,G91:T91) & "]" -> #NAME? | AB91: {=IFERROR(J91/_xludf.XLOOKUP(I91,Materials!$A$3:$A$292,Materials!$I$3:$I$292),0) +IFERROR(L91/_xludf.XLOOKUP(K91,Materials!$A$3:$A$292,Materials!$I$3:$I$292),0) +IFERROR(N91/_xludf.XLOOKUP(M91,Materials!$A$3:$A$292,Materials!$I$3:$I$292),0) +IFERROR(P91/_xludf.XLOOKUP(O91,Materials!$A$3:$A$292,Materials!$I$3:$I$292),0) +IFERROR(R91/_xludf.XLOOKUP(Q91,Materials!$A$3:$A$292,Materials!$I$3:$I$292),0) +IFERROR(H91/_xludf.XLOOKUP(G91,Materials!$A$3:$A$292,Materials!$I$3:$I$292),0)} -> 0
A92: KR_office_medium_pre1988 | B92: Facade | C92: 외벽(외피) | D92: =AA92 -> #NAME? | E92: =IFERROR(1/AB92, "Not enough information entered") -> Not enough information entered | F92: KR_office_medium_pre1988_Facade | G92: 철근콘크리트 | H92: 0.18 | I92: 공기층(비통기) | J92: 0.02 | K92: 석고보드 | L92: 0.012 | U92: Korean Energy Saving Design Standards (derived) | V92: =H92+J92+L92+N92+P92+R92+T92 -> 0.212 | W92: 0 | X92: 0 | Y92: 10 | AA92: ="[" & _xludf.TEXTJOIN(",",TRUE,G92:T92) & "]" -> #NAME? | AB92: {=IFERROR(J92/_xludf.XLOOKUP(I92,Materials!$A$3:$A$292,Materials!$I$3:$I$292),0) +IFERROR(L92/_xludf.XLOOKUP(K92,Materials!$A$3:$A$292,Materials!$I$3:$I$292),0) +IFERROR(N92/_xludf.XLOOKUP(M92,Materials!$A$3:$A$292,Materials!$I$3:$I$292),0) +IFERROR(P92/_xludf.XLOOKUP(O92,Materials!$A$3:$A$292,Materials!$I$3:$I$292),0) +IFERROR(R92/_xludf.XLOOKUP(Q92,Materials!$A$3:$A$292,Materials!$I$3:$I$292),0) +IFERROR(H92/_xludf.XLOOKUP(G92,Materials!$A$3:$A$292,Materials!$I$3:$I$292),0)} -> 0
A93: KR_office_medium_pre1988 | B93: FlatRoof | C93: 지붕(평지붕) | D93: =AA93 -> #NAME? | E93: =IFERROR(1/AB93, "Not enough information entered") -> Not enough information entered | F93: KR_office_medium_pre1988_FlatRoof | G93: 철근콘크리트 | H93: 0.15 | I93: 시멘트몰탈 | J93: 0.03 | U93: Korean Energy Saving Design Standards (derived) | V93: =H93+J93+L93+N93+P93+R93+T93 -> 0.18 | AA93: ="[" & _xludf.TEXTJOIN(",",TRUE,G93:T93) & "]" -> #NAME? | AB93: {=IFERROR(J93/_xludf.XLOOKUP(I93,Materials!$A$3:$A$292,Materials!$I$3:$I$292),0) +IFERROR(L93/_xludf.XLOOKUP(K93,Materials!$A$3:$A$292,Materials!$I$3:$I$292),0) +IFERROR(N93/_xludf.XLOOKUP(M93,Materials!$A$3:$A$292,Materials!$I$3:$I$292),0) +IFERROR(P93/_xludf.XLOOKUP(O93,Materials!$A$3:$A$292,Materials!$I$3:$I$292),0) +IFERROR(R93/_xludf.XLOOKUP(Q93,Materials!$A$3:$A$292,Materials!$I$3:$I$292),0) +IFERROR(H93/_xludf.XLOOKUP(G93,Materials!$A$3:$A$292,Materials!$I$3:$I$292),0)} -> 0
A94: KR_office_medium_pre1988 | B94: GroundSlab | C94: 지면접촉 바닥 | D94: =AA94 -> #NAME? | E94: =IFERROR(1/AB94, "Not enough information entered") -> Not enough information entered | F94: KR_office_medium_pre1988_GroundSlab | G94: 철근콘크리트 | H94: 0.18 | I94: 시멘트몰탈 | J94: 0.03 | U94: Korean Energy Saving Design Standards (derived) | V94: =H94+J94+L94+N94+P94+R94+T94 -> 0.21 | W94: 0 | X94: 0 | Y94: 10 | AA94: ="[" & _xludf.TEXTJOIN(",",TRUE,G94:T94) & "]" -> #NAME? | AB94: {=IFERROR(J94/_xludf.XLOOKUP(I94,Materials!$A$3:$A$292,Materials!$I$3:$I$292),0) +IFERROR(L94/_xludf.XLOOKUP(K94,Materials!$A$3:$A$292,Materials!$I$3:$I$292),0) +IFERROR(N94/_xludf.XLOOKUP(M94,Materials!$A$3:$A$292,Materials!$I$3:$I$292),0) +IFERROR(P94/_xludf.XLOOKUP(O94,Materials!$A$3:$A$292,Materials!$I$3:$I$292),0) +IFERROR(R94/_xludf.XLOOKUP(Q94,Materials!$A$3:$A$292,Materials!$I$3:$I$292),0) +IFERROR(H94/_xludf.XLOOKUP(G94,Materials!$A$3:$A$292,Materials!$I$3:$I$292),0)} -> 0
A95: KR_office_medium_1988_2000 | B95: Facade | C95: 외벽(외피) | D95: =AA95 -> #NAME? | E95: =IFERROR(1/AB95, "Not enough information entered") -> Not enough information entered | F95: KR_office_medium_1988_2000_Facade | G95: 압출법단열재(XPS) | H95: 0.03 | I95: 철근콘크리트 | J95: 0.18 | K95: 공기층(비통기) | L95: 0.02 | M95: 석고보드 | N95: 0.012 | U95: Korean Energy Saving Design Standards (derived) | V95: =H95+J95+L95+N95+P95+R95+T95 -> 0.242 | W95: 0 | X95: 0 | Y95: 10 | AA95: ="[" & _xludf.TEXTJOIN(",",TRUE,G95:T95) & "]" -> #NAME? | AB95: {=IFERROR(J95/_xludf.XLOOKUP(I95,Materials!$A$3:$A$292,Materials!$I$3:$I$292),0) +IFERROR(L95/_xludf.XLOOKUP(K95,Materials!$A$3:$A$292,Materials!$I$3:$I$292),0) +IFERROR(N95/_xludf.XLOOKUP(M95,Materials!$A$3:$A$292,Materials!$I$3:$I$292),0) +IFERROR(P95/_xludf.XLOOKUP(O95,Materials!$A$3:$A$292,Materials!$I$3:$I$292),0) +IFERROR(R95/_xludf.XLOOKUP(Q95,Materials!$A$3:$A$292,Materials!$I$3:$I$292),0) +IFERROR(H95/_xludf.XLOOKUP(G95,Materials!$A$3:$A$292,Materials!$I$3:$I$292),0)} -> 0
A96: KR_office_medium_1988_2000 | B96: FlatRoof | C96: 지붕(평지붕) | D96: =AA96 -> #NAME? | E96: =IFERROR(1/AB96, "Not enough information entered") -> Not enough information entered | F96: KR_office_medium_1988_2000_FlatRoof | G96: 압출법단열재(XPS) | H96: 0.058 | I96: 철근콘크리트 | J96: 0.15 | K96: 시멘트몰탈 | L96: 0.03 | U96: Korean Energy Saving Design Standards (derived) | V96: =H96+J96+L96+N96+P96+R96+T96 -> 0.238 | AA96: ="[" & _xludf.TEXTJOIN(",",TRUE,G96:T96) & "]" -> #NAME? | AB96: {=IFERROR(J96/_xludf.XLOOKUP(I96,Materials!$A$3:$A$292,Materials!$I$3:$I$292),0) +IFERROR(L96/_xludf.XLOOKUP(K96,Materials!$A$3:$A$292,Materials!$I$3:$I$292),0) +IFERROR(N96/_xludf.XLOOKUP(M96,Materials!$A$3:$A$292,Materials!$I$3:$I$292),0) +IFERROR(P96/_xludf.XLOOKUP(O96,Materials!$A$3:$A$292,Materials!$I$3:$I$292),0) +IFERROR(R96/_xludf.XLOOKUP(Q96,Materials!$A$3:$A$292,Materials!$I$3:$I$292),0) +IFERROR(H96/_xludf.XLOOKUP(G96,Materials!$A$3:$A$292,Materials!$I$3:$I$292),0)} -> 0
A97: KR_office_medium_1988_2000 | B97: GroundSlab | C97: 지면접촉 바닥 | D97: =AA97 -> #NAME? | E97: =IFERROR(1/AB97, "Not enough information entered") -> Not enough information entered | F97: KR_office_medium_1988_2000_GroundSlab | G97: 압출법단열재(XPS) | H97: 0.047 | I97: 철근콘크리트 | J97: 0.18 | K97: 시멘트몰탈 | L97: 0.03 | U97: Korean Energy Saving Design Standards (derived) | V97: =H97+J97+L97+N97+P97+R97+T97 -> 0.257 | W97: 0 | X97: 0 | Y97: 10 | AA97: ="[" & _xludf.TEXTJOIN(",",TRUE,G97:T97) & "]" -> #NAME? | AB97: {=IFERROR(J97/_xludf.XLOOKUP(I97,Materials!$A$3:$A$292,Materials!$I$3:$I$292),0) +IFERROR(L97/_xludf.XLOOKUP(K97,Materials!$A$3:$A$292,Materials!$I$3:$I$292),0) +IFERROR(N97/_xludf.XLOOKUP(M97,Materials!$A$3:$A$292,Materials!$I$3:$I$292),0) +IFERROR(P97/_xludf.XLOOKUP(O97,Materials!$A$3:$A$292,Materials!$I$3:$I$292),0) +IFERROR(R97/_xludf.XLOOKUP(Q97,Materials!$A$3:$A$292,Materials!$I$3:$I$292),0) +IFERROR(H97/_xludf.XLOOKUP(G97,Materials!$A$3:$A$292,Materials!$I$3:$I$292),0)} -> 0
A98: KR_office_medium_2001_2010 | B98: Facade | C98: 외벽(외피) | D98: =AA98 -> #NAME? | E98: =IFERROR(1/AB98, "Not enough information entered") -> Not enough information entered | F98: KR_office_medium_2001_2010_Facade | G98: 압출법단열재(XPS) | H98: 0.04 | I98: 철근콘크리트 | J98: 0.18 | K98: 공기층(비통기) | L98: 0.02 | M98: 석고보드 | N98: 0.012 | U98: Korean Energy Saving Design Standards (derived) | V98: =H98+J98+L98+N98+P98+R98+T98 -> 0.252 | W98: 0 | X98: 0 | Y98: 10 | AA98: ="[" & _xludf.TEXTJOIN(",",TRUE,G98:T98) & "]" -> #NAME? | AB98: {=IFERROR(J98/_xludf.XLOOKUP(I98,Materials!$A$3:$A$292,Materials!$I$3:$I$292),0) +IFERROR(L98/_xludf.XLOOKUP(K98,Materials!$A$3:$A$292,Materials!$I$3:$I$292),0) +IFERROR(N98/_xludf.XLOOKUP(M98,Materials!$A$3:$A$292,Materials!$I$3:$I$292),0) +IFERROR(P98/_xludf.XLOOKUP(O98,Materials!$A$3:$A$292,Materials!$I$3:$I$292),0) +IFERROR(R98/_xludf.XLOOKUP(Q98,Materials!$A$3:$A$292,Materials!$I$3:$I$292),0) +IFERROR(H98/_xludf.XLOOKUP(G98,Materials!$A$3:$A$292,Materials!$I$3:$I$292),0)} -> 0
A99: KR_office_medium_2001_2010 | B99: FlatRoof | C99: 지붕(평지붕) | D99: =AA99 -> #NAME? | E99: =IFERROR(1/AB99, "Not enough information entered") -> Not enough information entered | F99: KR_office_medium_2001_2010_FlatRoof | G99: 압출법단열재(XPS) | H99: 0.059 | I99: 철근콘크리트 | J99: 0.15 | K99: 시멘트몰탈 | L99: 0.03 | U99: Korean Energy Saving Design Standards (derived) | V99: =H99+J99+L99+N99+P99+R99+T99 -> 0.239 | AA99: ="[" & _xludf.TEXTJOIN(",",TRUE,G99:T99) & "]" -> #NAME? | AB99: {=IFERROR(J99/_xludf.XLOOKUP(I99,Materials!$A$3:$A$292,Materials!$I$3:$I$292),0) +IFERROR(L99/_xludf.XLOOKUP(K99,Materials!$A$3:$A$292,Materials!$I$3:$I$292),0) +IFERROR(N99/_xludf.XLOOKUP(M99,Materials!$A$3:$A$292,Materials!$I$3:$I$292),0) +IFERROR(P99/_xludf.XLOOKUP(O99,Materials!$A$3:$A$292,Materials!$I$3:$I$292),0) +IFERROR(R99/_xludf.XLOOKUP(Q99,Materials!$A$3:$A$292,Materials!$I$3:$I$292),0) +IFERROR(H99/_xludf.XLOOKUP(G99,Materials!$A$3:$A$292,Materials!$I$3:$I$292),0)} -> 0
A100: KR_office_medium_2001_2010 | B100: GroundSlab | C100: 지면접촉 바닥 | D100: =AA100 -> #NAME? | E100: =IFERROR(1/AB100, "Not enough information entered") -> Not enough information entered | F100: KR_office_medium_2001_2010_GroundSlab | G100: 압출법단열재(XPS) | H100: 0.058 | I100: 철근콘크리트 | J100: 0.18 | K100: 시멘트몰탈 | L100: 0.03 | U100: Korean Energy Saving Design Standards (derived) | V100: =H100+J100+L100+N100+P100+R100+T100 -> 0.268 | W100: 0 | X100: 0 | Y100: 10 | AA100: ="[" & _xludf.TEXTJOIN(",",TRUE,G100:T100) & "]" -> #NAME? | AB100: {=IFERROR(J100/_xludf.XLOOKUP(I100,Materials!$A$3:$A$292,Materials!$I$3:$I$292),0) +IFERROR(L100/_xludf.XLOOKUP(K100,Materials!$A$3:$A$292,Materials!$I$3:$I$292),0) +IFERROR(N100/_xludf.XLOOKUP(M100,Materials!$A$3:$A$292,Materials!$I$3:$I$292),0) +IFERROR(P100/_xludf.XLOOKUP(O100,Materials!$A$3:$A$292,Materials!$I$3:$I$292),0) +IFERROR(R100/_xludf.XLOOKUP(Q100,Materials!$A$3:$A$292,Materials!$I$3:$I$292),0) +IFERROR(H100/_xludf.XLOOKUP(G100,Materials!$A$3:$A$292,Materials!$I$3:$I$292),0)} -> 0
...

Sheet Infiltration_components
A2: Base_name | B2: Name | C2: Infiltration | D2: InfiltrationZone | E2: Infiltration_unit
A3: KR_res_sf_LeakyEnvelope | B3: KR_res_sf_LeakyEnvelope_Main | C3: 0.5 | D3: Main | E3: AirChanges/Hour
A4: KR_res_sf_SomewhatLeakyEnvelope | B4: KR_res_sf_SomewhatLeakyEnvelope_Main | C4: 0.3 | D4: Main | E4: AirChanges/Hour
A5: KR_res_sf_TightEnvelope | B5: KR_res_sf_TightEnvelope_Main | C5: 0.2 | D5: Main | E5: AirChanges/Hour
A6: KR_res_sf_TightEnvelopeHRV | B6: KR_res_sf_TightEnvelopeHRV_Main | C6: 0.1 | D6: Main | E6: AirChanges/Hour
A7: KR_res_mf_low_LeakyEnvelope | B7: KR_res_mf_low_LeakyEnvelope_Main | C7: 0.35 | D7: Main | E7: AirChanges/Hour
A8: KR_res_mf_low_SomewhatLeakyEnvelope | B8: KR_res_mf_low_SomewhatLeakyEnvelope_Main | C8: 0.25 | D8: Main | E8: AirChanges/Hour
A9: KR_res_mf_low_TightEnvelope | B9: KR_res_mf_low_TightEnvelope_Main | C9: 0.15 | D9: Main | E9: AirChanges/Hour
A10: KR_res_mf_low_TightEnvelopeHRV | B10: KR_res_mf_low_TightEnvelopeHRV_Main | C10: 0.1 | D10: Main | E10: AirChanges/Hour
A11: KR_res_mf_high_LeakyEnvelope | B11: KR_res_mf_high_LeakyEnvelope_Main | C11: 0.3 | D11: Main | E11: AirChanges/Hour
A12: KR_res_mf_high_SomewhatLeakyEnvelope | B12: KR_res_mf_high_SomewhatLeakyEnvelope_Main | C12: 0.2 | D12: Main | E12: AirChanges/Hour
A13: KR_res_mf_high_TightEnvelope | B13: KR_res_mf_high_TightEnvelope_Main | C13: 0.12 | D13: Main | E13: AirChanges/Hour
A14: KR_res_mf_high_TightEnvelopeHRV | B14: KR_res_mf_high_TightEnvelopeHRV_Main | C14: 0.08 | D14: Main | E14: AirChanges/Hour
... A106: KR_etc_TightEnvelope | B106: KR_etc_TightEnvelope_Main | C106: 0.1006 | D106: Main | E106: AirChanges/Hour

Sheet Construction_assembly
A2: Name | B2: InternalMassFraction | C2: InternalMass | D2: Partition | E2: FlatRoof | F2: Facade | G2: FloorCeiling | H2: ExternalFloor | I2: GroundSlab | J2: GroundWall | K2: BasementCeiling | L2: AtticRoof | M2: AtticFloor
A3: KR_res_sf_pre1988 | B3: 0.3 | C3: KR_res_sf_InternalMass | D3: KR_res_sf_Partition | E3: KR_res_sf_pre1988_FlatRoof | F3: KR_res_sf_pre1988_Facade | G3: KR_res_sf_FloorCeiling | H3: KR_ExternalFloor | I3: KR_res_sf_pre1988_GroundSlab | J3: KR_res_sf_GroundWall | K3: KR_res_sf_BasementCeiling | L3: KR_res_sf_pre1988_AtticRoof | M3: KR_AtticFloor
A4: KR_res_sf_1988_2000 | B4: 0.3 | C4: KR_res_sf_InternalMass | D4: KR_res_sf_Partition | E4: KR_res_sf_1988_2000_FlatRoof | F4: KR_res_sf_1988_2000_Facade | G4: KR_res_sf_FloorCeiling | H4: KR_ExternalFloor | I4: KR_res_sf_1988_2000_GroundSlab | J4: KR_res_sf_GroundWall | K4: KR_res_sf_BasementCeiling | L4: KR_res_sf_1988_2000_AtticRoof | M4: KR_AtticFloor
A5: KR_res_sf_2001_2010 | B5: 0.3 | C5: KR_res_sf_InternalMass | D5: KR_res_sf_Partition | E5: KR_res_sf_2001_2010_FlatRoof | F5: KR_res_sf_2001_2010_Facade | G5: KR_res_sf_FloorCeiling | H5: KR_ExternalFloor | I5: KR_res_sf_2001_2010_GroundSlab | J5: KR_res_sf_GroundWall | K5: KR_res_sf_BasementCeiling | L5: KR_res_sf_2001_2010_AtticRoof | M5: KR_AtticFloor
A6: KR_res_sf_2011_2018 | B6: 0.3 | C6: KR_res_sf_InternalMass | D6: KR_res_sf_Partition | E6: KR_res_sf_2011_2018_FlatRoof | F6: KR_res_sf_2011_2018_Facade | G6: KR_res_sf_FloorCeiling | H6: KR_ExternalFloor | I6: KR_res_sf_2011_2018_GroundSlab | J6: KR_res_sf_GroundWall | K6: KR_res_sf_BasementCeiling | L6: KR_res_sf_2011_2018_AtticRoof | M6: KR_AtticFloor
A7: KR_res_sf_post2019 | B7: 0.3 | C7: KR_res_sf_InternalMass | D7: KR_res_sf_Partition | E7: KR_res_sf_post2019_FlatRoof | F7: KR_res_sf_post2019_Facade | G7: KR_res_sf_FloorCeiling | H7: KR_ExternalFloor | I7: KR_res_sf_post2019_GroundSlab | J7: KR_res_sf_GroundWall | K7: KR_res_sf_BasementCeiling | L7: KR_res_sf_post2019_AtticRoof | M7: KR_AtticFloor
A8: KR_res_mf_low_pre1988 | B8: 0.3 | C8: KR_res_mf_low_InternalMass | D8: KR_res_mf_low_Partition | E8: KR_res_mf_low_pre1988_FlatRoof | F8: KR_res_mf_low_pre1988_Facade | G8: KR_res_mf_low_FloorCeiling | H8: KR_ExternalFloor | I8: KR_res_mf_low_pre1988_GroundSlab | J8: KR_res_mf_low_GroundWall | K8: KR_res_mf_low_BasementCeiling | L8: KR_res_mf_low_pre1988_AtticRoof | M8: KR_AtticFloor
A9: KR_res_mf_low_1988_2000 | B9: 0.3 | C9: KR_res_mf_low_InternalMass | D9: KR_res_mf_low_Partition | E9: KR_res_mf_low_1988_2000_FlatRoof | F9: KR_res_mf_low_1988_2000_Facade | G9: KR_res_mf_low_FloorCeiling | H9: KR_ExternalFloor | I9: KR_res_mf_low_1988_2000_GroundSlab | J9: KR_res_mf_low_GroundWall | K9: KR_res_mf_low_BasementCeiling | L9: KR_res_mf_low_1988_2000_AtticRoof | M9: KR_AtticFloor
A10: KR_res_mf_low_2001_2010 | B10: 0.3 | C10: KR_res_mf_low_InternalMass | D10: KR_res_mf_low_Partition | E10: KR_res_mf_low_2001_2010_FlatRoof | F10: KR_res_mf_low_2001_2010_Facade | G10: KR_res_mf_low_FloorCeiling | H10: KR_ExternalFloor | I10: KR_res_mf_low_2001_2010_GroundSlab | J10: KR_res_mf_low_GroundWall | K10: KR_res_mf_low_BasementCeiling | L10: KR_res_mf_low_2001_2010_AtticRoof | M10: KR_AtticFloor
A11: KR_res_mf_low_2011_2018 | B11: 0.3 | C11: KR_res_mf_low_InternalMass | D11: KR_res_mf_low_Partition | E11: KR_res_mf_low_2011_2018_FlatRoof | F11: KR_res_mf_low_2011_2018_Facade | G11: KR_res_mf_low_FloorCeiling | H11: KR_ExternalFloor | I11: KR_res_mf_low_2011_2018_GroundSlab | J11: KR_res_mf_low_GroundWall | K11: KR_res_mf_low_BasementCeiling | L11: KR_res_mf_low_2011_2018_AtticRoof | M11: KR_AtticFloor
A12: KR_res_mf_low_post2019 | B12: 0.3 | C12: KR_res_mf_low_InternalMass | D12: KR_res_mf_low_Partition | E12: KR_res_mf_low_post2019_FlatRoof | F12: KR_res_mf_low_post2019_Facade | G12: KR_res_mf_low_FloorCeiling | H12: KR_ExternalFloor | I12: KR_res_mf_low_post2019_GroundSlab | J12: KR_res_mf_low_GroundWall | K12: KR_res_mf_low_BasementCeiling | L12: KR_res_mf_low_post2019_AtticRoof | M12: KR_AtticFloor
A13: KR_res_mf_high_pre1988 | B13: 0.3 | C13: KR_res_mf_high_InternalMass | D13: KR_res_mf_high_Partition | E13: KR_res_mf_high_pre1988_FlatRoof | F13: KR_res_mf_high_pre1988_Facade | G13: KR_res_mf_high_FloorCeiling | H13: KR_ExternalFloor | I13: KR_res_mf_high_pre1988_GroundSlab | J13: KR_res_mf_high_GroundWall | K13: KR_res_mf_high_BasementCeiling | L13: KR_res_mf_high_pre1988_AtticRoof | M13: KR_AtticFloor
A14: KR_res_mf_high_1988_2000 | B14: 0.3 | C14: KR_res_mf_high_InternalMass | D14: KR_res_mf_high_Partition | E14: KR_res_mf_high_1988_2000_FlatRoof | F14: KR_res_mf_high_1988_2000_Facade | G14: KR_res_mf_high_FloorCeiling | H14: KR_ExternalFloor | I14: KR_res_mf_high_1988_2000_GroundSlab | J14: KR_res_mf_high_GroundWall | K14: KR_res_mf_high_BasementCeiling | L14: KR_res_mf_high_1988_2000_AtticRoof | M14: KR_AtticFloor
... A92: KR_etc_post2019 | B92: 0 | C92: KR_etc_InternalMass | D92: KR_etc_Partition | E92: KR_etc_post2019_FlatRoof | F92: KR_etc_post2019_Facade | G92: KR_etc_FloorCeiling | H92: KR_ExternalFloor | I92: KR_etc_post2019_GroundSlab | J92: KR_etc_GroundWall | K92: KR_etc_BasementCeiling | L92: KR_etc_post2019_AtticRoof | M92: KR_AtticFloor
B93: 0
B94: 0
B95: 0
B96: 0
B97: 0
B98: 0
B99: 0
B100: 0
B101: 0
B102: 0
B103: 0
B104: 0
... B627: 0

Sheet Envelope_assembly
A1: Fill in the name of your chosen construction. This can be anything, but should be recognizable to you top assign to a template | B1: Choose from existing window constructions or make your own in the construction_components | C1: Enter the ACH_natural infiltration rate for this construction | E1: Flow per exterior surface area
A2: Name | B2: Windows | C2: Infiltration | D2: AtticInfiltration | E2: Construction

Sheet Schedules_assembly (OPT)>>>

Sheet EPD_calculator
A1: Enter a preferred name for the loads schedule you are building | B1: Include this set of 5 different load types for each component name | C1: Choose number of household appliances for that specific component. This needs to be a integer.
A2: Loads_component_name | B2: Equipment_type | C2: Type | D2: kWh_m2_year | E2: W_m2 | F2: Sensible_load_fraction | G2: Latent_load_fraction
A3: MA_SFH | B3: Refrigerator | C3: 1 | D3: 434 | E3: =D3/8760 -> 0.049543379 | F3: 1 | G3: 0
A4: MA_SFH | B4: Clothes washer | C4: 1 | D4: =C4*(38.8+12.9*0.016) -> 39.0064 | E4: =D4/350 -> 0.11144686 | F4: 0.8 | G4: 0
A5: MA_SFH | B5: Clothes dryer | C5: 1 | D5: =C5*(538.2+179.4*0.016) -> 541.0704 | E5: =D5/350 -> 1.5459154 | F5: 0.15 | G5: 0.05
A6: MA_SFH | B6: Dishwasher | C6: 1 | D6: =C6*(87.6 + 29.2*0.016) -> 88.0672 | E6: =D6/350 -> 0.25162057 | F6: 0.6 | G6: 0.15
A7: MA_SFH | B7: Range | C7: 1 | D7: =C7*(250+83*0.016) -> 251.328 | E7: =D7/350 -> 0.71808 | F7: 0.4 | G7: 0.3
A8: MA_SFH | B8: Misc. loads | C8: 1 | F8: 0.93 | G8: 0.02

Sheet Day_schedules
A1: Enter the preferred name of the schedule. This needs to be recognizable | B1: Choose between a fractional (0-100%) schedule or a temperature schedule | C1: Assign values to each hour within a 24 hr cycle for the schedule
A2: Day_schedule_name | B2: Type | C2: Hour0 | D2: Hour1 | E2: Hour2 | F2: Hour3 | G2: Hour4 | H2: Hour5 | I2: Hour6 | J2: Hour7 | K2: Hour8 | L2: Hour9 | M2: Hour10 | N2: Hour11 | O2: Hour12 | P2: Hour13 | Q2: Hour14 | R2: Hour15 | S2: Hour16 | T2: Hour17 | U2: Hour18 | V2: Hour19 | W2: Hour20 | X2: Hour21 | Y2: Hour22 | Z2: Hour23 | AA2: Hour24
A3: Office_Occupancy | B3: Fraction | C3: 0 | D3: 0 | E3: 0 | F3: 0 | G3: 0 | H3: 0 | I3: 0.1 | J3: 0.2 | K3: 0.95 | L3: 0.95 | M3: 0.95 | N3: 0.95 | O3: 0.5 | P3: 0.95 | Q3: 0.95 | R3: 0.95 | S3: 0.95 | T3: 0.3 | U3: 0.1 | V3: 0.1 | W3: 0.05 | X3: 0.05 | Y3: 0.05 | Z3: 0 | AA3: 0
A4: Office_Occupancy_Off | B4: Fraction | C4: 0 | D4: 0 | E4: 0 | F4: 0 | G4: 0 | H4: 0 | I4: 0 | J4: 0 | K4: 0 | L4: 0 | M4: 0 | N4: 0 | O4: 0 | P4: 0 | Q4: 0 | R4: 0 | S4: 0 | T4: 0 | U4: 0 | V4: 0 | W4: 0 | X4: 0 | Y4: 0 | Z4: 0 | AA4: 0
A5: Office_Lighting | B5: Fraction | C5: 0.05 | D5: 0.05 | E5: 0.05 | F5: 0.05 | G5: 0.05 | H5: 0.1 | I5: 0.3 | J5: 0.9 | K5: 0.9 | L5: 0.9 | M5: 0.9 | N5: 0.9 | O5: 0.9 | P5: 0.9 | Q5: 0.9 | R5: 0.9 | S5: 0.9 | T5: 0.5 | U5: 0.3 | V5: 0.2 | W5: 0.1 | X5: 0.1 | Y5: 0.05 | Z5: 0.05 | AA5: 0.05
A6: Office_Lighting_Off | B6: Fraction | C6: 0.05 | D6: 0.05 | E6: 0.05 | F6: 0.05 | G6: 0.05 | H6: 0.05 | I6: 0.05 | J6: 0.05 | K6: 0.05 | L6: 0.05 | M6: 0.05 | N6: 0.05 | O6: 0.05 | P6: 0.05 | Q6: 0.05 | R6: 0.05 | S6: 0.05 | T6: 0.05 | U6: 0.05 | V6: 0.05 | W6: 0.05 | X6: 0.05 | Y6: 0.05 | Z6: 0.05 | AA6: 0.05
A7: Office_Equipment | B7: Fraction | C7: 0.4 | D7: 0.4 | E7: 0.4 | F7: 0.4 | G7: 0.4 | H7: 0.4 | I7: 0.4 | J7: 0.9 | K7: 0.9 | L7: 0.9 | M7: 0.9 | N7: 0.9 | O7: 0.9 | P7: 0.9 | Q7: 0.9 | R7: 0.9 | S7: 0.9 | T7: 0.5 | U7: 0.4 | V7: 0.4 | W7: 0.4 | X7: 0.4 | Y7: 0.4 | Z7: 0.4 | AA7: 0.4
A8: Office_Equipment_Off | B8: Fraction | C8: 0.3 | D8: 0.3 | E8: 0.3 | F8: 0.3 | G8: 0.3 | H8: 0.3 | I8: 0.3 | J8: 0.3 | K8: 0.3 | L8: 0.3 | M8: 0.3 | N8: 0.3 | O8: 0.3 | P8: 0.3 | Q8: 0.3 | R8: 0.3 | S8: 0.3 | T8: 0.3 | U8: 0.3 | V8: 0.3 | W8: 0.3 | X8: 0.3 | Y8: 0.3 | Z8: 0.3 | AA8: 0.3
A9: Retail_Occupancy | B9: Fraction | C9: 0 | D9: 0 | E9: 0 | F9: 0 | G9: 0 | H9: 0 | I9: 0 | J9: 0.1 | K9: 0.2 | L9: 0.5 | M9: 0.8 | N9: 0.9 | O9: 1 | P9: 1 | Q9: 1 | R9: 1 | S9: 1 | T9: 0.9 | U9: 0.8 | V9: 0.6 | W9: 0.4 | X9: 0.2 | Y9: 0.1 | Z9: 0 | AA9: 0
A10: Retail_Lighting | B10: Fraction | C10: 0.05 | D10: 0.05 | E10: 0.05 | F10: 0.05 | G10: 0.05 | H10: 0.05 | I10: 0.1 | J10: 0.2 | K10: 0.5 | L10: 0.9 | M10: 1 | N10: 1 | O10: 1 | P10: 1 | Q10: 1 | R10: 1 | S10: 1 | T10: 1 | U10: 1 | V10: 1 | W10: 0.9 | X10: 0.5 | Y10: 0.1 | Z10: 0.05 | AA10: 0.05
A11: Retail_Equipment | B11: Fraction | C11: 0.1 | D11: 0.1 | E11: 0.1 | F11: 0.1 | G11: 0.1 | H11: 0.1 | I11: 0.1 | J11: 0.2 | K11: 0.6 | L11: 0.9 | M11: 1 | N11: 1 | O11: 1 | P11: 1 | Q11: 1 | R11: 1 | S11: 1 | T11: 1 | U11: 1 | V11: 1 | W11: 0.9 | X11: 0.6 | Y11: 0.2 | Z11: 0.1 | AA11: 0.1
A12: Residential_Occupancy | B12: Fraction | C12: 1 | D12: 1 | E12: 1 | F12: 1 | G12: 1 | H12: 1 | I12: 1 | J12: 0.8 | K12: 0.5 | L12: 0.2 | M12: 0.2 | N12: 0.2 | O12: 0.2 | P12: 0.2 | Q12: 0.2 | R12: 0.2 | S12: 0.3 | T12: 0.5 | U12: 0.7 | V12: 0.8 | W12: 0.9 | X12: 1 | Y12: 1 | Z12: 1 | AA12: 1
A13: Residential_Occupancy_Weekend | B13: Fraction | C13: 1 | D13: 1 | E13: 1 | F13: 1 | G13: 1 | H13: 1 | I13: 1 | J13: 0.9 | K13: 0.8 | L13: 0.7 | M13: 0.7 | N13: 0.7 | O13: 0.7 | P13: 0.7 | Q13: 0.7 | R13: 0.7 | S13: 0.8 | T13: 0.8 | U13: 0.9 | V13: 0.9 | W13: 1 | X13: 1 | Y13: 1 | Z13: 1 | AA13: 1
A14: Residential_Lighting | B14: Fraction | C14: 0.1 | D14: 0.1 | E14: 0.1 | F14: 0.1 | G14: 0.1 | H14: 0.2 | I14: 0.4 | J14: 0.5 | K14: 0.1 | L14: 0 | M14: 0 | N14: 0 | O14: 0 | P14: 0 | Q14: 0 | R14: 0 | S14: 0 | T14: 0.1 | U14: 0.4 | V14: 0.7 | W14: 0.9 | X14: 0.8 | Y14: 0.6 | Z14: 0.3 | AA14: 0.3
... A59: Window | B59: Fraction | C59: 0 | D59: 0 | E59: 0 | F59: 0 | G59: 0 | H59: 0 | I59: 0 | J59: 0 | K59: 0 | L59: 0 | M59: 0 | N59: 0 | O59: 0 | P59: 0 | Q59: 0 | R59: 0 | S59: 0 | T59: 0 | U59: 0 | V59: 0 | W59: 0 | X59: 0 | Y59: 0 | Z59: 0 | AA59: 0
B76: ASHRAE Standard 90.1의 DOE 프로토타입 모델의 스케줄 데이터 참고 | K76: Standard 90.1 User's Manual based on ANSI/ASHRAE/IES Standard 90.1-2016
B77: GloBI 용도 (Target) | C77: ASHRAE 원본 | D77: 매칭 및 생성 논리 (Rationale) | K77: page 453
B78: Office Large | C78: Large Office | D78: (1:1 매칭) 표준 업무 시간(09~18) 및 중앙 냉난방 패턴 적용 | K78: Table G-D. Acceptable occupant densities
B79: Office Medium | C79: Large Office | D79: (패턴 동일) 중형 사무실도 근무 시간 및 재실 패턴은 대형과 동일함
B80: Office Small | C80: Large Office | D80: (패턴 동일) 소형 사무실도 근무 시간은 동일함
B81: Retail Large | C81: Standalone Retail | D81: (1:1 매칭) 백화점/마트의 10시 오픈, 21시 마감, 주말 영업 패턴 적용
B82: Retail Medium | C82: Standalone Retail | D82: (패턴 동일) 일반 상점도 대형 점포와 운영 시간 및 주말 영업 특성 공유
B83: Retail Small | C83: Standalone Retail | D83: (패턴 동일) 편의점/소매점 등도 상업 시설 표준 스케줄 적용
B84: Residential | C84: Midrise Apartment | D84: (유사 매칭) 한국의 아파트/빌라와 가장 유사한 4~5층 규모 공동주택 모델 (M자형 패턴)
B85: School | C85: Secondary School | D85: (유사 매칭) 초/중/고교의 일반적인 등하교(08~16) 및 수업 패턴 반영
B86: Hospital | C86: Hospital | D86: (1:1 매칭) 24시간 365일 운영되는 종합병원 패턴 적용 (야간 부하 높음)
B87: Hotel | C87: Large Hotel | D87: (1:1 매칭) 24시간 투숙객 재실 및 로비/식당 등 공용부 운영 특성 반영
